Workbook

Sheet How to use
A1: Swansura keyword research — product pages
A2: Built 18 Oct 2026 from "Swansura_Vilvah_Deyga_Fragrance_Data_Sheet" (546 products: 159 Vilvah & Deyga, 387 fragrance). Keywords are generated from each product name plus real Google UK autocomplete suggestions (google.co.uk, en-GB, collected 18 Oct 2026).
A4: How to add search volumes (Semrush)
A5: 1. Open the "Semrush Batches" tab. Each column is one batch of up to 100 keywords, in priority order (Tier 1 first).
A6: 2. In Semrush go to Keyword Overview, set the database to United Kingdom, paste one batch and click Analyze.
A7: 3. Export the results (Excel/CSV), then paste the export INCLUDING its header row into the "Semrush Data" tab, starting at cell A1. Add later batches below the previous ones (skip their header rows).
A8: 4. Volume, Keyword Difficulty, CPC and Intent fill in automatically on "Products" and "Keyword List". "Primary keyword" picks the highest-volume variant for each product.
A9: Tip: Tier 1 alone (batches 1–9) covers every product's core keyword plus brand, category and concern terms — start there.
A11: Tiers
A12: Tier 1 — core product keyword (brand + product), brand terms, category and concern terms (e.g. "face wash for dry skin").
A13: Tier 2 — product + "uk", product + concentration (e.g. "... eau de parfum").
A14: Tier 3 — commercial modifiers ("buy ... online", "... price") and Google autocomplete suggestions.
... A28: Batches 10–38 were the original full plan and are greyed out as SKIPPED: the 324 useful keywords from them are in T2/T3; the other 2,527 (buy/price/uk/type variants and autocomplete for low-demand products) were left out because even top-100 "+ uk" variants had a median volume of 0.

Sheet Insights
A1: Semrush insights — UK, Tiers 1–3
A2: Figures are formulas over the "Semrush Data" tab (Semrush Keyword Overview, UK database: Tier 1 batches 1–9, Tier 2 T2-1 to T2-3, Tier 3 T3-1 to T3-2, Oct 2026). Volume = average monthly UK searches; KD = keyword difficulty 0–100; 0 / blank = no Semrush data.
A4: Summary
B5: Keywords checked in Semrush | D5: =COUNTA('Semrush Data'!A2:A5000) -> 1314
B6: Keywords with UK search volume | D6: =COUNTIF('Semrush Data'!C2:C5000,">0") -> 735
B7: Products whose primary keyword has volume | D7: =COUNTIF(Products!W2:W600,">0") -> 265
B8: …of which Vilvah & Deyga (of 159) | D8: =COUNTIFS(Products!B2:B600,"Vilvah & Deyga",Products!W2:W600,">0") -> 18
B9: …of which fragrance (of 387) | D9: =COUNTIFS(Products!B2:B600,"Fragrance Catalogue",Products!W2:W600,">0") -> 247
B10: Total monthly searches for product primary keywords | D10: =SUM(Products!W2:W600) -> 221200
A12: What the data says
B13: 1. Fragrance carries the search demand: designer lines (Dior Sauvage, Tom Ford, Gucci, Marc Jacobs, Calvin Klein) get thousands of searches a month, but big retailers own page 1, so pick the lower-KD ones (KD ≤ 20) first.
B14: 2. Vilvah and Deyga product names get very few searches (10–30 a month each); "vilvah" (480), "vilvah milk drops" (390) and "deyga" (140) are the brand terms people use. Brand pages + the Milk Drops page should target these.
B15: 3. The skincare opportunity is non-branded: "moisturiser for dry skin" (2,900), "hair mask for dry hair" (2,400), "hair oil for dry hair" (1,900), "face wash for dry/oily skin" (1,600 each), "shampoo for dandruff" (1,600). Build concern collection pages for these and use the phrases in Vilvah/Deyga product copy and FAQs.
B16: 4. Product pages: keep the brand + product name as H1 (it is the primary keyword for 265 products); add the matching concern phrase in the first paragraph and meta description.
B17: 5. Tier 2 checked perfume-type / "+ uk" variants for the top 100 fragrances and generic ingredient and product-type terms; the Primary keyword per product now picks the highest-volume variant.
A19: Top 50 hero products
A20: Ranked by primary-keyword volume, KD as tie-break. Suggested set for the "premium description rewrite × 50" in the quote. Ranking is a snapshot; volumes are live formulas.
A21: ID | B21: Product | C21: Primary keyword | D21: Volume | E21: KD | F21: CPC ($) | G21: Ease | H21: Where to use
A22: FR-115 | B22: Dior Sauvage Eau de Parfum 100ml + 10ml Men's Gift Set | C22: =INDEX(Products!$V$2:$V$600,MATCH(A22,Products!$A$2:$A$600,0)) -> dior sauvage | D22: =IFERROR(INDEX('Semrush Data'!$C$2:$C$5000,MATCH(C22,'Semrush Data'!$A$2:$A$5000,0)),"") -> 60500 | E22: =IFERROR(INDEX('Semrush Data'!$D$2:$D$5000,MATCH(C22,'Semrush Data'!$A$2:$A$5000,0)),"") -> 38 | F22: =IFERROR(INDEX('Semrush Data'!$E$2:$E$5000,MATCH(C22,'Semrush Data'!$A$2:$A$5000,0)),"") -> 0.57 | G22: =IF(E22="","",IF(E22<=20,"Easier",IF(E22<=35,"Medium","Hard"))) -> Hard | H22: H1 + meta title + first sentence; long-form description (premium rewrite)
A23: FR-378 | B23: Tom Ford Black Orchid Parfum 100ml Unisex | C23: =INDEX(Products!$V$2:$V$600,MATCH(A23,Products!$A$2:$A$600,0)) -> tom ford black orchid | D23: =IFERROR(INDEX('Semrush Data'!$C$2:$C$5000,MATCH(C23,'Semrush Data'!$A$2:$A$5000,0)),"") -> 22200 | E23: =IFERROR(INDEX('Semrush Data'!$D$2:$D$5000,MATCH(C23,'Semrush Data'!$A$2:$A$5000,0)),"") -> 22 | F23: =IFERROR(INDEX('Semrush Data'!$E$2:$E$5000,MATCH(C23,'Semrush Data'!$A$2:$A$5000,0)),"") -> 0.49 | G23: =IF(E23="","",IF(E23<=20,"Easier",IF(E23<=35,"Medium","Hard"))) -> Medium | H23: H1 + meta title + first sentence; long-form description (premium rewrite)
A24: FR-375 | B24: Tom Ford Oud Wood Eau de Parfum 50ml Unisex | C24: =INDEX(Products!$V$2:$V$600,MATCH(A24,Products!$A$2:$A$600,0)) -> tom ford oud wood | D24: =IFERROR(INDEX('Semrush Data'!$C$2:$C$5000,MATCH(C24,'Semrush Data'!$A$2:$A$5000,0)),"") -> 18100 | E24: =IFERROR(INDEX('Semrush Data'!$D$2:$D$5000,MATCH(C24,'Semrush Data'!$A$2:$A$5000,0)),"") -> 16 | F24: =IFERROR(INDEX('Semrush Data'!$E$2:$E$5000,MATCH(C24,'Semrush Data'!$A$2:$A$5000,0)),"") -> 0.54 | G24: =IF(E24="","",IF(E24<=20,"Easier",IF(E24<=35,"Medium","Hard"))) -> Easier | H24: H1 + meta title + first sentence; long-form description (premium rewrite)
A25: FR-269 | B25: Joop! Homme Eau de Toilette 200ml – Men's Warm Spicy Long lasting Fragrance | C25: =INDEX(Products!$V$2:$V$600,MATCH(A25,Products!$A$2:$A$600,0)) -> joop! homme | D25: =IFERROR(INDEX('Semrush Data'!$C$2:$C$5000,MATCH(C25,'Semrush Data'!$A$2:$A$5000,0)),"") -> 9900 | E25: =IFERROR(INDEX('Semrush Data'!$D$2:$D$5000,MATCH(C25,'Semrush Data'!$A$2:$A$5000,0)),"") -> 23 | F25: =IFERROR(INDEX('Semrush Data'!$E$2:$E$5000,MATCH(C25,'Semrush Data'!$A$2:$A$5000,0)),"") -> 0.36 | G25: =IF(E25="","",IF(E25<=20,"Easier",IF(E25<=35,"Medium","Hard"))) -> Medium | H25: H1 + meta title + first sentence; long-form description (premium rewrite)
A26: FR-379 | B26: Tom Ford Noir Extreme Parfum 100ml for Men | C26: =INDEX(Products!$V$2:$V$600,MATCH(A26,Products!$A$2:$A$600,0)) -> tom ford noir extreme | D26: =IFERROR(INDEX('Semrush Data'!$C$2:$C$5000,MATCH(C26,'Semrush Data'!$A$2:$A$5000,0)),"") -> 8100 | E26: =IFERROR(INDEX('Semrush Data'!$D$2:$D$5000,MATCH(C26,'Semrush Data'!$A$2:$A$5000,0)),"") -> 15 | F26: =IFERROR(INDEX('Semrush Data'!$E$2:$E$5000,MATCH(C26,'Semrush Data'!$A$2:$A$5000,0)),"") -> 0.59 | G26: =IF(E26="","",IF(E26<=20,"Easier",IF(E26<=35,"Medium","Hard"))) -> Easier | H26: H1 + meta title + first sentence; long-form description (premium rewrite)
A27: FR-220 | B27: Gucci Intense Oud Eau de Parfum Spray 90ml – Long Lasting Luxury Unisex Oud Fragrance | C27: =INDEX(Products!$V$2:$V$600,MATCH(A27,Products!$A$2:$A$600,0)) -> gucci intense oud | D27: =IFERROR(INDEX('Semrush Data'!$C$2:$C$5000,MATCH(C27,'Semrush Data'!$A$2:$A$5000,0)),"") -> 6600 | E27: =IFERROR(INDEX('Semrush Data'!$D$2:$D$5000,MATCH(C27,'Semrush Data'!$A$2:$A$5000,0)),"") -> 21 | F27: =IFERROR(INDEX('Semrush Data'!$E$2:$E$5000,MATCH(C27,'Semrush Data'!$A$2:$A$5000,0)),"") -> 0.44 | G27: =IF(E27="","",IF(E27<=20,"Easier",IF(E27<=35,"Medium","Hard"))) -> Medium | H27: H1 + meta title + first sentence; long-form description (premium rewrite)
A28: FR-292 | B28: Marc Jacobs Perfect Eau de Parfum 50ml – Women's Floral Fragrance | C28: =INDEX(Products!$V$2:$V$600,MATCH(A28,Products!$A$2:$A$600,0)) -> marc jacobs perfect | D28: =IFERROR(INDEX('Semrush Data'!$C$2:$C$5000,MATCH(C28,'Semrush Data'!$A$2:$A$5000,0)),"") -> 6600 | E28: =IFERROR(INDEX('Semrush Data'!$D$2:$D$5000,MATCH(C28,'Semrush Data'!$A$2:$A$5000,0)),"") -> 26 | F28: =IFERROR(INDEX('Semrush Data'!$E$2:$E$5000,MATCH(C28,'Semrush Data'!$A$2:$A$5000,0)),"") -> 0.36 | G28: =IF(E28="","",IF(E28<=20,"Easier",IF(E28<=35,"Medium","Hard"))) -> Medium | H28: H1 + meta title + first sentence; long-form description (premium rewrite)
A29: FR-077 | B29: Calvin Klein Eternity Eau de Parfum – Women's Classic Floral Fragrance | C29: =INDEX(Products!$V$2:$V$600,MATCH(A29,Products!$A$2:$A$600,0)) -> calvin klein eternity | D29: =IFERROR(INDEX('Semrush Data'!$C$2:$C$5000,MATCH(C29,'Semrush Data'!$A$2:$A$5000,0)),"") -> 4400 | E29: =IFERROR(INDEX('Semrush Data'!$D$2:$D$5000,MATCH(C29,'Semrush Data'!$A$2:$A$5000,0)),"") -> 21 | F29: =IFERROR(INDEX('Semrush Data'!$E$2:$E$5000,MATCH(C29,'Semrush Data'!$A$2:$A$5000,0)),"") -> 0.37 | G29: =IF(E29="","",IF(E29<=20,"Easier",IF(E29<=35,"Medium","Hard"))) -> Medium | H29: H1 + meta title + first sentence; long-form description (premium rewrite)
A30: FR-257 | B30: Hugo Boss Bottled Eau de Parfum 200ml for Men | C30: =INDEX(Products!$V$2:$V$600,MATCH(A30,Products!$A$2:$A$600,0)) -> hugo boss bottled | D30: =IFERROR(INDEX('Semrush Data'!$C$2:$C$5000,MATCH(C30,'Semrush Data'!$A$2:$A$5000,0)),"") -> 4400 | E30: =IFERROR(INDEX('Semrush Data'!$D$2:$D$5000,MATCH(C30,'Semrush Data'!$A$2:$A$5000,0)),"") -> 28 | F30: =IFERROR(INDEX('Semrush Data'!$E$2:$E$5000,MATCH(C30,'Semrush Data'!$A$2:$A$5000,0)),"") -> 0.45 | G30: =IF(E30="","",IF(E30<=20,"Easier",IF(E30<=35,"Medium","Hard"))) -> Medium | H30: H1 + meta title + first sentence; long-form description (premium rewrite)
A31: FR-217 | B31: Gucci Flora Gorgeous Gardenia Eau de Parfum 50ml – Women's Floral Fragrance | C31: =INDEX(Products!$V$2:$V$600,MATCH(A31,Products!$A$2:$A$600,0)) -> gucci flora gorgeous gardenia | D31: =IFERROR(INDEX('Semrush Data'!$C$2:$C$5000,MATCH(C31,'Semrush Data'!$A$2:$A$5000,0)),"") -> 4400 | E31: =IFERROR(INDEX('Semrush Data'!$D$2:$D$5000,MATCH(C31,'Semrush Data'!$A$2:$A$5000,0)),"") -> 29 | F31: =IFERROR(INDEX('Semrush Data'!$E$2:$E$5000,MATCH(C31,'Semrush Data'!$A$2:$A$5000,0)),"") -> 0.43 | G31: =IF(E31="","",IF(E31<=20,"Easier",IF(E31<=35,"Medium","Hard"))) -> Medium | H31: H1 + meta title + first sentence; long-form description (premium rewrite)
A32: FR-374 | B32: Tom Ford Neroli Portofino Eau de Parfum 50ml Unisex | C32: =INDEX(Products!$V$2:$V$600,MATCH(A32,Products!$A$2:$A$600,0)) -> tom ford neroli portofino | D32: =IFERROR(INDEX('Semrush Data'!$C$2:$C$5000,MATCH(C32,'Semrush Data'!$A$2:$A$5000,0)),"") -> 3600 | E32: =IFERROR(INDEX('Semrush Data'!$D$2:$D$5000,MATCH(C32,'Semrush Data'!$A$2:$A$5000,0)),"") -> 14 | F32: =IFERROR(INDEX('Semrush Data'!$E$2:$E$5000,MATCH(C32,'Semrush Data'!$A$2:$A$5000,0)),"") -> 0.63 | G32: =IF(E32="","",IF(E32<=20,"Easier",IF(E32<=35,"Medium","Hard"))) -> Easier | H32: H1 + meta title + first sentence; long-form description (premium rewrite)
A33: FR-095 | B33: Chloé Nomade Eau de Parfum 50ml – Women's Floral Chypre Fragrance | C33: =INDEX(Products!$V$2:$V$600,MATCH(A33,Products!$A$2:$A$600,0)) -> chloe nomade | D33: =IFERROR(INDEX('Semrush Data'!$C$2:$C$5000,MATCH(C33,'Semrush Data'!$A$2:$A$5000,0)),"") -> 2900 | E33: =IFERROR(INDEX('Semrush Data'!$D$2:$D$5000,MATCH(C33,'Semrush Data'!$A$2:$A$5000,0)),"") -> 22 | F33: =IFERROR(INDEX('Semrush Data'!$E$2:$E$5000,MATCH(C33,'Semrush Data'!$A$2:$A$5000,0)),"") -> 0.47 | G33: =IF(E33="","",IF(E33<=20,"Easier",IF(E33<=35,"Medium","Hard"))) -> Medium | H33: H1 + meta title + first sentence; long-form description (premium rewrite)
... A71: FR-094 | B71: Carolina Herrera Very Good Girl Glam Parfum 50ml – Women's Floral Fruity Gourmand Fragrance | C71: =INDEX(Products!$V$2:$V$600,MATCH(A71,Products!$A$2:$A$600,0)) -> carolina herrera very good girl glam | D71: =IFERROR(INDEX('Semrush Data'!$C$2:$C$5000,MATCH(C71,'Semrush Data'!$A$2:$A$5000,0)),"") -> 320 | E71: =IFERROR(INDEX('Semrush Data'!$D$2:$D$5000,MATCH(C71,'Semrush Data'!$A$2:$A$5000,0)),"") -> 20 | F71: =IFERROR(INDEX('Semrush Data'!$E$2:$E$5000,MATCH(C71,'Semrush Data'!$A$2:$A$5000,0)),"") -> 0 | G71: =IF(E71="","",IF(E71<=20,"Easier",IF(E71<=35,"Medium","Hard"))) -> Easier | H71: H1 + meta title + first sentence; long-form description (premium rewrite)
A73: Non-branded skincare & haircare opportunities
A74: Category and concern searches: the main organic opportunity for Vilvah & Deyga.
B75: Keyword | C75: Type | D75: Volume | E75: KD | F75: CPC ($) | G75: Ease | H75: Where to use
B76: moisturiser for dry skin | C76: Category / concern | D76: =IFERROR(INDEX('Semrush Data'!$C$2:$C$5000,MATCH(B76,'Semrush Data'!$A$2:$A$5000,0)),"") -> 2900 | E76: =IFERROR(INDEX('Semrush Data'!$D$2:$D$5000,MATCH(B76,'Semrush Data'!$A$2:$A$5000,0)),"") -> 29 | F76: =IFERROR(INDEX('Semrush Data'!$E$2:$E$5000,MATCH(B76,'Semrush Data'!$A$2:$A$5000,0)),"") -> 0.91 | G76: =IF(E76="","",IF(E76<=20,"Easier",IF(E76<=35,"Medium","Hard"))) -> Medium | H76: Concern collection page (H1 + intro + FAQ); product copy & meta description
B77: hair mask for dry hair | C77: Category / concern | D77: =IFERROR(INDEX('Semrush Data'!$C$2:$C$5000,MATCH(B77,'Semrush Data'!$A$2:$A$5000,0)),"") -> 2400 | E77: =IFERROR(INDEX('Semrush Data'!$D$2:$D$5000,MATCH(B77,'Semrush Data'!$A$2:$A$5000,0)),"") -> 13 | F77: =IFERROR(INDEX('Semrush Data'!$E$2:$E$5000,MATCH(B77,'Semrush Data'!$A$2:$A$5000,0)),"") -> 0.75 | G77: =IF(E77="","",IF(E77<=20,"Easier",IF(E77<=35,"Medium","Hard"))) -> Easier | H77: Concern collection page (H1 + intro + FAQ); product copy & meta description
B78: hair oil for dry hair | C78: Category / concern | D78: =IFERROR(INDEX('Semrush Data'!$C$2:$C$5000,MATCH(B78,'Semrush Data'!$A$2:$A$5000,0)),"") -> 1900 | E78: =IFERROR(INDEX('Semrush Data'!$D$2:$D$5000,MATCH(B78,'Semrush Data'!$A$2:$A$5000,0)),"") -> 30 | F78: =IFERROR(INDEX('Semrush Data'!$E$2:$E$5000,MATCH(B78,'Semrush Data'!$A$2:$A$5000,0)),"") -> 0.82 | G78: =IF(E78="","",IF(E78<=20,"Easier",IF(E78<=35,"Medium","Hard"))) -> Medium | H78: Concern collection page (H1 + intro + FAQ); product copy & meta description
B79: face wash for dry skin | C79: Category / concern | D79: =IFERROR(INDEX('Semrush Data'!$C$2:$C$5000,MATCH(B79,'Semrush Data'!$A$2:$A$5000,0)),"") -> 1600 | E79: =IFERROR(INDEX('Semrush Data'!$D$2:$D$5000,MATCH(B79,'Semrush Data'!$A$2:$A$5000,0)),"") -> 29 | F79: =IFERROR(INDEX('Semrush Data'!$E$2:$E$5000,MATCH(B79,'Semrush Data'!$A$2:$A$5000,0)),"") -> 0.85 | G79: =IF(E79="","",IF(E79<=20,"Easier",IF(E79<=35,"Medium","Hard"))) -> Medium | H79: Concern collection page (H1 + intro + FAQ); product copy & meta description
B80: face wash for oily skin | C80: Category / concern | D80: =IFERROR(INDEX('Semrush Data'!$C$2:$C$5000,MATCH(B80,'Semrush Data'!$A$2:$A$5000,0)),"") -> 1600 | E80: =IFERROR(INDEX('Semrush Data'!$D$2:$D$5000,MATCH(B80,'Semrush Data'!$A$2:$A$5000,0)),"") -> 33 | F80: =IFERROR(INDEX('Semrush Data'!$E$2:$E$5000,MATCH(B80,'Semrush Data'!$A$2:$A$5000,0)),"") -> 1.19 | G80: =IF(E80="","",IF(E80<=20,"Easier",IF(E80<=35,"Medium","Hard"))) -> Medium | H80: Concern collection page (H1 + intro + FAQ); product copy & meta description
B81: shampoo for dandruff | C81: Category / concern | D81: =IFERROR(INDEX('Semrush Data'!$C$2:$C$5000,MATCH(B81,'Semrush Data'!$A$2:$A$5000,0)),"") -> 1600 | E81: =IFERROR(INDEX('Semrush Data'!$D$2:$D$5000,MATCH(B81,'Semrush Data'!$A$2:$A$5000,0)),"") -> 31 | F81: =IFERROR(INDEX('Semrush Data'!$E$2:$E$5000,MATCH(B81,'Semrush Data'!$A$2:$A$5000,0)),"") -> 1.05 | G81: =IF(E81="","",IF(E81<=20,"Easier",IF(E81<=35,"Medium","Hard"))) -> Medium | H81: Concern collection page (H1 + intro + FAQ); product copy & meta description
B82: body lotion for dry skin | C82: Category / concern | D82: =IFERROR(INDEX('Semrush Data'!$C$2:$C$5000,MATCH(B82,'Semrush Data'!$A$2:$A$5000,0)),"") -> 1300 | E82: =IFERROR(INDEX('Semrush Data'!$D$2:$D$5000,MATCH(B82,'Semrush Data'!$A$2:$A$5000,0)),"") -> 11 | F82: =IFERROR(INDEX('Semrush Data'!$E$2:$E$5000,MATCH(B82,'Semrush Data'!$A$2:$A$5000,0)),"") -> 0.77 | G82: =IF(E82="","",IF(E82<=20,"Easier",IF(E82<=35,"Medium","Hard"))) -> Easier | H82: Concern collection page (H1 + intro + FAQ); product copy & meta description
B83: hair serum for frizzy hair | C83: Category / concern | D83: =IFERROR(INDEX('Semrush Data'!$C$2:$C$5000,MATCH(B83,'Semrush Data'!$A$2:$A$5000,0)),"") -> 1000 | E83: =IFERROR(INDEX('Semrush Data'!$D$2:$D$5000,MATCH(B83,'Semrush Data'!$A$2:$A$5000,0)),"") -> 27 | F83: =IFERROR(INDEX('Semrush Data'!$E$2:$E$5000,MATCH(B83,'Semrush Data'!$A$2:$A$5000,0)),"") -> 0.72 | G83: =IF(E83="","",IF(E83<=20,"Easier",IF(E83<=35,"Medium","Hard"))) -> Medium | H83: Concern collection page (H1 + intro + FAQ); product copy & meta description
B84: lip balm for dry lips | C84: Category / concern | D84: =IFERROR(INDEX('Semrush Data'!$C$2:$C$5000,MATCH(B84,'Semrush Data'!$A$2:$A$5000,0)),"") -> 1000 | E84: =IFERROR(INDEX('Semrush Data'!$D$2:$D$5000,MATCH(B84,'Semrush Data'!$A$2:$A$5000,0)),"") -> 41 | F84: =IFERROR(INDEX('Semrush Data'!$E$2:$E$5000,MATCH(B84,'Semrush Data'!$A$2:$A$5000,0)),"") -> 0.76 | G84: =IF(E84="","",IF(E84<=20,"Easier",IF(E84<=35,"Medium","Hard"))) -> Hard | H84: Concern collection page (H1 + intro + FAQ); product copy & meta description
B85: hair treatment for dry hair | C85: Category / concern | D85: =IFERROR(INDEX('Semrush Data'!$C$2:$C$5000,MATCH(B85,'Semrush Data'!$A$2:$A$5000,0)),"") -> 720 | E85: =IFERROR(INDEX('Semrush Data'!$D$2:$D$5000,MATCH(B85,'Semrush Data'!$A$2:$A$5000,0)),"") -> 25 | F85: =IFERROR(INDEX('Semrush Data'!$E$2:$E$5000,MATCH(B85,'Semrush Data'!$A$2:$A$5000,0)),"") -> 0.84 | G85: =IF(E85="","",IF(E85<=20,"Easier",IF(E85<=35,"Medium","Hard"))) -> Medium | H85: Concern collection page (H1 + intro + FAQ); product copy & meta description
B86: natural sunscreen uk | C86: Category / concern | D86: =IFERROR(INDEX('Semrush Data'!$C$2:$C$5000,MATCH(B86,'Semrush Data'!$A$2:$A$5000,0)),"") -> 720 | E86: =IFERROR(INDEX('Semrush Data'!$D$2:$D$5000,MATCH(B86,'Semrush Data'!$A$2:$A$5000,0)),"") -> 20 | F86: =IFERROR(INDEX('Semrush Data'!$E$2:$E$5000,MATCH(B86,'Semrush Data'!$A$2:$A$5000,0)),"") -> 0.57 | G86: =IF(E86="","",IF(E86<=20,"Easier",IF(E86<=35,"Medium","Hard"))) -> Easier | H86: Category page H1 / intro; homepage section
B87: toner for dry skin | C87: Category / concern | D87: =IFERROR(INDEX('Semrush Data'!$C$2:$C$5000,MATCH(B87,'Semrush Data'!$A$2:$A$5000,0)),"") -> 720 | E87: =IFERROR(INDEX('Semrush Data'!$D$2:$D$5000,MATCH(B87,'Semrush Data'!$A$2:$A$5000,0)),"") -> 16 | F87: =IFERROR(INDEX('Semrush Data'!$E$2:$E$5000,MATCH(B87,'Semrush Data'!$A$2:$A$5000,0)),"") -> 0.77 | G87: =IF(E87="","",IF(E87<=20,"Easier",IF(E87<=35,"Medium","Hard"))) -> Easier | H87: Concern collection page (H1 + intro + FAQ); product copy & meta description
... B105: natural body scrub uk | C105: Category / concern | D105: =IFERROR(INDEX('Semrush Data'!$C$2:$C$5000,MATCH(B105,'Semrush Data'!$A$2:$A$5000,0)),"") -> 30 | E105: =IFERROR(INDEX('Semrush Data'!$D$2:$D$5000,MATCH(B105,'Semrush Data'!$A$2:$A$5000,0)),"") -> 12 | F105: =IFERROR(INDEX('Semrush Data'!$E$2:$E$5000,MATCH(B105,'Semrush Data'!$A$2:$A$5000,0)),"") -> 0 | G105: =IF(E105="","",IF(E105<=20,"Easier",IF(E105<=35,"Medium","Hard"))) -> Easier | H105: Category page H1 / intro; homepage section
A107: Ingredient & product-type searches (Tier 2)
A108: Generic searches that match the Vilvah & Deyga range: candidates for new collection pages, product-copy phrases and blog topics.
B109: Keyword | C109: Type | D109: Volume | E109: KD | F109: CPC ($) | G109: Ease | H109: Where to use
B110: vitamin c serum | C110: Generic product term | D110: =IFERROR(INDEX('Semrush Data'!$C$2:$C$5000,MATCH(B110,'Semrush Data'!$A$2:$A$5000,0)),"") -> 33100 | E110: =IFERROR(INDEX('Semrush Data'!$D$2:$D$5000,MATCH(B110,'Semrush Data'!$A$2:$A$5000,0)),"") -> 44 | F110: =IFERROR(INDEX('Semrush Data'!$E$2:$E$5000,MATCH(B110,'Semrush Data'!$A$2:$A$5000,0)),"") -> 1.23 | G110: =IF(E110="","",IF(E110<=20,"Easier",IF(E110<=35,"Medium","Hard"))) -> Hard | H110: New collection / keyword page + product copy
B111: face mask | C111: VD target keyword | D111: =IFERROR(INDEX('Semrush Data'!$C$2:$C$5000,MATCH(B111,'Semrush Data'!$A$2:$A$5000,0)),"") -> 22200 | E111: =IFERROR(INDEX('Semrush Data'!$D$2:$D$5000,MATCH(B111,'Semrush Data'!$A$2:$A$5000,0)),"") -> 30 | F111: =IFERROR(INDEX('Semrush Data'!$E$2:$E$5000,MATCH(B111,'Semrush Data'!$A$2:$A$5000,0)),"") -> 0.87 | G111: =IF(E111="","",IF(E111<=20,"Easier",IF(E111<=35,"Medium","Hard"))) -> Medium | H111: New collection / keyword page + product copy
B112: aloe vera gel | C112: Generic product term | D112: =IFERROR(INDEX('Semrush Data'!$C$2:$C$5000,MATCH(B112,'Semrush Data'!$A$2:$A$5000,0)),"") -> 18100 | E112: =IFERROR(INDEX('Semrush Data'!$D$2:$D$5000,MATCH(B112,'Semrush Data'!$A$2:$A$5000,0)),"") -> 16 | F112: =IFERROR(INDEX('Semrush Data'!$E$2:$E$5000,MATCH(B112,'Semrush Data'!$A$2:$A$5000,0)),"") -> 0.31 | G112: =IF(E112="","",IF(E112<=20,"Easier",IF(E112<=35,"Medium","Hard"))) -> Easier | H112: New collection / keyword page + product copy
B113: niacinamide serum | C113: Generic product term | D113: =IFERROR(INDEX('Semrush Data'!$C$2:$C$5000,MATCH(B113,'Semrush Data'!$A$2:$A$5000,0)),"") -> 14800 | E113: =IFERROR(INDEX('Semrush Data'!$D$2:$D$5000,MATCH(B113,'Semrush Data'!$A$2:$A$5000,0)),"") -> 38 | F113: =IFERROR(INDEX('Semrush Data'!$E$2:$E$5000,MATCH(B113,'Semrush Data'!$A$2:$A$5000,0)),"") -> 0.77 | G113: =IF(E113="","",IF(E113<=20,"Easier",IF(E113<=35,"Medium","Hard"))) -> Hard | H113: New collection / keyword page + product copy
B114: body scrub | C114: VD target keyword | D114: =IFERROR(INDEX('Semrush Data'!$C$2:$C$5000,MATCH(B114,'Semrush Data'!$A$2:$A$5000,0)),"") -> 12100 | E114: =IFERROR(INDEX('Semrush Data'!$D$2:$D$5000,MATCH(B114,'Semrush Data'!$A$2:$A$5000,0)),"") -> 18 | F114: =IFERROR(INDEX('Semrush Data'!$E$2:$E$5000,MATCH(B114,'Semrush Data'!$A$2:$A$5000,0)),"") -> 0.44 | G114: =IF(E114="","",IF(E114<=20,"Easier",IF(E114<=35,"Medium","Hard"))) -> Easier | H114: New collection / keyword page + product copy
B115: face serum | C115: VD target keyword | D115: =IFERROR(INDEX('Semrush Data'!$C$2:$C$5000,MATCH(B115,'Semrush Data'!$A$2:$A$5000,0)),"") -> 9900 | E115: =IFERROR(INDEX('Semrush Data'!$D$2:$D$5000,MATCH(B115,'Semrush Data'!$A$2:$A$5000,0)),"") -> 30 | F115: =IFERROR(INDEX('Semrush Data'!$E$2:$E$5000,MATCH(B115,'Semrush Data'!$A$2:$A$5000,0)),"") -> 1.02 | G115: =IF(E115="","",IF(E115<=20,"Easier",IF(E115<=35,"Medium","Hard"))) -> Medium | H115: New collection / keyword page + product copy
B116: sunscreen spf 50 | C116: Generic product term | D116: =IFERROR(INDEX('Semrush Data'!$C$2:$C$5000,MATCH(B116,'Semrush Data'!$A$2:$A$5000,0)),"") -> 9900 | E116: =IFERROR(INDEX('Semrush Data'!$D$2:$D$5000,MATCH(B116,'Semrush Data'!$A$2:$A$5000,0)),"") -> 22 | F116: =IFERROR(INDEX('Semrush Data'!$E$2:$E$5000,MATCH(B116,'Semrush Data'!$A$2:$A$5000,0)),"") -> 0.78 | G116: =IF(E116="","",IF(E116<=20,"Easier",IF(E116<=35,"Medium","Hard"))) -> Medium | H116: New collection / keyword page + product copy
B117: tinted sunscreen | C117: Generic product term | D117: =IFERROR(INDEX('Semrush Data'!$C$2:$C$5000,MATCH(B117,'Semrush Data'!$A$2:$A$5000,0)),"") -> 8100 | E117: =IFERROR(INDEX('Semrush Data'!$D$2:$D$5000,MATCH(B117,'Semrush Data'!$A$2:$A$5000,0)),"") -> 31 | F117: =IFERROR(INDEX('Semrush Data'!$E$2:$E$5000,MATCH(B117,'Semrush Data'!$A$2:$A$5000,0)),"") -> 0.76 | G117: =IF(E117="","",IF(E117<=20,"Easier",IF(E117<=35,"Medium","Hard"))) -> Medium | H117: New collection / keyword page + product copy
B118: natural deodorant | C118: VD target keyword | D118: =IFERROR(INDEX('Semrush Data'!$C$2:$C$5000,MATCH(B118,'Semrush Data'!$A$2:$A$5000,0)),"") -> 6600 | E118: =IFERROR(INDEX('Semrush Data'!$D$2:$D$5000,MATCH(B118,'Semrush Data'!$A$2:$A$5000,0)),"") -> 26 | F118: =IFERROR(INDEX('Semrush Data'!$E$2:$E$5000,MATCH(B118,'Semrush Data'!$A$2:$A$5000,0)),"") -> 2.37 | G118: =IF(E118="","",IF(E118<=20,"Easier",IF(E118<=35,"Medium","Hard"))) -> Medium | H118: New collection / keyword page + product copy
B119: body butter | C119: Generic product term | D119: =IFERROR(INDEX('Semrush Data'!$C$2:$C$5000,MATCH(B119,'Semrush Data'!$A$2:$A$5000,0)),"") -> 6600 | E119: =IFERROR(INDEX('Semrush Data'!$D$2:$D$5000,MATCH(B119,'Semrush Data'!$A$2:$A$5000,0)),"") -> 12 | F119: =IFERROR(INDEX('Semrush Data'!$E$2:$E$5000,MATCH(B119,'Semrush Data'!$A$2:$A$5000,0)),"") -> 0.76 | G119: =IF(E119="","",IF(E119<=20,"Easier",IF(E119<=35,"Medium","Hard"))) -> Easier | H119: New collection / keyword page + product copy
B120: lip scrub | C120: Generic product term | D120: =IFERROR(INDEX('Semrush Data'!$C$2:$C$5000,MATCH(B120,'Semrush Data'!$A$2:$A$5000,0)),"") -> 5400 | E120: =IFERROR(INDEX('Semrush Data'!$D$2:$D$5000,MATCH(B120,'Semrush Data'!$A$2:$A$5000,0)),"") -> 16 | F120: =IFERROR(INDEX('Semrush Data'!$E$2:$E$5000,MATCH(B120,'Semrush Data'!$A$2:$A$5000,0)),"") -> 0.46 | G120: =IF(E120="","",IF(E120<=20,"Easier",IF(E120<=35,"Medium","Hard"))) -> Easier | H120: New collection / keyword page + product copy
B121: hair growth oil | C121: Generic product term | D121: =IFERROR(INDEX('Semrush Data'!$C$2:$C$5000,MATCH(B121,'Semrush Data'!$A$2:$A$5000,0)),"") -> 5400 | E121: =IFERROR(INDEX('Semrush Data'!$D$2:$D$5000,MATCH(B121,'Semrush Data'!$A$2:$A$5000,0)),"") -> 21 | F121: =IFERROR(INDEX('Semrush Data'!$E$2:$E$5000,MATCH(B121,'Semrush Data'!$A$2:$A$5000,0)),"") -> 1.76 | G121: =IF(E121="","",IF(E121<=20,"Easier",IF(E121<=35,"Medium","Hard"))) -> Medium | H121: New collection / keyword page + product copy
... B154: natural moisturiser | C154: Generic product term | D154: =IFERROR(INDEX('Semrush Data'!$C$2:$C$5000,MATCH(B154,'Semrush Data'!$A$2:$A$5000,0)),"") -> 1000 | E154: =IFERROR(INDEX('Semrush Data'!$D$2:$D$5000,MATCH(B154,'Semrush Data'!$A$2:$A$5000,0)),"") -> 24 | F154: =IFERROR(INDEX('Semrush Data'!$E$2:$E$5000,MATCH(B154,'Semrush Data'!$A$2:$A$5000,0)),"") -> 0.92 | G154: =IF(E154="","",IF(E154<=20,"Easier",IF(E154<=35,"Medium","Hard"))) -> Medium | H154: New collection / keyword page + product copy
A156: Questions & buying searches (Tier 3)
A157: What people ask and how they shop for the hero and Vilvah & Deyga products.
B158: Keyword | C158: Type | D158: Volume | E158: KD | F158: CPC ($) | G158: Ease | H158: Where to use
B159: joop homme | C159: Google suggest | D159: =IFERROR(INDEX('Semrush Data'!$C$2:$C$5000,MATCH(B159,'Semrush Data'!$A$2:$A$5000,0)),"") -> 9900 | E159: =IFERROR(INDEX('Semrush Data'!$D$2:$D$5000,MATCH(B159,'Semrush Data'!$A$2:$A$5000,0)),"") -> 23 | F159: =IFERROR(INDEX('Semrush Data'!$E$2:$E$5000,MATCH(B159,'Semrush Data'!$A$2:$A$5000,0)),"") -> 0.36 | G159: =IF(E159="","",IF(E159<=20,"Easier",IF(E159<=35,"Medium","Hard"))) -> Medium | H159: Product copy / secondary keyword
B160: dior sauvage parfum | C160: Google suggest | D160: =IFERROR(INDEX('Semrush Data'!$C$2:$C$5000,MATCH(B160,'Semrush Data'!$A$2:$A$5000,0)),"") -> 5400 | E160: =IFERROR(INDEX('Semrush Data'!$D$2:$D$5000,MATCH(B160,'Semrush Data'!$A$2:$A$5000,0)),"") -> 35 | F160: =IFERROR(INDEX('Semrush Data'!$E$2:$E$5000,MATCH(B160,'Semrush Data'!$A$2:$A$5000,0)),"") -> 0.66 | G160: =IF(E160="","",IF(E160<=20,"Easier",IF(E160<=35,"Medium","Hard"))) -> Medium | H160: Product copy / secondary keyword
B161: calvin klein eternity for women | C161: Google suggest | D161: =IFERROR(INDEX('Semrush Data'!$C$2:$C$5000,MATCH(B161,'Semrush Data'!$A$2:$A$5000,0)),"") -> 2900 | E161: =IFERROR(INDEX('Semrush Data'!$D$2:$D$5000,MATCH(B161,'Semrush Data'!$A$2:$A$5000,0)),"") -> 16 | F161: =IFERROR(INDEX('Semrush Data'!$E$2:$E$5000,MATCH(B161,'Semrush Data'!$A$2:$A$5000,0)),"") -> 0.36 | G161: =IF(E161="","",IF(E161<=20,"Easier",IF(E161<=35,"Medium","Hard"))) -> Easier | H161: Product copy / secondary keyword
B162: chloe nomade perfume | C162: Google suggest | D162: =IFERROR(INDEX('Semrush Data'!$C$2:$C$5000,MATCH(B162,'Semrush Data'!$A$2:$A$5000,0)),"") -> 2900 | E162: =IFERROR(INDEX('Semrush Data'!$D$2:$D$5000,MATCH(B162,'Semrush Data'!$A$2:$A$5000,0)),"") -> 13 | F162: =IFERROR(INDEX('Semrush Data'!$E$2:$E$5000,MATCH(B162,'Semrush Data'!$A$2:$A$5000,0)),"") -> 0.4 | G162: =IF(E162="","",IF(E162<=20,"Easier",IF(E162<=35,"Medium","Hard"))) -> Easier | H162: Product copy / secondary keyword
B163: calvin klein eternity for men | C163: Google suggest | D163: =IFERROR(INDEX('Semrush Data'!$C$2:$C$5000,MATCH(B163,'Semrush Data'!$A$2:$A$5000,0)),"") -> 2400 | E163: =IFERROR(INDEX('Semrush Data'!$D$2:$D$5000,MATCH(B163,'Semrush Data'!$A$2:$A$5000,0)),"") -> 17 | F163: =IFERROR(INDEX('Semrush Data'!$E$2:$E$5000,MATCH(B163,'Semrush Data'!$A$2:$A$5000,0)),"") -> 0.36 | G163: =IF(E163="","",IF(E163<=20,"Easier",IF(E163<=35,"Medium","Hard"))) -> Easier | H163: Product copy / secondary keyword
B164: marc jacobs perfect perfume | C164: Google suggest | D164: =IFERROR(INDEX('Semrush Data'!$C$2:$C$5000,MATCH(B164,'Semrush Data'!$A$2:$A$5000,0)),"") -> 1900 | E164: =IFERROR(INDEX('Semrush Data'!$D$2:$D$5000,MATCH(B164,'Semrush Data'!$A$2:$A$5000,0)),"") -> 24 | F164: =IFERROR(INDEX('Semrush Data'!$E$2:$E$5000,MATCH(B164,'Semrush Data'!$A$2:$A$5000,0)),"") -> 0.4 | G164: =IF(E164="","",IF(E164<=20,"Easier",IF(E164<=35,"Medium","Hard"))) -> Medium | H164: Product copy / secondary keyword
B165: paloma picasso perfume | C165: Google suggest | D165: =IFERROR(INDEX('Semrush Data'!$C$2:$C$5000,MATCH(B165,'Semrush Data'!$A$2:$A$5000,0)),"") -> 1900 | E165: =IFERROR(INDEX('Semrush Data'!$D$2:$D$5000,MATCH(B165,'Semrush Data'!$A$2:$A$5000,0)),"") -> 23 | F165: =IFERROR(INDEX('Semrush Data'!$E$2:$E$5000,MATCH(B165,'Semrush Data'!$A$2:$A$5000,0)),"") -> 0.41 | G165: =IF(E165="","",IF(E165<=20,"Easier",IF(E165<=35,"Medium","Hard"))) -> Medium | H165: Product copy / secondary keyword
B166: bentley azure for sale | C166: Google suggest | D166: =IFERROR(INDEX('Semrush Data'!$C$2:$C$5000,MATCH(B166,'Semrush Data'!$A$2:$A$5000,0)),"") -> 720 | E166: =IFERROR(INDEX('Semrush Data'!$D$2:$D$5000,MATCH(B166,'Semrush Data'!$A$2:$A$5000,0)),"") -> 16 | F166: =IFERROR(INDEX('Semrush Data'!$E$2:$E$5000,MATCH(B166,'Semrush Data'!$A$2:$A$5000,0)),"") -> 0.27 | G166: =IF(E166="","",IF(E166<=20,"Easier",IF(E166<=35,"Medium","Hard"))) -> Easier | H166: Product copy / secondary keyword
B167: dior sauvage price | C167: Price | D167: =IFERROR(INDEX('Semrush Data'!$C$2:$C$5000,MATCH(B167,'Semrush Data'!$A$2:$A$5000,0)),"") -> 590 | E167: =IFERROR(INDEX('Semrush Data'!$D$2:$D$5000,MATCH(B167,'Semrush Data'!$A$2:$A$5000,0)),"") -> 22 | F167: =IFERROR(INDEX('Semrush Data'!$E$2:$E$5000,MATCH(B167,'Semrush Data'!$A$2:$A$5000,0)),"") -> 0.32 | G167: =IF(E167="","",IF(E167<=20,"Easier",IF(E167<=35,"Medium","Hard"))) -> Medium | H167: Meta title / description wording
B168: dolce & gabbana the one for men | C168: Google suggest | D168: =IFERROR(INDEX('Semrush Data'!$C$2:$C$5000,MATCH(B168,'Semrush Data'!$A$2:$A$5000,0)),"") -> 480 | E168: =IFERROR(INDEX('Semrush Data'!$D$2:$D$5000,MATCH(B168,'Semrush Data'!$A$2:$A$5000,0)),"") -> 16 | F168: =IFERROR(INDEX('Semrush Data'!$E$2:$E$5000,MATCH(B168,'Semrush Data'!$A$2:$A$5000,0)),"") -> 0.44 | G168: =IF(E168="","",IF(E168<=20,"Easier",IF(E168<=35,"Medium","Hard"))) -> Easier | H168: Product copy / secondary keyword
B169: dolce & gabbana the one edp | C169: Google suggest | D169: =IFERROR(INDEX('Semrush Data'!$C$2:$C$5000,MATCH(B169,'Semrush Data'!$A$2:$A$5000,0)),"") -> 390 | E169: =IFERROR(INDEX('Semrush Data'!$D$2:$D$5000,MATCH(B169,'Semrush Data'!$A$2:$A$5000,0)),"") -> 16 | F169: =IFERROR(INDEX('Semrush Data'!$E$2:$E$5000,MATCH(B169,'Semrush Data'!$A$2:$A$5000,0)),"") -> 0.48 | G169: =IF(E169="","",IF(E169<=20,"Easier",IF(E169<=35,"Medium","Hard"))) -> Easier | H169: Product copy / secondary keyword
B170: bvlgari man in black parfum | C170: Google suggest | D170: =IFERROR(INDEX('Semrush Data'!$C$2:$C$5000,MATCH(B170,'Semrush Data'!$A$2:$A$5000,0)),"") -> 320 | E170: =IFERROR(INDEX('Semrush Data'!$D$2:$D$5000,MATCH(B170,'Semrush Data'!$A$2:$A$5000,0)),"") -> 19 | F170: =IFERROR(INDEX('Semrush Data'!$E$2:$E$5000,MATCH(B170,'Semrush Data'!$A$2:$A$5000,0)),"") -> 0.41 | G170: =IF(E170="","",IF(E170<=20,"Easier",IF(E170<=35,"Medium","Hard"))) -> Easier | H170: Product copy / secondary keyword
... B208: carolina herrera 212 vip men notes | C208: Google suggest | D208: =IFERROR(INDEX('Semrush Data'!$C$2:$C$5000,MATCH(B208,'Semrush Data'!$A$2:$A$5000,0)),"") -> 20 | E208: =IFERROR(INDEX('Semrush Data'!$D$2:$D$5000,MATCH(B208,'Semrush Data'!$A$2:$A$5000,0)),"") -> 12 | F208: =IFERROR(INDEX('Semrush Data'!$E$2:$E$5000,MATCH(B208,'Semrush Data'!$A$2:$A$5000,0)),"") -> 0 | G208: =IF(E208="","",IF(E208<=20,"Easier",IF(E208<=35,"Medium","Hard"))) -> Easier | H208: Product FAQ question
A210: Vilvah & Deyga brand searches
A211: What people type about the two partner brands.
B212: Keyword | C212: Type | D212: Volume | E212: KD | F212: CPC ($) | G212: Ease | H212: Where to use
B213: vilvah | C213: Brand | D213: =IFERROR(INDEX('Semrush Data'!$C$2:$C$5000,MATCH(B213,'Semrush Data'!$A$2:$A$5000,0)),"") -> 480 | E213: =IFERROR(INDEX('Semrush Data'!$D$2:$D$5000,MATCH(B213,'Semrush Data'!$A$2:$A$5000,0)),"") -> 12 | F213: =IFERROR(INDEX('Semrush Data'!$E$2:$E$5000,MATCH(B213,'Semrush Data'!$A$2:$A$5000,0)),"") -> 1.03 | G213: =IF(E213="","",IF(E213<=20,"Easier",IF(E213<=35,"Medium","Hard"))) -> Easier | H213: Brand page title + intro
B214: vilvah milk drops | C214: Google suggest (brand) | D214: =IFERROR(INDEX('Semrush Data'!$C$2:$C$5000,MATCH(B214,'Semrush Data'!$A$2:$A$5000,0)),"") -> 390 | E214: =IFERROR(INDEX('Semrush Data'!$D$2:$D$5000,MATCH(B214,'Semrush Data'!$A$2:$A$5000,0)),"") -> 17 | F214: =IFERROR(INDEX('Semrush Data'!$E$2:$E$5000,MATCH(B214,'Semrush Data'!$A$2:$A$5000,0)),"") -> 0.7 | G214: =IF(E214="","",IF(E214<=20,"Easier",IF(E214<=35,"Medium","Hard"))) -> Easier | H214: Product page H1 / meta (matching product)
B215: deyga | C215: Brand | D215: =IFERROR(INDEX('Semrush Data'!$C$2:$C$5000,MATCH(B215,'Semrush Data'!$A$2:$A$5000,0)),"") -> 140 | E215: =IFERROR(INDEX('Semrush Data'!$D$2:$D$5000,MATCH(B215,'Semrush Data'!$A$2:$A$5000,0)),"") -> 28 | F215: =IFERROR(INDEX('Semrush Data'!$E$2:$E$5000,MATCH(B215,'Semrush Data'!$A$2:$A$5000,0)),"") -> 0.3 | G215: =IF(E215="","",IF(E215<=20,"Easier",IF(E215<=35,"Medium","Hard"))) -> Medium | H215: Brand page title + intro
B216: vilvah store | C216: Google suggest (brand) | D216: =IFERROR(INDEX('Semrush Data'!$C$2:$C$5000,MATCH(B216,'Semrush Data'!$A$2:$A$5000,0)),"") -> 90 | E216: =IFERROR(INDEX('Semrush Data'!$D$2:$D$5000,MATCH(B216,'Semrush Data'!$A$2:$A$5000,0)),"") -> 36 | F216: =IFERROR(INDEX('Semrush Data'!$E$2:$E$5000,MATCH(B216,'Semrush Data'!$A$2:$A$5000,0)),"") -> 1.14 | G216: =IF(E216="","",IF(E216<=20,"Easier",IF(E216<=35,"Medium","Hard"))) -> Hard | H216: Brand page title + intro
B217: deyga organics | C217: Google suggest (brand) | D217: =IFERROR(INDEX('Semrush Data'!$C$2:$C$5000,MATCH(B217,'Semrush Data'!$A$2:$A$5000,0)),"") -> 70 | E217: =IFERROR(INDEX('Semrush Data'!$D$2:$D$5000,MATCH(B217,'Semrush Data'!$A$2:$A$5000,0)),"") -> 29 | F217: =IFERROR(INDEX('Semrush Data'!$E$2:$E$5000,MATCH(B217,'Semrush Data'!$A$2:$A$5000,0)),"") -> 0.62 | G217: =IF(E217="","",IF(E217<=20,"Easier",IF(E217<=35,"Medium","Hard"))) -> Medium | H217: Brand page title + intro
B218: vilvah uk | C218: Brand | D218: =IFERROR(INDEX('Semrush Data'!$C$2:$C$5000,MATCH(B218,'Semrush Data'!$A$2:$A$5000,0)),"") -> 30 | E218: =IFERROR(INDEX('Semrush Data'!$D$2:$D$5000,MATCH(B218,'Semrush Data'!$A$2:$A$5000,0)),"") -> 9 | F218: =IFERROR(INDEX('Semrush Data'!$E$2:$E$5000,MATCH(B218,'Semrush Data'!$A$2:$A$5000,0)),"") -> 0.78 | G218: =IF(E218="","",IF(E218<=20,"Easier",IF(E218<=35,"Medium","Hard"))) -> Easier | H218: Brand page title + intro
B219: deyga hair color | C219: Google suggest (brand) | D219: =IFERROR(INDEX('Semrush Data'!$C$2:$C$5000,MATCH(B219,'Semrush Data'!$A$2:$A$5000,0)),"") -> 30 | E219: =IFERROR(INDEX('Semrush Data'!$D$2:$D$5000,MATCH(B219,'Semrush Data'!$A$2:$A$5000,0)),"") -> 24 | F219: =IFERROR(INDEX('Semrush Data'!$E$2:$E$5000,MATCH(B219,'Semrush Data'!$A$2:$A$5000,0)),"") -> 0 | G219: =IF(E219="","",IF(E219<=20,"Easier",IF(E219<=35,"Medium","Hard"))) -> Medium | H219: Product page H1 / meta (matching product)
B220: deyga products | C220: Brand | D220: =IFERROR(INDEX('Semrush Data'!$C$2:$C$5000,MATCH(B220,'Semrush Data'!$A$2:$A$5000,0)),"") -> 20 | E220: =IFERROR(INDEX('Semrush Data'!$D$2:$D$5000,MATCH(B220,'Semrush Data'!$A$2:$A$5000,0)),"") -> 12 | F220: =IFERROR(INDEX('Semrush Data'!$E$2:$E$5000,MATCH(B220,'Semrush Data'!$A$2:$A$5000,0)),"") -> 0 | G220: =IF(E220="","",IF(E220<=20,"Easier",IF(E220<=35,"Medium","Hard"))) -> Easier | H220: Brand page title + intro
B221: vilvah official website | C221: Brand | D221: =IFERROR(INDEX('Semrush Data'!$C$2:$C$5000,MATCH(B221,'Semrush Data'!$A$2:$A$5000,0)),"") -> 20 | E221: =IFERROR(INDEX('Semrush Data'!$D$2:$D$5000,MATCH(B221,'Semrush Data'!$A$2:$A$5000,0)),"") -> 33 | F221: =IFERROR(INDEX('Semrush Data'!$E$2:$E$5000,MATCH(B221,'Semrush Data'!$A$2:$A$5000,0)),"") -> 0 | G221: =IF(E221="","",IF(E221<=20,"Easier",IF(E221<=35,"Medium","Hard"))) -> Medium | H221: Brand page title + intro
B222: vilvah products | C222: Brand | D222: =IFERROR(INDEX('Semrush Data'!$C$2:$C$5000,MATCH(B222,'Semrush Data'!$A$2:$A$5000,0)),"") -> 20 | E222: =IFERROR(INDEX('Semrush Data'!$D$2:$D$5000,MATCH(B222,'Semrush Data'!$A$2:$A$5000,0)),"") -> 26 | F222: =IFERROR(INDEX('Semrush Data'!$E$2:$E$5000,MATCH(B222,'Semrush Data'!$A$2:$A$5000,0)),"") -> 0.36 | G222: =IF(E222="","",IF(E222<=20,"Easier",IF(E222<=35,"Medium","Hard"))) -> Medium | H222: Brand page title + intro
B223: deyga beetroot lip balm | C223: Google suggest (brand) | D223: =IFERROR(INDEX('Semrush Data'!$C$2:$C$5000,MATCH(B223,'Semrush Data'!$A$2:$A$5000,0)),"") -> 20 | E223: =IFERROR(INDEX('Semrush Data'!$D$2:$D$5000,MATCH(B223,'Semrush Data'!$A$2:$A$5000,0)),"") -> 14 | F223: =IFERROR(INDEX('Semrush Data'!$E$2:$E$5000,MATCH(B223,'Semrush Data'!$A$2:$A$5000,0)),"") -> 0 | G223: =IF(E223="","",IF(E223<=20,"Easier",IF(E223<=35,"Medium","Hard"))) -> Easier | H223: Product page H1 / meta (matching product)
B224: deyga hair dye | C224: Google suggest (brand) | D224: =IFERROR(INDEX('Semrush Data'!$C$2:$C$5000,MATCH(B224,'Semrush Data'!$A$2:$A$5000,0)),"") -> 20 | E224: =IFERROR(INDEX('Semrush Data'!$D$2:$D$5000,MATCH(B224,'Semrush Data'!$A$2:$A$5000,0)),"") -> 9 | F224: =IFERROR(INDEX('Semrush Data'!$E$2:$E$5000,MATCH(B224,'Semrush Data'!$A$2:$A$5000,0)),"") -> 0 | G224: =IF(E224="","",IF(E224<=20,"Easier",IF(E224<=35,"Medium","Hard"))) -> Easier | H224: Product page H1 / meta (matching product)
... B226: deyga charcoal soap | C226: Google suggest (brand) | D226: =IFERROR(INDEX('Semrush Data'!$C$2:$C$5000,MATCH(B226,'Semrush Data'!$A$2:$A$5000,0)),"") -> 10 | E226: =IFERROR(INDEX('Semrush Data'!$D$2:$D$5000,MATCH(B226,'Semrush Data'!$A$2:$A$5000,0)),"") -> 15 | F226: =IFERROR(INDEX('Semrush Data'!$E$2:$E$5000,MATCH(B226,'Semrush Data'!$A$2:$A$5000,0)),"") -> 0 | G226: =IF(E226="","",IF(E226<=20,"Easier",IF(E226<=35,"Medium","Hard"))) -> Easier | H226: Product page H1 / meta (matching product)
A228: Fragrance brand & scent-family searches
A229: Brand pages and scent-family collections. High-volume designer terms are hard (LOOKFANTASTIC, Boots, The Perfume Shop); target "Easier" ones first.
B230: Keyword | C230: Type | D230: Volume | E230: KD | F230: CPC ($) | G230: Ease | H230: Where to use
B231: ariana grande perfume | C231: Brand / family | D231: =IFERROR(INDEX('Semrush Data'!$C$2:$C$5000,MATCH(B231,'Semrush Data'!$A$2:$A$5000,0)),"") -> 40500 | E231: =IFERROR(INDEX('Semrush Data'!$D$2:$D$5000,MATCH(B231,'Semrush Data'!$A$2:$A$5000,0)),"") -> 17 | F231: =IFERROR(INDEX('Semrush Data'!$E$2:$E$5000,MATCH(B231,'Semrush Data'!$A$2:$A$5000,0)),"") -> 0.34 | G231: =IF(E231="","",IF(E231<=20,"Easier",IF(E231<=35,"Medium","Hard"))) -> Easier | H231: Brand page title + intro
B232: jimmy choo perfume | C232: Brand / family | D232: =IFERROR(INDEX('Semrush Data'!$C$2:$C$5000,MATCH(B232,'Semrush Data'!$A$2:$A$5000,0)),"") -> 40500 | E232: =IFERROR(INDEX('Semrush Data'!$D$2:$D$5000,MATCH(B232,'Semrush Data'!$A$2:$A$5000,0)),"") -> 32 | F232: =IFERROR(INDEX('Semrush Data'!$E$2:$E$5000,MATCH(B232,'Semrush Data'!$A$2:$A$5000,0)),"") -> 0.33 | G232: =IF(E232="","",IF(E232<=20,"Easier",IF(E232<=35,"Medium","Hard"))) -> Medium | H232: Brand page title + intro
...

Sheet VD Content
A1: ID | B1: Brand | C1: Product | D1: Type | E1: Concern | F1: Target keyword | G1: Target vol. | H1: Target KD | I1: Brand keyword | J1: Brand vol. | K1: Collection page (link to) | L1: H1 | M1: Meta title | N1: Title len | O1: Meta description | P1: Desc len | Q1: Intro paragraph (first lines of product copy) | R1: FAQ ideas (Google autocomplete) | S1: Source description | T1: Claims check
A2: VD-001 | B2: Vilvah | C2: Rosewater Facial Toner | D2: Toners | E2: Skin Nourishment | F2: toner for dry skin | G2: =IFERROR(INDEX('Semrush Data'!$C$2:$C$5000,MATCH(F2,'Semrush Data'!$A$2:$A$5000,0)),"") -> 720 | H2: =IFERROR(INDEX('Semrush Data'!$D$2:$D$5000,MATCH(F2,'Semrush Data'!$A$2:$A$5000,0)),"") -> 16 | I2: vilvah | J2: =IFERROR(INDEX('Semrush Data'!$C$2:$C$5000,MATCH(I2,'Semrush Data'!$A$2:$A$5000,0)),"") -> 480 | K2: /collections/toner-for-dry-skin | L2: Vilvah Rosewater Facial Toner | M2: Vilvah Rosewater Facial Toner | Toner for Dry Skin | N2: =LEN(M2) -> 50 | O2: Buy Vilvah Rosewater Facial Toner, a natural toner for dry skin from Vilvah. Official UK partner: 100% authentic, shipped from the UK, free delivery over £50. | P2: =LEN(O2) -> 158 | Q2: Vilvah Rosewater Facial Toner is a natural toner for dry skin from Vilvah. 100% Natural Rose Hydrosol – Gently extracted from rose petals to preserve skin-loving nutrients. Hydrates & Balances pH – Restores skin's natural moisture and maintains optimal pH levels. Swansura is an official UK partner of Vilvah, so every order is 100% authentic and ships from the UK. | S2: Matched
A3: VD-002 | B3: Vilvah | C3: Hair growth oil | D3: Hair Oil | E3: Hair Thinning & Loss | F3: hair growth oil | G3: =IFERROR(INDEX('Semrush Data'!$C$2:$C$5000,MATCH(F3,'Semrush Data'!$A$2:$A$5000,0)),"") -> 5400 | H3: =IFERROR(INDEX('Semrush Data'!$D$2:$D$5000,MATCH(F3,'Semrush Data'!$A$2:$A$5000,0)),"") -> 21 | I3: vilvah | J3: =IFERROR(INDEX('Semrush Data'!$C$2:$C$5000,MATCH(I3,'Semrush Data'!$A$2:$A$5000,0)),"") -> 480 | K3: /collections/hair-growth-oil | L3: Vilvah Hair Growth Oil | M3: Vilvah Hair Growth Oil – Hair Growth Oil | Swansura | N3: =LEN(M3) -> 51 | O3: Buy Vilvah Hair Growth Oil, a natural hair growth oil from Vilvah. Official UK partner: 100% authentic, shipped from the UK, free delivery over £50. | P3: =LEN(O3) -> 148 | Q3: Vilvah Hair Growth Oil is a natural hair growth oil from Vilvah. Combines Pumpkin Seed, Kalonji, Castor, and Grapeseed Oils to nourish and revitalize hair. Enriched with Vitamin E and essential fatty acids to fortify hair from root to tip. Swansura is an official UK partner of Vilvah, so every order is 100% authentic and ships from the UK. | R3: vilvah hair growth oil review · vilvah hair growth oil how to use · vilvah hair growth oil benefits · vilvah hair growth oil india · vilvah hair growth oil review before and after · vilvah hair growth oil amazon | S3: Matched | T3: Review: source copy has medical-style claims (kept out of intro)
A4: VD-003 | B4: Vilvah | C4: Classic Goatmilk Soap | D4: Bath & Body Wash | E4: Body Cleansing | F4: natural body wash | G4: =IFERROR(INDEX('Semrush Data'!$C$2:$C$5000,MATCH(F4,'Semrush Data'!$A$2:$A$5000,0)),"") -> 1300 | H4: =IFERROR(INDEX('Semrush Data'!$D$2:$D$5000,MATCH(F4,'Semrush Data'!$A$2:$A$5000,0)),"") -> 19 | I4: vilvah | J4: =IFERROR(INDEX('Semrush Data'!$C$2:$C$5000,MATCH(I4,'Semrush Data'!$A$2:$A$5000,0)),"") -> 480 | K4: /collections/shower-gel-body-wash | L4: Vilvah Classic Goatmilk Soap | M4: Vilvah Classic Goatmilk Soap – Natural Body Wash | Swansura | N4: =LEN(M4) -> 59 | O4: Buy Vilvah Classic Goatmilk Soap, a natural body wash from Vilvah. Official UK partner: 100% authentic, shipped from the UK, free delivery over £50. | P4: =LEN(O4) -> 148 | Q4: Vilvah Classic Goatmilk Soap is a natural body wash from Vilvah. Swansura is an official UK partner of Vilvah, so every order is 100% authentic and ships from the UK. | S4: Not found – write from pack
A5: VD-004 | B5: Vilvah | C5: Deo Shot - Rose and Vanilla | D5: Deodorant | E5: Body Hydration | F5: natural deodorant | G5: =IFERROR(INDEX('Semrush Data'!$C$2:$C$5000,MATCH(F5,'Semrush Data'!$A$2:$A$5000,0)),"") -> 6600 | H5: =IFERROR(INDEX('Semrush Data'!$D$2:$D$5000,MATCH(F5,'Semrush Data'!$A$2:$A$5000,0)),"") -> 26 | I5: vilvah | J5: =IFERROR(INDEX('Semrush Data'!$C$2:$C$5000,MATCH(I5,'Semrush Data'!$A$2:$A$5000,0)),"") -> 480 | K5: /collections/deodorant | L5: Vilvah Deo Shot - Rose and Vanilla | M5: Vilvah Deo Shot - Rose and Vanilla | Natural Deodorant | N5: =LEN(M5) -> 54 | O5: Buy Vilvah Deo Shot - Rose and Vanilla, a natural deodorant from Vilvah. Official UK partner: 100% authentic, shipped from the UK, free delivery over £50. | P5: =LEN(O5) -> 154 | Q5: Vilvah Deo Shot - Rose and Vanilla is a natural deodorant from Vilvah. 24-Hour Odour Protection: Provides all-day freshness by neutralizing odour-causing bacteria. Crafted with virgin coconut oil, shea butter, and jojoba oil to nourish and protect the skin. Swansura is an official UK partner of Vilvah, so every order is 100% authentic and ships from the UK. | S5: Matched
A6: VD-005 | B6: Vilvah | C6: Skin finish Sunscreen SPF 50 | D6: SPF for Face | E6: Sun Protection | F6: natural sunscreen | G6: =IFERROR(INDEX('Semrush Data'!$C$2:$C$5000,MATCH(F6,'Semrush Data'!$A$2:$A$5000,0)),"") -> 3600 | H6: =IFERROR(INDEX('Semrush Data'!$D$2:$D$5000,MATCH(F6,'Semrush Data'!$A$2:$A$5000,0)),"") -> 24 | I6: vilvah | J6: =IFERROR(INDEX('Semrush Data'!$C$2:$C$5000,MATCH(I6,'Semrush Data'!$A$2:$A$5000,0)),"") -> 480 | K6: /collections/natural-sunscreen | L6: Vilvah Skin Finish Sunscreen SPF 50 | M6: Vilvah Skin Finish Sunscreen SPF 50 | Natural Sunscreen | N6: =LEN(M6) -> 55 | O6: Buy Vilvah Skin Finish Sunscreen SPF 50, a natural sunscreen from Vilvah. Official UK partner: 100% authentic, shipped from the UK, free delivery over £50. | P6: =LEN(O6) -> 155 | Q6: Vilvah Skin Finish Sunscreen SPF 50 is a natural sunscreen from Vilvah. Swansura is an official UK partner of Vilvah, so every order is 100% authentic and ships from the UK. | S6: Matched – no usable facts, add 1–2 from pack
A7: VD-006 | B7: Vilvah | C7: Milk Powder Face Wash | D7: Cleansers | E7: Skin Nourishment | F7: face wash for oily skin | G7: =IFERROR(INDEX('Semrush Data'!$C$2:$C$5000,MATCH(F7,'Semrush Data'!$A$2:$A$5000,0)),"") -> 1600 | H7: =IFERROR(INDEX('Semrush Data'!$D$2:$D$5000,MATCH(F7,'Semrush Data'!$A$2:$A$5000,0)),"") -> 33 | I7: vilvah | J7: =IFERROR(INDEX('Semrush Data'!$C$2:$C$5000,MATCH(I7,'Semrush Data'!$A$2:$A$5000,0)),"") -> 480 | K7: /collections/face-wash-for-oily-skin | L7: Vilvah Milk Powder Face Wash | M7: Vilvah Milk Powder Face Wash | Face Wash for Oily Skin | N7: =LEN(M7) -> 54 | O7: Vilvah Milk Powder Face Wash: a natural face wash for oily skin from Vilvah. Official UK partner: 100% authentic, shipped from the UK, free delivery over £50. | P7: =LEN(O7) -> 158 | Q7: Vilvah Milk Powder Face Wash is a natural face wash for oily skin from Vilvah. Hydrating & pH-balanced – infused with hyaluronic acid to retain moisture, with a skin-friendly pH of 6-7 so skin stays soft, not stripped. Powered by papain enzyme and rice husk powder to buff away dead skin gently. Swansura is an official UK partner of Vilvah, so every order is 100% authentic and ships from the UK. | R7: vilvah milk powder face wash review · vilvah milk powder face wash benefits · vilvah milk powder face wash price · vilvah milk powder face wash how to use · vilvah milk powder face wash and serum · vilvah milk powder face wash amazon | S7: Matched
A8: VD-007 | B8: Vilvah | C8: Ultra Moisturising Cream | D8: Moisturisers | E8: Dry Skin | F8: moisturiser for dry skin | G8: =IFERROR(INDEX('Semrush Data'!$C$2:$C$5000,MATCH(F8,'Semrush Data'!$A$2:$A$5000,0)),"") -> 2900 | H8: =IFERROR(INDEX('Semrush Data'!$D$2:$D$5000,MATCH(F8,'Semrush Data'!$A$2:$A$5000,0)),"") -> 29 | I8: vilvah | J8: =IFERROR(INDEX('Semrush Data'!$C$2:$C$5000,MATCH(I8,'Semrush Data'!$A$2:$A$5000,0)),"") -> 480 | K8: /collections/moisturiser-for-dry-skin | L8: Vilvah Ultra Moisturising Cream | M8: Vilvah Ultra Moisturising Cream | Moisturiser for Dry Skin | N8: =LEN(M8) -> 58 | O8: Buy Vilvah Ultra Moisturising Cream, a natural moisturiser for dry skin from Vilvah. Official UK partner, 100% authentic, free UK delivery over £50. | P8: =LEN(O8) -> 148 | Q8: Vilvah Ultra Moisturising Cream is a natural moisturiser for dry skin from Vilvah. Antioxidant-rich ingredients smooth rough patches, leaving the skin soft and supple. The non-greasy formula hydrates without clogging pores, suitable for all skin types. Swansura is an official UK partner of Vilvah, so every order is 100% authentic and ships from the UK. | S8: Matched | T8: Review: source copy has medical-style claims (kept out of intro)
A9: VD-008 | B9: Vilvah | C9: Classic Rose Goatmilk Soap | D9: Bath & Body Wash | E9: Body Cleansing | F9: natural body wash | G9: =IFERROR(INDEX('Semrush Data'!$C$2:$C$5000,MATCH(F9,'Semrush Data'!$A$2:$A$5000,0)),"") -> 1300 | H9: =IFERROR(INDEX('Semrush Data'!$D$2:$D$5000,MATCH(F9,'Semrush Data'!$A$2:$A$5000,0)),"") -> 19 | I9: vilvah | J9: =IFERROR(INDEX('Semrush Data'!$C$2:$C$5000,MATCH(I9,'Semrush Data'!$A$2:$A$5000,0)),"") -> 480 | K9: /collections/shower-gel-body-wash | L9: Vilvah Classic Rose Goatmilk Soap | M9: Vilvah Classic Rose Goatmilk Soap | Natural Body Wash | N9: =LEN(M9) -> 53 | O9: Buy Vilvah Classic Rose Goatmilk Soap, a natural body wash from Vilvah. Official UK partner: 100% authentic, shipped from the UK, free delivery over £50. | P9: =LEN(O9) -> 153 | Q9: Vilvah Classic Rose Goatmilk Soap is a natural body wash from Vilvah. Swansura is an official UK partner of Vilvah, so every order is 100% authentic and ships from the UK. | S9: Not found – write from pack
A10: VD-009 | B10: Vilvah | C10: Goat Milk Body Wash | D10: Bath & Body Wash | E10: Body Cleansing | F10: natural body wash | G10: =IFERROR(INDEX('Semrush Data'!$C$2:$C$5000,MATCH(F10,'Semrush Data'!$A$2:$A$5000,0)),"") -> 1300 | H10: =IFERROR(INDEX('Semrush Data'!$D$2:$D$5000,MATCH(F10,'Semrush Data'!$A$2:$A$5000,0)),"") -> 19 | I10: vilvah | J10: =IFERROR(INDEX('Semrush Data'!$C$2:$C$5000,MATCH(I10,'Semrush Data'!$A$2:$A$5000,0)),"") -> 480 | K10: /collections/shower-gel-body-wash | L10: Vilvah Goat Milk Body Wash | M10: Vilvah Goat Milk Body Wash – Natural Body Wash | Swansura | N10: =LEN(M10) -> 57 | O10: Buy Vilvah Goat Milk Body Wash, a natural body wash from Vilvah. Official UK partner: 100% authentic, shipped from the UK, free delivery over £50. | P10: =LEN(O10) -> 146 | Q10: Vilvah Goat Milk Body Wash is a natural body wash from Vilvah. Enriched with goat milk and virgin coconut oil, this body wash replenishes moisture, making it ideal for dry and sensitive skin types. Designed with a low-foam lather and a pH-balanced 5.5, ensuring a mild cleanse that maintains the skin's natural barrier. Swansura is an official UK partner of Vilvah, so every order is 100% authentic and ships from the UK. | R10: vilvah goat milk body wash review · vilvah goat milk body wash ingredients · vilvah goat milk body wash benefits · vilvah goat milk body soap · vilvah goat milk soap review | S10: Matched
A11: VD-010 | B11: Vilvah | C11: Rose Milk Lip Balm | D11: Lip Care | E11: Dry Lips | F11: lip balm for dry lips | G11: =IFERROR(INDEX('Semrush Data'!$C$2:$C$5000,MATCH(F11,'Semrush Data'!$A$2:$A$5000,0)),"") -> 1000 | H11: =IFERROR(INDEX('Semrush Data'!$D$2:$D$5000,MATCH(F11,'Semrush Data'!$A$2:$A$5000,0)),"") -> 41 | I11: vilvah | J11: =IFERROR(INDEX('Semrush Data'!$C$2:$C$5000,MATCH(I11,'Semrush Data'!$A$2:$A$5000,0)),"") -> 480 | K11: /collections/lip-balm-for-dry-lips | L11: Vilvah Rose Milk Lip Balm | M11: Vilvah Rose Milk Lip Balm – Lip Balm for Dry Lips | Swansura | N11: =LEN(M11) -> 60 | O11: Buy Vilvah Rose Milk Lip Balm, a natural lip balm for dry lips from Vilvah. Official UK partner: 100% authentic, shipped from the UK, free delivery over £50. | P11: =LEN(O11) -> 157 | Q11: Vilvah Rose Milk Lip Balm is a natural lip balm for dry lips from Vilvah. Swansura is an official UK partner of Vilvah, so every order is 100% authentic and ships from the UK. | R11: vilvah rose milk lip balm review · vilvah rose milk lip balm ingredients · vilvah rose milk lip balm price · vilvah lip balm review · vilvah lip balm price | S11: Not found – write from pack
A12: VD-011 | B12: Vilvah | C12: Charcoal Goatmilk Soap | D12: Bath & Body Wash | E12: Body Cleansing | F12: natural body wash | G12: =IFERROR(INDEX('Semrush Data'!$C$2:$C$5000,MATCH(F12,'Semrush Data'!$A$2:$A$5000,0)),"") -> 1300 | H12: =IFERROR(INDEX('Semrush Data'!$D$2:$D$5000,MATCH(F12,'Semrush Data'!$A$2:$A$5000,0)),"") -> 19 | I12: vilvah | J12: =IFERROR(INDEX('Semrush Data'!$C$2:$C$5000,MATCH(I12,'Semrush Data'!$A$2:$A$5000,0)),"") -> 480 | K12: /collections/shower-gel-body-wash | L12: Vilvah Charcoal Goatmilk Soap | M12: Vilvah Charcoal Goatmilk Soap – Natural Body Wash | Swansura | N12: =LEN(M12) -> 60 | O12: Buy Vilvah Charcoal Goatmilk Soap, a natural body wash from Vilvah. Official UK partner: 100% authentic, shipped from the UK, free delivery over £50. | P12: =LEN(O12) -> 149 | Q12: Vilvah Charcoal Goatmilk Soap is a natural body wash from Vilvah. Swansura is an official UK partner of Vilvah, so every order is 100% authentic and ships from the UK. | S12: Not found – write from pack
A13: VD-012 | B13: Vilvah | C13: Cream Conditioner | D13: Conditioner | E13: Hair Nourishment | F13: hair mask for dry hair | G13: =IFERROR(INDEX('Semrush Data'!$C$2:$C$5000,MATCH(F13,'Semrush Data'!$A$2:$A$5000,0)),"") -> 2400 | H13: =IFERROR(INDEX('Semrush Data'!$D$2:$D$5000,MATCH(F13,'Semrush Data'!$A$2:$A$5000,0)),"") -> 13 | I13: vilvah | J13: =IFERROR(INDEX('Semrush Data'!$C$2:$C$5000,MATCH(I13,'Semrush Data'!$A$2:$A$5000,0)),"") -> 480 | K13: /collections/hair-mask-for-dry-hair | L13: Vilvah Cream Conditioner | M13: Vilvah Cream Conditioner – Hair Mask for Dry Hair | Swansura | N13: =LEN(M13) -> 60 | O13: Buy Vilvah Cream Conditioner, a natural hair mask for dry hair from Vilvah. Official UK partner: 100% authentic, shipped from the UK, free delivery over £50. | P13: =LEN(O13) -> 157 | Q13: Vilvah Cream Conditioner is a natural hair mask for dry hair from Vilvah. Swansura is an official UK partner of Vilvah, so every order is 100% authentic and ships from the UK. | R13: vilvah cream conditioner review · vilvah cream conditioner ingredients · how to use vilvah cream conditioner · vilvah conditioner review | S13: Matched – no usable facts, add 1–2 from pack | T13: Review: source copy has medical-style claims (kept out of intro)
A14: VD-013 | B14: Vilvah | C14: Goat Milk Shampoo | D14: Shampoo | E14: Dry Skin | F14: natural shampoo | G14: =IFERROR(INDEX('Semrush Data'!$C$2:$C$5000,MATCH(F14,'Semrush Data'!$A$2:$A$5000,0)),"") -> 3600 | H14: =IFERROR(INDEX('Semrush Data'!$D$2:$D$5000,MATCH(F14,'Semrush Data'!$A$2:$A$5000,0)),"") -> 21 | I14: vilvah | J14: =IFERROR(INDEX('Semrush Data'!$C$2:$C$5000,MATCH(I14,'Semrush Data'!$A$2:$A$5000,0)),"") -> 480 | K14: /collections/natural-shampoo | L14: Vilvah Goat Milk Shampoo | M14: Vilvah Goat Milk Shampoo – Natural Shampoo | Swansura | N14: =LEN(M14) -> 53 | O14: Buy Vilvah Goat Milk Shampoo, a natural shampoo from Vilvah. Official UK partner: 100% authentic, shipped from the UK, free delivery over £50. | P14: =LEN(O14) -> 142 | Q14: Vilvah Goat Milk Shampoo is a natural shampoo from Vilvah. Perfect for dry, damaged, or chemically treated hair, this shampoo leaves the hair feeling clean, manageable, and naturally silky without feeling heavy. Swansura is an official UK partner of Vilvah, so every order is 100% authentic and ships from the UK. | R14: vilvah goat milk shampoo review · vilvah goat milk shampoo price · vilvah goat milk shampoo benefits · vilvah goat milk shampoo ingredients | S14: Matched | T14: Review: source copy has medical-style claims (kept out of intro)
A15: VD-014 | B15: Vilvah | C15: Honey Fix Face Wash | D15: Cleansers | E15: Skin Nourishment | F15: face wash for oily skin | G15: =IFERROR(INDEX('Semrush Data'!$C$2:$C$5000,MATCH(F15,'Semrush Data'!$A$2:$A$5000,0)),"") -> 1600 | H15: =IFERROR(INDEX('Semrush Data'!$D$2:$D$5000,MATCH(F15,'Semrush Data'!$A$2:$A$5000,0)),"") -> 33 | I15: vilvah | J15: =IFERROR(INDEX('Semrush Data'!$C$2:$C$5000,MATCH(I15,'Semrush Data'!$A$2:$A$5000,0)),"") -> 480 | K15: /collections/face-wash-for-oily-skin | L15: Vilvah Honey Fix Face Wash | M15: Vilvah Honey Fix Face Wash | Face Wash for Oily Skin | N15: =LEN(M15) -> 52 | O15: Buy Vilvah Honey Fix Face Wash, a natural face wash for oily skin from Vilvah. Official UK partner: 100% authentic, shipped from the UK, free delivery over £50. | P15: =LEN(O15) -> 160 | Q15: Vilvah Honey Fix Face Wash is a natural face wash for oily skin from Vilvah. Contains 10% raw honey plus fruit extracts (papaya, blackberry, orange peel) to gently exfoliate, brighten, and promote skin radiance. Features witch hazel and Gotu kola extracts to calm inflammation, soothe irritation, and minimize pores. Swansura is an official UK partner of Vilvah, so every order is 100% authentic and ships from the UK. | R15: vilvah honey fix face wash review | S15: Matched
A16: VD-015 | B16: Vilvah | C16: Lip Balm - Lemon | D16: Lip Care | E16: Dry Lips | F16: lip balm for dry lips | G16: =IFERROR(INDEX('Semrush Data'!$C$2:$C$5000,MATCH(F16,'Semrush Data'!$A$2:$A$5000,0)),"") -> 1000 | H16: =IFERROR(INDEX('Semrush Data'!$D$2:$D$5000,MATCH(F16,'Semrush Data'!$A$2:$A$5000,0)),"") -> 41 | I16: vilvah | J16: =IFERROR(INDEX('Semrush Data'!$C$2:$C$5000,MATCH(I16,'Semrush Data'!$A$2:$A$5000,0)),"") -> 480 | K16: /collections/lip-balm-for-dry-lips | L16: Vilvah Lip Balm - Lemon | M16: Vilvah Lip Balm - Lemon – Lip Balm for Dry Lips | Swansura | N16: =LEN(M16) -> 58 | O16: Buy Vilvah Lip Balm - Lemon, a natural lip balm for dry lips from Vilvah. Official UK partner: 100% authentic, shipped from the UK, free delivery over £50. | P16: =LEN(O16) -> 155 | Q16: Vilvah Lip Balm - Lemon is a natural lip balm for dry lips from Vilvah. Lightweight barrier that seals in hydration while letting lips breathe, helping softness last throughout the day. Vegan and free from parabens, sulfates, and synthetic fragrances, ideal for sensitive lips and daily use. Swansura is an official UK partner of Vilvah, so every order is 100% authentic and ships from the UK. | R16: vilvah lip balm lemon · vilvah lemon lip balm review · vilvah lip balm review · vilvah lip balm price | S16: Matched | T16: Review: source copy has medical-style claims (kept out of intro)
A17: VD-016 | B17: Vilvah | C17: Milk Body Lotion | D17: Body Cream & Lotions | E17: Dry Skin | F17: body lotion for dry skin | G17: =IFERROR(INDEX('Semrush Data'!$C$2:$C$5000,MATCH(F17,'Semrush Data'!$A$2:$A$5000,0)),"") -> 1300 | H17: =IFERROR(INDEX('Semrush Data'!$D$2:$D$5000,MATCH(F17,'Semrush Data'!$A$2:$A$5000,0)),"") -> 11 | I17: vilvah | J17: =IFERROR(INDEX('Semrush Data'!$C$2:$C$5000,MATCH(I17,'Semrush Data'!$A$2:$A$5000,0)),"") -> 480 | K17: /collections/body-lotion-for-dry-skin | L17: Vilvah Milk Body Lotion | M17: Vilvah Milk Body Lotion | Body Lotion for Dry Skin | N17: =LEN(M17) -> 50 | O17: Buy Vilvah Milk Body Lotion, a natural body lotion for dry skin from Vilvah. Official UK partner: 100% authentic, shipped from the UK, free delivery over £50. | P17: =LEN(O17) -> 158 | Q17: Vilvah Milk Body Lotion is a natural body lotion for dry skin from Vilvah. Infused with oat milk, ceramides, and olive squalane to hydrate and repair the skin barrier. Formulated without animal-derived ingredients and not tested on animals. Swansura is an official UK partner of Vilvah, so every order is 100% authentic and ships from the UK. | R17: vilvah milk body lotion review · vilvah milk body lotion price | S17: Matched
A18: VD-017 | B18: Vilvah | C18: Milk Face Toner | D18: Toners | E18: Dry Skin | F18: toner for dry skin | G18: =IFERROR(INDEX('Semrush Data'!$C$2:$C$5000,MATCH(F18,'Semrush Data'!$A$2:$A$5000,0)),"") -> 720 | H18: =IFERROR(INDEX('Semrush Data'!$D$2:$D$5000,MATCH(F18,'Semrush Data'!$A$2:$A$5000,0)),"") -> 16 | I18: vilvah | J18: =IFERROR(INDEX('Semrush Data'!$C$2:$C$5000,MATCH(I18,'Semrush Data'!$A$2:$A$5000,0)),"") -> 480 | K18: /collections/toner-for-dry-skin | L18: Vilvah Milk Face Toner | M18: Vilvah Milk Face Toner – Toner for Dry Skin | Swansura | N18: =LEN(M18) -> 54 | O18: Buy Vilvah Milk Face Toner, a natural toner for dry skin from Vilvah. Official UK partner: 100% authentic, shipped from the UK, free delivery over £50. | P18: =LEN(O18) -> 151 | Q18: Vilvah Milk Face Toner is a natural toner for dry skin from Vilvah. Formulated with Earth Marine Water to reduce pore size and provide a smoother skin texture. Effectively removes excess oil and impurities, leaving the skin feeling refreshed and clean. Swansura is an official UK partner of Vilvah, so every order is 100% authentic and ships from the UK. | R18: vilvah milk face toner review · vilvah toner review | S18: Matched | T18: Review: source copy has medical-style claims (kept out of intro)
A19: VD-018 | B19: Vilvah | C19: Milk Mud Mask | D19: Face Masks | E19: Skin Nourishment | F19: face mask | G19: =IFERROR(INDEX('Semrush Data'!$C$2:$C$5000,MATCH(F19,'Semrush Data'!$A$2:$A$5000,0)),"") -> 22200 | H19: =IFERROR(INDEX('Semrush Data'!$D$2:$D$5000,MATCH(F19,'Semrush Data'!$A$2:$A$5000,0)),"") -> 30 | I19: vilvah | J19: =IFERROR(INDEX('Semrush Data'!$C$2:$C$5000,MATCH(I19,'Semrush Data'!$A$2:$A$5000,0)),"") -> 480 | K19: /collections/face-mask | L19: Vilvah Milk Mud Mask | M19: Vilvah Milk Mud Mask | Face Mask | N19: =LEN(M19) -> 32 | O19: Buy Vilvah Milk Mud Mask, a natural face mask from Vilvah. Instantly brightens and rejuvenates dull, tanned skin. Free UK delivery over £50. | P19: =LEN(O19) -> 140 | Q19: Vilvah Milk Mud Mask is a natural face mask from Vilvah. Instantly brightens and rejuvenates dull, tanned skin. Controls excess oil and unclogs pores for a smoother complexion. Swansura is an official UK partner of Vilvah, so every order is 100% authentic and ships from the UK. | R19: vilvah milk mud mask review · vilvah milk mud mask benefits · vilvah milk mud mask ingredients · vilvah milk mud mask how to use · vilvah milk mud mask amazon · vilvah milk mud mask price | S19: Matched
A20: VD-019 | B20: Vilvah | C20: Wild Rose Facemask | D20: Face Masks | E20: Skin Nourishment | F20: face mask | G20: =IFERROR(INDEX('Semrush Data'!$C$2:$C$5000,MATCH(F20,'Semrush Data'!$A$2:$A$5000,0)),"") -> 22200 | H20: =IFERROR(INDEX('Semrush Data'!$D$2:$D$5000,MATCH(F20,'Semrush Data'!$A$2:$A$5000,0)),"") -> 30 | I20: vilvah | J20: =IFERROR(INDEX('Semrush Data'!$C$2:$C$5000,MATCH(I20,'Semrush Data'!$A$2:$A$5000,0)),"") -> 480 | K20: /collections/face-mask | L20: Vilvah Wild Rose Facemask | M20: Vilvah Wild Rose Facemask | Face Mask | N20: =LEN(M20) -> 37 | O20: Buy Vilvah Wild Rose Facemask, a natural face mask from Vilvah. Official UK partner: 100% authentic, shipped from the UK, free delivery over £50. | P20: =LEN(O20) -> 145 | Q20: Vilvah Wild Rose Facemask is a natural face mask from Vilvah. Swansura is an official UK partner of Vilvah, so every order is 100% authentic and ships from the UK. | S20: Not found – write from pack
A21: VD-020 | B21: Vilvah | C21: Aloe Vera Gel | D21: Moisturisers | E21: Skin Nourishment | F21: aloe vera gel | G21: =IFERROR(INDEX('Semrush Data'!$C$2:$C$5000,MATCH(F21,'Semrush Data'!$A$2:$A$5000,0)),"") -> 18100 | H21: =IFERROR(INDEX('Semrush Data'!$D$2:$D$5000,MATCH(F21,'Semrush Data'!$A$2:$A$5000,0)),"") -> 16 | I21: vilvah | J21: =IFERROR(INDEX('Semrush Data'!$C$2:$C$5000,MATCH(I21,'Semrush Data'!$A$2:$A$5000,0)),"") -> 480 | K21: /collections/moisturiser-for-dry-skin | L21: Vilvah Aloe Vera Gel | M21: Vilvah Aloe Vera Gel | Aloe Vera Gel | N21: =LEN(M21) -> 36 | O21: Buy Vilvah Aloe Vera Gel, a natural aloe vera gel from Vilvah. Official UK partner: 100% authentic, shipped from the UK, free delivery over £50. | P21: =LEN(O21) -> 144 | Q21: Vilvah Aloe Vera Gel is a natural aloe vera gel from Vilvah. Pure, cold-stabilised aloe vera juice preserves nutrients for maximum soothing power, ideal for sensitive or sunburned skin. Hydrates deeply without greasy residue; absorbs quickly to leave skin soft, smooth and comfortably moisturised. Swansura is an official UK partner of Vilvah, so every order is 100% authentic and ships from the UK. | R21: vilvah aloe vera gel review · vilvah aloe vera gel ingredients · vilvah aloe vera gel benefits · vilvah aloe vera gel price · vilvah aloe vera gel how to use · vilvah aloe vera gel india | S21: Matched | T21: Review: source copy has medical-style claims (kept out of intro)
A22: VD-021 | B22: Vilvah | C22: Anti-dandruff Hair oil | D22: Hair Oil | E22: Anti-Dandruff | F22: hair growth oil | G22: =IFERROR(INDEX('Semrush Data'!$C$2:$C$5000,MATCH(F22,'Semrush Data'!$A$2:$A$5000,0)),"") -> 5400 | H22: =IFERROR(INDEX('Semrush Data'!$D$2:$D$5000,MATCH(F22,'Semrush Data'!$A$2:$A$5000,0)),"") -> 21 | I22: vilvah | J22: =IFERROR(INDEX('Semrush Data'!$C$2:$C$5000,MATCH(I22,'Semrush Data'!$A$2:$A$5000,0)),"") -> 480 | K22: /collections/hair-growth-oil | L22: Vilvah Anti-dandruff Hair Oil | M22: Vilvah Anti-dandruff Hair Oil – Hair Growth Oil | Swansura | N22: =LEN(M22) -> 58 | O22: Buy Vilvah Anti-dandruff Hair Oil, a natural hair growth oil from Vilvah. Official UK partner: 100% authentic, shipped from the UK, free delivery over £50. | P22: =LEN(O22) -> 155 | Q22: Vilvah Anti-dandruff Hair Oil is a natural hair growth oil from Vilvah. Combines Tea Tree, Neem, Peppermint, and Amla oils to effectively tackle dandruff and nourish the scalp. Calms irritation and balances scalp pH, providing relief from itching and discomfort. Swansura is an official UK partner of Vilvah, so every order is 100% authentic and ships from the UK. | R22: vilvah anti dandruff hair oil review · vilvah anti dandruff oil review | S22: Matched | T22: Review: source copy has medical-style claims (kept out of intro)
A23: VD-022 | B23: Vilvah | C23: Anti-Frizz Hair Serum | D23: Hair Serums | E23: Frizzy Hair | F23: hair serum for frizzy hair | G23: =IFERROR(INDEX('Semrush Data'!$C$2:$C$5000,MATCH(F23,'Semrush Data'!$A$2:$A$5000,0)),"") -> 1000 | H23: =IFERROR(INDEX('Semrush Data'!$D$2:$D$5000,MATCH(F23,'Semrush Data'!$A$2:$A$5000,0)),"") -> 27 | I23: vilvah | J23: =IFERROR(INDEX('Semrush Data'!$C$2:$C$5000,MATCH(I23,'Semrush Data'!$A$2:$A$5000,0)),"") -> 480 | K23: /collections/hair-serum-for-frizzy-hair | L23: Vilvah Anti-Frizz Hair Serum | M23: Vilvah Anti-Frizz Hair Serum | Hair Serum for Frizzy Hair | N23: =LEN(M23) -> 57 | O23: Buy Vilvah Anti-Frizz Hair Serum, a natural hair serum for frizzy hair from Vilvah. Official UK partner, 100% authentic, free UK delivery over £50. | P23: =LEN(O23) -> 147 | Q23: Vilvah Anti-Frizz Hair Serum is a natural hair serum for frizzy hair from Vilvah. Enriched with Black Seed Oil and Hibiscus Oil to nourish and strengthen hair, reducing split ends and breakage. Hibiscus and Arnica Oils impart intense smoothness and a glossy finish, making every day a great hair day. Swansura is an official UK partner of Vilvah, so every order is 100% authentic and ships from the UK. | R23: vilvah anti frizz hair serum review · vilvah anti frizz hair serum price · how to use vilvah anti frizz hair serum | S23: Matched | T23: Review: source copy has medical-style claims (kept out of intro)
A24: VD-023 | B24: Vilvah | C24: Better Ageing Serum | D24: Serums | E24: Anti-Ageing | F24: face serum | G24: =IFERROR(INDEX('Semrush Data'!$C$2:$C$5000,MATCH(F24,'Semrush Data'!$A$2:$A$5000,0)),"") -> 9900 | H24: =IFERROR(INDEX('Semrush Data'!$D$2:$D$5000,MATCH(F24,'Semrush Data'!$A$2:$A$5000,0)),"") -> 30 | I24: vilvah | J24: =IFERROR(INDEX('Semrush Data'!$C$2:$C$5000,MATCH(I24,'Semrush Data'!$A$2:$A$5000,0)),"") -> 480 | K24: /collections/face-serum | L24: Vilvah Better Ageing Serum | M24: Vilvah Better Ageing Serum – Face Serum | Swansura | N24: =LEN(M24) -> 50 | O24: Buy Vilvah Better Ageing Serum, a natural face serum from Vilvah. Official UK partner: 100% authentic, shipped from the UK, free delivery over £50. | P24: =LEN(O24) -> 147 | Q24: Vilvah Better Ageing Serum is a natural face serum from Vilvah. Formulated with plant-derived antioxidants that help neutralise free radicals and slow down visible signs of ageing. Enhances skin elasticity and firmness through natural tightening agents without harsh chemicals. Swansura is an official UK partner of Vilvah, so every order is 100% authentic and ships from the UK. | R24: vilvah better ageing serum review | S24: Matched
A25: VD-024 | B25: Vilvah | C25: Charcoal Facemask | D25: Face Masks | E25: Oily Skin | F25: face mask for oily skin | G25: =IFERROR(INDEX('Semrush Data'!$C$2:$C$5000,MATCH(F25,'Semrush Data'!$A$2:$A$5000,0)),"") -> 210 | H25: =IFERROR(INDEX('Semrush Data'!$D$2:$D$5000,MATCH(F25,'Semrush Data'!$A$2:$A$5000,0)),"") -> 20 | I25: vilvah | J25: =IFERROR(INDEX('Semrush Data'!$C$2:$C$5000,MATCH(I25,'Semrush Data'!$A$2:$A$5000,0)),"") -> 480 | K25: /collections/face-mask-for-oily-skin | L25: Vilvah Charcoal Facemask | M25: Vilvah Charcoal Facemask | Face Mask for Oily Skin | N25: =LEN(M25) -> 50 | O25: Buy Vilvah Charcoal Facemask, a natural face mask for oily skin from Vilvah. Official UK partner: 100% authentic, shipped from the UK, free delivery over £50. | P25: =LEN(O25) -> 158 | Q25: Vilvah Charcoal Facemask is a natural face mask for oily skin from Vilvah. Swansura is an official UK partner of Vilvah, so every order is 100% authentic and ships from the UK. | S25: Not found – write from pack
A26: VD-025 | B26: Vilvah | C26: Cookie n Cream Body Mask | D26: Body Cream & Lotions | E26: Dry Skin | F26: body lotion for dry skin | G26: =IFERROR(INDEX('Semrush Data'!$C$2:$C$5000,MATCH(F26,'Semrush Data'!$A$2:$A$5000,0)),"") -> 1300 | H26: =IFERROR(INDEX('Semrush Data'!$D$2:$D$5000,MATCH(F26,'Semrush Data'!$A$2:$A$5000,0)),"") -> 11 | I26: vilvah | J26: =IFERROR(INDEX('Semrush Data'!$C$2:$C$5000,MATCH(I26,'Semrush Data'!$A$2:$A$5000,0)),"") -> 480 | K26: /collections/body-lotion-for-dry-skin | L26: Vilvah Cookie N Cream Body Mask | M26: Vilvah Cookie N Cream Body Mask | Body Lotion for Dry Skin | N26: =LEN(M26) -> 58 | O26: Buy Vilvah Cookie N Cream Body Mask, a natural body lotion for dry skin from Vilvah. Official UK partner, 100% authentic, free UK delivery over £50. | P26: =LEN(O26) -> 148 | Q26: Vilvah Cookie N Cream Body Mask is a natural body lotion for dry skin from Vilvah. Enriched with almond milk and coffee, known for their moisturizing and antioxidant properties. Regular use promotes a smoother, more even-toned complexion. Swansura is an official UK partner of Vilvah, so every order is 100% authentic and ships from the UK. | S26: Matched | T26: Review: source copy has medical-style claims (kept out of intro)
A27: VD-026 | B27: Vilvah | C27: Cookie n Cream Body Polish | D27: Body Scrub & Exfoliators | E27: Dull Skin | F27: body scrub | G27: =IFERROR(INDEX('Semrush Data'!$C$2:$C$5000,MATCH(F27,'Semrush Data'!$A$2:$A$5000,0)),"") -> 12100 | H27: =IFERROR(INDEX('Semrush Data'!$D$2:$D$5000,MATCH(F27,'Semrush Data'!$A$2:$A$5000,0)),"") -> 18 | I27: vilvah | J27: =IFERROR(INDEX('Semrush Data'!$C$2:$C$5000,MATCH(I27,'Semrush Data'!$A$2:$A$5000,0)),"") -> 480 | K27: /collections/body-scrub | L27: Vilvah Cookie N Cream Body Polish | M27: Vilvah Cookie N Cream Body Polish – Body Scrub | Swansura | N27: =LEN(M27) -> 57 | O27: Buy Vilvah Cookie N Cream Body Polish, a natural body scrub from Vilvah. Official UK partner: 100% authentic, shipped from the UK, free delivery over £50. | P27: =LEN(O27) -> 154 | Q27: Vilvah Cookie N Cream Body Polish is a natural body scrub from Vilvah. Coffee powder effectively sloughs away dead skin cells, unclogs pores, and fades tan, revealing smoother skin. Infused with almond milk, shea butter, and argan oil to nourish and moisturize, leaving skin soft and supple. Swansura is an official UK partner of Vilvah, so every order is 100% authentic and ships from the UK. | S27: Matched | T27: Review: source copy has medical-style claims (kept out of intro)
A28: VD-027 | B28: Vilvah | C28: Cream Face Wash (Fragrance free) | D28: Cleansers | E28: Skin Nourishment | F28: face wash for dry skin | G28: =IFERROR(INDEX('Semrush Data'!$C$2:$C$5000,MATCH(F28,'Semrush Data'!$A$2:$A$5000,0)),"") -> 1600 | H28: =IFERROR(INDEX('Semrush Data'!$D$2:$D$5000,MATCH(F28,'Semrush Data'!$A$2:$A$5000,0)),"") -> 29 | I28: vilvah | J28: =IFERROR(INDEX('Semrush Data'!$C$2:$C$5000,MATCH(I28,'Semrush Data'!$A$2:$A$5000,0)),"") -> 480 | K28: /collections/face-wash-for-dry-skin | L28: Vilvah Cream Face Wash (Fragrance Free) | M28: Vilvah Cream Face Wash (Fragrance Free) | Swansura UK | N28: =LEN(M28) -> 53 | O28: Buy Vilvah Cream Face Wash (Fragrance Free), a natural face wash for dry skin from Vilvah. Official UK partner, 100% authentic, free UK delivery over £50. | P28: =LEN(O28) -> 154 | Q28: Vilvah Cream Face Wash (Fragrance Free) is a natural face wash for dry skin from Vilvah. Swansura is an official UK partner of Vilvah, so every order is 100% authentic and ships from the UK. | S28: Not found – write from pack
A29: VD-028 | B29: Vilvah | C29: Cucumber, Curd & Mint Soap | D29: Bath & Body Wash | E29: Body Cleansing | F29: natural body wash | G29: =IFERROR(INDEX('Semrush Data'!$C$2:$C$5000,MATCH(F29,'Semrush Data'!$A$2:$A$5000,0)),"") -> 1300 | H29: =IFERROR(INDEX('Semrush Data'!$D$2:$D$5000,MATCH(F29,'Semrush Data'!$A$2:$A$5000,0)),"") -> 19 | I29: vilvah | J29: =IFERROR(INDEX('Semrush Data'!$C$2:$C$5000,MATCH(I29,'Semrush Data'!$A$2:$A$5000,0)),"") -> 480 | K29: /collections/shower-gel-body-wash | L29: Vilvah Cucumber, Curd & Mint Soap | M29: Vilvah Cucumber, Curd & Mint Soap | Natural Body Wash | N29: =LEN(M29) -> 53 | O29: Buy Vilvah Cucumber, Curd & Mint Soap, a natural body wash from Vilvah. Official UK partner: 100% authentic, shipped from the UK, free delivery over £50. | P29: =LEN(O29) -> 153 | Q29: Vilvah Cucumber, Curd & Mint Soap is a natural body wash from Vilvah. Swansura is an official UK partner of Vilvah, so every order is 100% authentic and ships from the UK. | S29: Not found – write from pack
A30: VD-029 | B30: Vilvah | C30: Deo shot - Lavender and Sage | D30: Deodorant | E30: Body Hydration | F30: natural deodorant | G30: =IFERROR(INDEX('Semrush Data'!$C$2:$C$5000,MATCH(F30,'Semrush Data'!$A$2:$A$5000,0)),"") -> 6600 | H30: =IFERROR(INDEX('Semrush Data'!$D$2:$D$5000,MATCH(F30,'Semrush Data'!$A$2:$A$5000,0)),"") -> 26 | I30: vilvah | J30: =IFERROR(INDEX('Semrush Data'!$C$2:$C$5000,MATCH(I30,'Semrush Data'!$A$2:$A$5000,0)),"") -> 480 | K30: /collections/deodorant | L30: Vilvah Deo Shot - Lavender and Sage | M30: Vilvah Deo Shot - Lavender and Sage | Natural Deodorant | N30: =LEN(M30) -> 55 | O30: Buy Vilvah Deo Shot - Lavender and Sage, a natural deodorant from Vilvah. Official UK partner: 100% authentic, shipped from the UK, free delivery over £50. | P30: =LEN(O30) -> 155 | Q30: Vilvah Deo Shot - Lavender and Sage is a natural deodorant from Vilvah. Made with natural ingredients, free from alcohol, silicones, and synthetic fragrances, ensuring a gentle experience for sensitive skin. Offers up to 24 hours of odour protection, keeping you feeling fresh throughout the day. Swansura is an official UK partner of Vilvah, so every order is 100% authentic and ships from the UK. | S30: Matched
A31: VD-030 | B31: Vilvah | C31: Foot Cream | D31: Body Cream & Lotions | E31: Dry Skin | F31: foot cream | G31: =IFERROR(INDEX('Semrush Data'!$C$2:$C$5000,MATCH(F31,'Semrush Data'!$A$2:$A$5000,0)),"") -> 5400 | H31: =IFERROR(INDEX('Semrush Data'!$D$2:$D$5000,MATCH(F31,'Semrush Data'!$A$2:$A$5000,0)),"") -> 22 | I31: vilvah | J31: =IFERROR(INDEX('Semrush Data'!$C$2:$C$5000,MATCH(I31,'Semrush Data'!$A$2:$A$5000,0)),"") -> 480 | K31: /collections/body-lotion-for-dry-skin | L31: Vilvah Foot Cream | M31: Vilvah Foot Cream | Foot Cream | N31: =LEN(M31) -> 30 | O31: Buy Vilvah Foot Cream, a natural foot cream from Vilvah. Official UK partner: 100% authentic, shipped from the UK, free delivery over £50. | P31: =LEN(O31) -> 138 | Q31: Vilvah Foot Cream is a natural foot cream from Vilvah. Dermatologically tested and free from harsh chemicals, making it safe for sensitive skin. Ideal for both men and women; apply daily for best results, especially before bedtime. Swansura is an official UK partner of Vilvah, so every order is 100% authentic and ships from the UK. | R31: vilvah foot cream review · vilvah foot cream price · vilvah foot cream ingredients | S31: Matched | T31: Review: source copy has medical-style claims (kept out of intro)
A32: VD-031 | B32: Vilvah | C32: Goat Milk Hair Mask | D32: Hair Masks | E32: Dry Hair | F32: hair mask for dry hair | G32: =IFERROR(INDEX('Semrush Data'!$C$2:$C$5000,MATCH(F32,'Semrush Data'!$A$2:$A$5000,0)),"") -> 2400 | H32: =IFERROR(INDEX('Semrush Data'!$D$2:$D$5000,MATCH(F32,'Semrush Data'!$A$2:$A$5000,0)),"") -> 13 | I32: vilvah | J32: =IFERROR(INDEX('Semrush Data'!$C$2:$C$5000,MATCH(I32,'Semrush Data'!$A$2:$A$5000,0)),"") -> 480 | K32: /collections/hair-mask-for-dry-hair | L32: Vilvah Goat Milk Hair Mask | M32: Vilvah Goat Milk Hair Mask | Hair Mask for Dry Hair | N32: =LEN(M32) -> 51 | O32: Buy Vilvah Goat Milk Hair Mask, a natural hair mask for dry hair from Vilvah. Official UK partner: 100% authentic, shipped from the UK, free delivery over £50. | P32: =LEN(O32) -> 159 | Q32: Vilvah Goat Milk Hair Mask is a natural hair mask for dry hair from Vilvah. Enriched with goat milk and ceramides to restore the hair’s barrier, reduce breakage, and strengthen from root to tip. Lightweight yet intensely nourishing formula tames flyaways and smooths frizz without leaving hair greasy. Swansura is an official UK partner of Vilvah, so every order is 100% authentic and ships from the UK. | R32: vilvah goat milk hair mask review · vilvah goat milk hair mask ingredients · how to use vilvah goat milk hair mask · how to use vilvah hair mask | S32: Matched
A33: VD-032 | B33: Vilvah | C33: Hair growth oil | D33: Hair Oil | E33: Hair Thinning & Loss | F33: hair growth oil | G33: =IFERROR(INDEX('Semrush Data'!$C$2:$C$5000,MATCH(F33,'Semrush Data'!$A$2:$A$5000,0)),"") -> 5400 | H33: =IFERROR(INDEX('Semrush Data'!$D$2:$D$5000,MATCH(F33,'Semrush Data'!$A$2:$A$5000,0)),"") -> 21 | I33: vilvah | J33: =IFERROR(INDEX('Semrush Data'!$C$2:$C$5000,MATCH(I33,'Semrush Data'!$A$2:$A$5000,0)),"") -> 480 | K33: /collections/hair-growth-oil | L33: Vilvah Hair Growth Oil | M33: Vilvah Hair Growth Oil – Hair Growth Oil | Swansura | N33: =LEN(M33) -> 51 | O33: Buy Vilvah Hair Growth Oil, a natural hair growth oil from Vilvah. Official UK partner: 100% authentic, shipped from the UK, free delivery over £50. | P33: =LEN(O33) -> 148 | Q33: Vilvah Hair Growth Oil is a natural hair growth oil from Vilvah. Combines Pumpkin Seed, Kalonji, Castor, and Grapeseed Oils to nourish and revitalize hair. Enriched with Vitamin E and essential fatty acids to fortify hair from root to tip. Swansura is an official UK partner of Vilvah, so every order is 100% authentic and ships from the UK. | R33: vilvah hair growth oil review · vilvah hair growth oil how to use · vilvah hair growth oil benefits · vilvah hair growth oil india · vilvah hair growth oil review before and after · vilvah hair growth oil amazon | S33: Matched | T33: Review: source copy has medical-style claims (kept out of intro)
A34: VD-033 | B34: Vilvah | C34: Hair growth oil | D34: Hair Oil | E34: Hair Thinning & Loss | F34: hair growth oil | G34: =IFERROR(INDEX('Semrush Data'!$C$2:$C$5000,MATCH(F34,'Semrush Data'!$A$2:$A$5000,0)),"") -> 5400 | H34: =IFERROR(INDEX('Semrush Data'!$D$2:$D$5000,MATCH(F34,'Semrush Data'!$A$2:$A$5000,0)),"") -> 21 | I34: vilvah | J34: =IFERROR(INDEX('Semrush Data'!$C$2:$C$5000,MATCH(I34,'Semrush Data'!$A$2:$A$5000,0)),"") -> 480 | K34: /collections/hair-growth-oil | L34: Vilvah Hair Growth Oil | M34: Vilvah Hair Growth Oil – Hair Growth Oil | Swansura | N34: =LEN(M34) -> 51 | O34: Buy Vilvah Hair Growth Oil, a natural hair growth oil from Vilvah. Official UK partner: 100% authentic, shipped from the UK, free delivery over £50. | P34: =LEN(O34) -> 148 | Q34: Vilvah Hair Growth Oil is a natural hair growth oil from Vilvah. Combines Pumpkin Seed, Kalonji, Castor, and Grapeseed Oils to nourish and revitalize hair. Enriched with Vitamin E and essential fatty acids to fortify hair from root to tip. Swansura is an official UK partner of Vilvah, so every order is 100% authentic and ships from the UK. | R34: vilvah hair growth oil review · vilvah hair growth oil how to use · vilvah hair growth oil benefits · vilvah hair growth oil india · vilvah hair growth oil review before and after · vilvah hair growth oil amazon | S34: Matched | T34: Review: source copy has medical-style claims (kept out of intro)
A35: VD-034 | B35: Vilvah | C35: Herbal Shampoo (Dandruff Control) | D35: Shampoo | E35: Anti-Dandruff | F35: shampoo for dandruff | G35: =IFERROR(INDEX('Semrush Data'!$C$2:$C$5000,MATCH(F35,'Semrush Data'!$A$2:$A$5000,0)),"") -> 1600 | H35: =IFERROR(INDEX('Semrush Data'!$D$2:$D$5000,MATCH(F35,'Semrush Data'!$A$2:$A$5000,0)),"") -> 31 | I35: vilvah | J35: =IFERROR(INDEX('Semrush Data'!$C$2:$C$5000,MATCH(I35,'Semrush Data'!$A$2:$A$5000,0)),"") -> 480 | K35: /collections/shampoo-for-dandruff | L35: Vilvah Herbal Shampoo (Dandruff Control) | M35: Vilvah Herbal Shampoo (Dandruff Control) | Swansura UK | N35: =LEN(M35) -> 54 | O35: Buy Vilvah Herbal Shampoo (Dandruff Control), a natural shampoo for dandruff from Vilvah. Official UK partner, 100% authentic, free UK delivery over £50. | P35: =LEN(O35) -> 153 | Q35: Vilvah Herbal Shampoo (Dandruff Control) is a natural shampoo for dandruff from Vilvah. Crafted with Neem, Tea Tree, Rosemary, and Black Pepper to effectively combat dandruff and soothe scalp irritation. Contains no parabens, sulfates, or artificial fragrances, making it a safe choice for sensitive scalps. Swansura is an official UK partner of Vilvah, so every order is 100% authentic and ships from the UK. | R35: vilvah herbal shampoo dandruff control | S35: Matched | T35: Review: source copy has medical-style claims (kept out of intro)
A36: VD-035 | B36: Vilvah | C36: Lip Balm - Grapefruit | D36: Lip Care | E36: Dry Lips | F36: lip balm for dry lips | G36: =IFERROR(INDEX('Semrush Data'!$C$2:$C$5000,MATCH(F36,'Semrush Data'!$A$2:$A$5000,0)),"") -> 1000 | H36: =IFERROR(INDEX('Semrush Data'!$D$2:$D$5000,MATCH(F36,'Semrush Data'!$A$2:$A$5000,0)),"") -> 41 | I36: vilvah | J36: =IFERROR(INDEX('Semrush Data'!$C$2:$C$5000,MATCH(I36,'Semrush Data'!$A$2:$A$5000,0)),"") -> 480 | K36: /collections/lip-balm-for-dry-lips | L36: Vilvah Lip Balm - Grapefruit | M36: Vilvah Lip Balm - Grapefruit | Lip Balm for Dry Lips | N36: =LEN(M36) -> 52 | O36: Buy Vilvah Lip Balm - Grapefruit, a natural lip balm for dry lips from Vilvah. Official UK partner: 100% authentic, shipped from the UK, free delivery over £50. | P36: =LEN(O36) -> 160 | Q36: Vilvah Lip Balm - Grapefruit is a natural lip balm for dry lips from Vilvah. Swansura is an official UK partner of Vilvah, so every order is 100% authentic and ships from the UK. | R36: vilvah lip balm grapefruit · vilvah grapefruit lip balm review · vilvah grapefruit lip balm 10g · vilvah grapefruit lip balm benefits · vilvah grapefruit lip balm amazon · vilvah lip balm review | S36: Not found – write from pack
A37: VD-036 | B37: Vilvah | C37: Lip Scrub | D37: Lip Care | E37: Lip Exfoliation | F37: lip scrub | G37: =IFERROR(INDEX('Semrush Data'!$C$2:$C$5000,MATCH(F37,'Semrush Data'!$A$2:$A$5000,0)),"") -> 5400 | H37: =IFERROR(INDEX('Semrush Data'!$D$2:$D$5000,MATCH(F37,'Semrush Data'!$A$2:$A$5000,0)),"") -> 16 | I37: vilvah | J37: =IFERROR(INDEX('Semrush Data'!$C$2:$C$5000,MATCH(I37,'Semrush Data'!$A$2:$A$5000,0)),"") -> 480 | K37: /collections/lip-scrub | L37: Vilvah Lip Scrub | M37: Vilvah Lip Scrub | Lip Scrub | N37: =LEN(M37) -> 28 | O37: Buy Vilvah Lip Scrub, a natural lip scrub from Vilvah. Official UK partner: 100% authentic, shipped from the UK, free delivery over £50. | P37: =LEN(O37) -> 136 | Q37: Vilvah Lip Scrub is a natural lip scrub from Vilvah. Gentle sugar grains exfoliate dead skin without irritation, leaving lips smooth, soft and supple. Free from alcohol, silicones, surfactants and harmful aldehydes—designed for sensitive lips and daily care. Swansura is an official UK partner of Vilvah, so every order is 100% authentic and ships from the UK. | R37: vilvah lip scrub how to use · vilvah lip scrub review · vilvah lip scrub ingredients · vilvah lip scrub and lip balm · vilvah lip balm price · vilvah lip balm review | S37: Matched | T37: Review: source copy has medical-style claims (kept out of intro)
A38: VD-037 | B38: Vilvah | C38: Men's Comb / Detangling Comb | D38: Hair Accessories | E38: Sun Protection | F38: natural skincare | G38: =IFERROR(INDEX('Semrush Data'!$C$2:$C$5000,MATCH(F38,'Semrush Data'!$A$2:$A$5000,0)),"") -> 1600 | H38: =IFERROR(INDEX('Semrush Data'!$D$2:$D$5000,MATCH(F38,'Semrush Data'!$A$2:$A$5000,0)),"") -> 55 | I38: vilvah | J38: =IFERROR(INDEX('Semrush Data'!$C$2:$C$5000,MATCH(I38,'Semrush Data'!$A$2:$A$5000,0)),"") -> 480 | K38: /collections/natural-skincare | L38: Vilvah Men's Comb / Detangling Comb | M38: Vilvah Men's Comb / Detangling Comb | Natural Skincare | N38: =LEN(M38) -> 54 | O38: Buy Vilvah Men's Comb / Detangling Comb, natural skincare from Vilvah. Official UK partner: 100% authentic, shipped from the UK, free delivery over £50. | P38: =LEN(O38) -> 152 | Q38: Vilvah Men's Comb / Detangling Comb is natural skincare from Vilvah. Swansura is an official UK partner of Vilvah, so every order is 100% authentic and ships from the UK. | S38: Not found – write from pack
A39: VD-038 | B39: Vilvah | C39: Milk Drops Brightening Serum 20ml | D39: Serums | E39: Dull Skin | F39: skincare for dull skin | G39: =IFERROR(INDEX('Semrush Data'!$C$2:$C$5000,MATCH(F39,'Semrush Data'!$A$2:$A$5000,0)),"") -> 320 | H39: =IFERROR(INDEX('Semrush Data'!$D$2:$D$5000,MATCH(F39,'Semrush Data'!$A$2:$A$5000,0)),"") -> 10 | I39: vilvah | J39: =IFERROR(INDEX('Semrush Data'!$C$2:$C$5000,MATCH(I39,'Semrush Data'!$A$2:$A$5000,0)),"") -> 480 | K39: /collections/dull-skin | L39: Vilvah Milk Drops Brightening Serum | M39: Vilvah Milk Drops Brightening Serum | Skincare for Dull Skin | N39: =LEN(M39) -> 60 | O39: Buy Vilvah Milk Drops Brightening Serum, natural skincare for dull skin from Vilvah. Official UK partner, 100% authentic, free UK delivery over £50. | P39: =LEN(O39) -> 148 | Q39: Vilvah Milk Drops Brightening Serum is natural skincare for dull skin from Vilvah. Swansura is an official UK partner of Vilvah, so every order is 100% authentic and ships from the UK. | R39: vilvah milk drops brightening serum review · vilvah milk drops brightening serum how to use · vilvah milk drops brightening serum ingredients · vilvah milk drops brightening serum benefits | S39: Matched – no usable facts, add 1–2 from pack | T39: Review: source copy has medical-style claims (kept out of intro)
A40: VD-039 | B40: Vilvah | C40: Milk Drops Brightening Serum 40ml | D40: Serums | E40: Dull Skin | F40: skincare for dull skin | G40: =IFERROR(INDEX('Semrush Data'!$C$2:$C$5000,MATCH(F40,'Semrush Data'!$A$2:$A$5000,0)),"") -> 320 | H40: =IFERROR(INDEX('Semrush Data'!$D$2:$D$5000,MATCH(F40,'Semrush Data'!$A$2:$A$5000,0)),"") -> 10 | I40: vilvah | J40: =IFERROR(INDEX('Semrush Data'!$C$2:$C$5000,MATCH(I40,'Semrush Data'!$A$2:$A$5000,0)),"") -> 480 | K40: /collections/dull-skin | L40: Vilvah Milk Drops Brightening Serum | M40: Vilvah Milk Drops Brightening Serum | Skincare for Dull Skin | N40: =LEN(M40) -> 60 | O40: Buy Vilvah Milk Drops Brightening Serum, natural skincare for dull skin from Vilvah. Official UK partner, 100% authentic, free UK delivery over £50. | P40: =LEN(O40) -> 148 | Q40: Vilvah Milk Drops Brightening Serum is natural skincare for dull skin from Vilvah. Swansura is an official UK partner of Vilvah, so every order is 100% authentic and ships from the UK. | R40: vilvah milk drops brightening serum review · vilvah milk drops brightening serum how to use · vilvah milk drops brightening serum ingredients · vilvah milk drops brightening serum benefits | S40: Matched – no usable facts, add 1–2 from pack | T40: Review: source copy has medical-style claims (kept out of intro)
A41: VD-040 | B41: Vilvah | C41: Milk Lip Balm SPF 30 PA+++ | D41: Lip Care | E41: Dry Lips | F41: spf lip balm | G41: =IFERROR(INDEX('Semrush Data'!$C$2:$C$5000,MATCH(F41,'Semrush Data'!$A$2:$A$5000,0)),"") -> 4400 | H41: =IFERROR(INDEX('Semrush Data'!$D$2:$D$5000,MATCH(F41,'Semrush Data'!$A$2:$A$5000,0)),"") -> 30 | I41: vilvah | J41: =IFERROR(INDEX('Semrush Data'!$C$2:$C$5000,MATCH(I41,'Semrush Data'!$A$2:$A$5000,0)),"") -> 480 | K41: /collections/lip-balm-for-dry-lips | L41: Vilvah Milk Lip Balm SPF 30 PA | M41: Vilvah Milk Lip Balm SPF 30 PA – Spf Lip Balm | Swansura | N41: =LEN(M41) -> 56 | O41: Buy Vilvah Milk Lip Balm SPF 30 PA, a natural spf lip balm from Vilvah. Official UK partner: 100% authentic, shipped from the UK, free delivery over £50. | P41: =LEN(O41) -> 153 | Q41: Vilvah Milk Lip Balm SPF 30 PA is a natural spf lip balm from Vilvah. Enriched with soy milk, soy butter, shea butter, and kokum butter to deliver intense hydration and nourishment. Contains mineral-based UV filters like titanium dioxide and zinc oxide, ensuring safe and effective sun defense. Swansura is an official UK partner of Vilvah, so every order is 100% authentic and ships from the UK. | S41: Matched | T41: Review: source copy has medical-style claims (kept out of intro)
A42: VD-041 | B42: Vilvah | C42: Neem Wood Comb (With Handle) | D42: Hair Accessories | E42: Hair Nourishment | F42: natural skincare | G42: =IFERROR(INDEX('Semrush Data'!$C$2:$C$5000,MATCH(F42,'Semrush Data'!$A$2:$A$5000,0)),"") -> 1600 | H42: =IFERROR(INDEX('Semrush Data'!$D$2:$D$5000,MATCH(F42,'Semrush Data'!$A$2:$A$5000,0)),"") -> 55 | I42: vilvah | J42: =IFERROR(INDEX('Semrush Data'!$C$2:$C$5000,MATCH(I42,'Semrush Data'!$A$2:$A$5000,0)),"") -> 480 | K42: /collections/natural-skincare | L42: Vilvah Neem Wood Comb (With Handle) | M42: Vilvah Neem Wood Comb (With Handle) | Natural Skincare | N42: =LEN(M42) -> 54 | O42: Buy Vilvah Neem Wood Comb (With Handle), natural skincare from Vilvah. Official UK partner: 100% authentic, shipped from the UK, free delivery over £50. | P42: =LEN(O42) -> 152 | Q42: Vilvah Neem Wood Comb (With Handle) is natural skincare from Vilvah. Made from 100% herbal Indian neem wood, this handcrafted comb is biodegradable and an environmentally conscious choice for your hair care routine. Designed to smoothly glide through hair, minimizing breakage and split ends, ensuring a pain-free detangling experience. Swansura is an official UK partner of Vilvah, so every order is 100% authentic and ships from the UK. | S42: Matched | T42: Review: source copy has medical-style claims (kept out of intro)
A43: VD-042 | B43: Vilvah | C43: Neem Wood Comb(Fine and wide tooth) | D43: Hair Accessories | E43: Hair Nourishment | F43: natural skincare | G43: =IFERROR(INDEX('Semrush Data'!$C$2:$C$5000,MATCH(F43,'Semrush Data'!$A$2:$A$5000,0)),"") -> 1600 | H43: =IFERROR(INDEX('Semrush Data'!$D$2:$D$5000,MATCH(F43,'Semrush Data'!$A$2:$A$5000,0)),"") -> 55 | I43: vilvah | J43: =IFERROR(INDEX('Semrush Data'!$C$2:$C$5000,MATCH(I43,'Semrush Data'!$A$2:$A$5000,0)),"") -> 480 | K43: /collections/natural-skincare | L43: Vilvah Neem Wood Comb(Fine and Wide Tooth) | M43: Vilvah Neem Wood Comb(Fine and Wide Tooth) | Swansura UK | N43: =LEN(M43) -> 56 | O43: Buy Vilvah Neem Wood Comb(Fine and Wide Tooth), natural skincare from Vilvah. Official UK partner: 100% authentic, shipped from the UK, free delivery over £50. | P43: =LEN(O43) -> 159 | Q43: Vilvah Neem Wood Comb(Fine and Wide Tooth) is natural skincare from Vilvah. Swansura is an official UK partner of Vilvah, so every order is 100% authentic and ships from the UK. | S43: Not found – write from pack
A44: VD-043 | B44: Vilvah | C44: Under Eye Cream (Dark Circles Control) | D44: Moisturisers | E44: Dark Circles | F44: moisturiser for dry skin | G44: =IFERROR(INDEX('Semrush Data'!$C$2:$C$5000,MATCH(F44,'Semrush Data'!$A$2:$A$5000,0)),"") -> 2900 | H44: =IFERROR(INDEX('Semrush Data'!$D$2:$D$5000,MATCH(F44,'Semrush Data'!$A$2:$A$5000,0)),"") -> 29 | I44: vilvah | J44: =IFERROR(INDEX('Semrush Data'!$C$2:$C$5000,MATCH(I44,'Semrush Data'!$A$2:$A$5000,0)),"") -> 480 | K44: /collections/moisturiser-for-dry-skin | L44: Vilvah Under Eye Cream (Dark Circles Control) | M44: Vilvah Under Eye Cream (Dark Circles Control) | Swansura UK | N44: =LEN(M44) -> 59 | O44: Buy Vilvah Under Eye Cream (Dark Circles Control), a natural moisturiser for dry skin from Vilvah. 100% authentic, shipped from the UK, free delivery over £50. | P44: =LEN(O44) -> 159 | Q44: Vilvah Under Eye Cream (Dark Circles Control) is a natural moisturiser for dry skin from Vilvah. Swansura is an official UK partner of Vilvah, so every order is 100% authentic and ships from the UK. | R44: vilvah under eye cream dark circles control · how to use vilvah under eye cream | S44: Not found – write from pack
A45: VD-044 | B45: Vilvah | C45: Filter Kaapi Lip Balm | D45: Lip Care | E45: Dry Lips | F45: lip balm for dry lips | G45: =IFERROR(INDEX('Semrush Data'!$C$2:$C$5000,MATCH(F45,'Semrush Data'!$A$2:$A$5000,0)),"") -> 1000 | H45: =IFERROR(INDEX('Semrush Data'!$D$2:$D$5000,MATCH(F45,'Semrush Data'!$A$2:$A$5000,0)),"") -> 41 | I45: vilvah | J45: =IFERROR(INDEX('Semrush Data'!$C$2:$C$5000,MATCH(I45,'Semrush Data'!$A$2:$A$5000,0)),"") -> 480 | K45: /collections/lip-balm-for-dry-lips | L45: Vilvah Filter Kaapi Lip Balm | M45: Vilvah Filter Kaapi Lip Balm | Lip Balm for Dry Lips | N45: =LEN(M45) -> 52 | O45: Buy Vilvah Filter Kaapi Lip Balm, a natural lip balm for dry lips from Vilvah. Official UK partner: 100% authentic, shipped from the UK, free delivery over £50. | P45: =LEN(O45) -> 160 | Q45: Vilvah Filter Kaapi Lip Balm is a natural lip balm for dry lips from Vilvah. Swansura is an official UK partner of Vilvah, so every order is 100% authentic and ships from the UK. | R45: vilvah lip balm review · vilvah lip balm price | S45: Not found – write from pack
A46: VD-045 | B46: Vilvah | C46: Mango Shake Lip Balm | D46: Lip Care | E46: Dry Lips | F46: lip balm for dry lips | G46: =IFERROR(INDEX('Semrush Data'!$C$2:$C$5000,MATCH(F46,'Semrush Data'!$A$2:$A$5000,0)),"") -> 1000 | H46: =IFERROR(INDEX('Semrush Data'!$D$2:$D$5000,MATCH(F46,'Semrush Data'!$A$2:$A$5000,0)),"") -> 41 | I46: vilvah | J46: =IFERROR(INDEX('Semrush Data'!$C$2:$C$5000,MATCH(I46,'Semrush Data'!$A$2:$A$5000,0)),"") -> 480 | K46: /collections/lip-balm-for-dry-lips | L46: Vilvah Mango Shake Lip Balm | M46: Vilvah Mango Shake Lip Balm | Lip Balm for Dry Lips | N46: =LEN(M46) -> 51 | O46: Buy Vilvah Mango Shake Lip Balm, a natural lip balm for dry lips from Vilvah. Official UK partner: 100% authentic, shipped from the UK, free delivery over £50. | P46: =LEN(O46) -> 159 | Q46: Vilvah Mango Shake Lip Balm is a natural lip balm for dry lips from Vilvah. Swansura is an official UK partner of Vilvah, so every order is 100% authentic and ships from the UK. | R46: vilvah lip balm review · vilvah lip balm price | S46: Not found – write from pack
A47: VD-046 | B47: Vilvah | C47: Cream Bun Lip Balm | D47: Lip Care | E47: Dry Lips | F47: lip balm for dry lips | G47: =IFERROR(INDEX('Semrush Data'!$C$2:$C$5000,MATCH(F47,'Semrush Data'!$A$2:$A$5000,0)),"") -> 1000 | H47: =IFERROR(INDEX('Semrush Data'!$D$2:$D$5000,MATCH(F47,'Semrush Data'!$A$2:$A$5000,0)),"") -> 41 | I47: vilvah | J47: =IFERROR(INDEX('Semrush Data'!$C$2:$C$5000,MATCH(I47,'Semrush Data'!$A$2:$A$5000,0)),"") -> 480 | K47: /collections/lip-balm-for-dry-lips | L47: Vilvah Cream Bun Lip Balm | M47: Vilvah Cream Bun Lip Balm – Lip Balm for Dry Lips | Swansura | N47: =LEN(M47) -> 60 | O47: Buy Vilvah Cream Bun Lip Balm, a natural lip balm for dry lips from Vilvah. Official UK partner: 100% authentic, shipped from the UK, free delivery over £50. | P47: =LEN(O47) -> 157 | Q47: Vilvah Cream Bun Lip Balm is a natural lip balm for dry lips from Vilvah. Swansura is an official UK partner of Vilvah, so every order is 100% authentic and ships from the UK. | R47: vilvah cream bun lip balm review · vilvah lip balm price · vilvah lip balm review | S47: Not found – write from pack
A48: VD-047 | B48: Vilvah | C48: Vilvah Milk Body Kit | D48: Gift Sets & Combos | E48: Dry Skin | F48: skincare for dry skin | G48: =IFERROR(INDEX('Semrush Data'!$C$2:$C$5000,MATCH(F48,'Semrush Data'!$A$2:$A$5000,0)),"") -> 1300 | H48: =IFERROR(INDEX('Semrush Data'!$D$2:$D$5000,MATCH(F48,'Semrush Data'!$A$2:$A$5000,0)),"") -> 16 | I48: vilvah | J48: =IFERROR(INDEX('Semrush Data'!$C$2:$C$5000,MATCH(I48,'Semrush Data'!$A$2:$A$5000,0)),"") -> 480 | K48: /collections/dry-skin | L48: Vilvah Milk Body Kit | M48: Vilvah Milk Body Kit – Skincare for Dry Skin | Swansura | N48: =LEN(M48) -> 55 | O48: Buy Vilvah Milk Body Kit, natural skincare for dry skin from Vilvah. Official UK partner: 100% authentic, shipped from the UK, free delivery over £50. | P48: =LEN(O48) -> 150 | Q48: Vilvah Milk Body Kit is natural skincare for dry skin from Vilvah. Goat Milk Body Wash cleanses and hydrates with a soothing vanilla scent. Milk Body Lotion provides 48 hours of intense hydration and barrier protection. Swansura is an official UK partner of Vilvah, so every order is 100% authentic and ships from the UK. | S48: Matched
A49: VD-048 | B49: Vilvah | C49: Vilvah Foot Cream and Body Lotion Kit | D49: Gift Sets & Combos | E49: Dry Skin | F49: skincare for dry skin | G49: =IFERROR(INDEX('Semrush Data'!$C$2:$C$5000,MATCH(F49,'Semrush Data'!$A$2:$A$5000,0)),"") -> 1300 | H49: =IFERROR(INDEX('Semrush Data'!$D$2:$D$5000,MATCH(F49,'Semrush Data'!$A$2:$A$5000,0)),"") -> 16 | I49: vilvah | J49: =IFERROR(INDEX('Semrush Data'!$C$2:$C$5000,MATCH(I49,'Semrush Data'!$A$2:$A$5000,0)),"") -> 480 | K49: /collections/dry-skin | L49: Vilvah Foot Cream and Body Lotion Kit | M49: Vilvah Foot Cream and Body Lotion Kit | Vilvah UK | Swansura | N49: =LEN(M49) -> 60 | O49: Buy Vilvah Foot Cream and Body Lotion Kit, natural skincare for dry skin from Vilvah. Official UK partner, 100% authentic, free UK delivery over £50. | P49: =LEN(O49) -> 149 | Q49: Vilvah Foot Cream and Body Lotion Kit is natural skincare for dry skin from Vilvah. Swansura is an official UK partner of Vilvah, so every order is 100% authentic and ships from the UK. | S49: Not found – write from pack
A50: VD-049 | B50: Vilvah | C50: Vilvah Milk Face Kit | D50: Gift Sets & Combos | E50: Dry Skin | F50: skincare for dry skin | G50: =IFERROR(INDEX('Semrush Data'!$C$2:$C$5000,MATCH(F50,'Semrush Data'!$A$2:$A$5000,0)),"") -> 1300 | H50: =IFERROR(INDEX('Semrush Data'!$D$2:$D$5000,MATCH(F50,'Semrush Data'!$A$2:$A$5000,0)),"") -> 16 | I50: vilvah | J50: =IFERROR(INDEX('Semrush Data'!$C$2:$C$5000,MATCH(I50,'Semrush Data'!$A$2:$A$5000,0)),"") -> 480 | K50: /collections/dry-skin | L50: Vilvah Milk Face Kit | M50: Vilvah Milk Face Kit – Skincare for Dry Skin | Swansura | N50: =LEN(M50) -> 55 | O50: Buy Vilvah Milk Face Kit, natural skincare for dry skin from Vilvah. Milk Mud Mask banishes tan lines and renews complexion. Free UK delivery over £50. | P50: =LEN(O50) -> 151 | Q50: Vilvah Milk Face Kit is natural skincare for dry skin from Vilvah. Milk Mud Mask banishes tan lines and renews complexion. Milk Drops Brightening Serum smooths uneven skin texture and adds a dewy glow. Swansura is an official UK partner of Vilvah, so every order is 100% authentic and ships from the UK. | S50: Matched
A51: VD-050 | B51: Vilvah | C51: oil control kit | D51: Gift Sets & Combos | E51: Oily Skin | F51: face wash for oily skin | G51: =IFERROR(INDEX('Semrush Data'!$C$2:$C$5000,MATCH(F51,'Semrush Data'!$A$2:$A$5000,0)),"") -> 1600 | H51: =IFERROR(INDEX('Semrush Data'!$D$2:$D$5000,MATCH(F51,'Semrush Data'!$A$2:$A$5000,0)),"") -> 33 | I51: vilvah | J51: =IFERROR(INDEX('Semrush Data'!$C$2:$C$5000,MATCH(I51,'Semrush Data'!$A$2:$A$5000,0)),"") -> 480 | K51: /collections/face-wash-for-oily-skin | L51: Vilvah Oil Control Kit | M51: Vilvah Oil Control Kit – Face Wash for Oily Skin | Swansura | N51: =LEN(M51) -> 59 | O51: Buy Vilvah Oil Control Kit, a natural face wash for oily skin from Vilvah. Official UK partner: 100% authentic, shipped from the UK, free delivery over £50. | P51: =LEN(O51) -> 156 | Q51: Vilvah Oil Control Kit is a natural face wash for oily skin from Vilvah. Swansura is an official UK partner of Vilvah, so every order is 100% authentic and ships from the UK. | S51: Matched – no usable facts, add 1–2 from pack | T51: Review: source copy has medical-style claims (kept out of intro)
A52: VD-051 | B52: Vilvah | C52: Vilvah Sensitive Skin Kit | D52: Gift Sets & Combos | E52: Sensitive Skin | F52: skincare gift set | G52: =IFERROR(INDEX('Semrush Data'!$C$2:$C$5000,MATCH(F52,'Semrush Data'!$A$2:$A$5000,0)),"") -> 3600 | H52: =IFERROR(INDEX('Semrush Data'!$D$2:$D$5000,MATCH(F52,'Semrush Data'!$A$2:$A$5000,0)),"") -> 22 | I52: vilvah | J52: =IFERROR(INDEX('Semrush Data'!$C$2:$C$5000,MATCH(I52,'Semrush Data'!$A$2:$A$5000,0)),"") -> 480 | K52: /collections/gifts-for-her | L52: Vilvah Sensitive Skin Kit | M52: Vilvah Sensitive Skin Kit – Skincare Gift Set | Swansura | N52: =LEN(M52) -> 56 | O52: Buy Vilvah Sensitive Skin Kit, natural skincare gift set from Vilvah. Steam-distilled Rose Toner calms and balances sensitive skin. Free UK delivery over £50. | P52: =LEN(O52) -> 158 | Q52: Vilvah Sensitive Skin Kit is natural skincare gift set from Vilvah. Steam-distilled Rose Toner calms and balances sensitive skin. Aloe Vera Gel soothes discomfort and restores moisture. Swansura is an official UK partner of Vilvah, so every order is 100% authentic and ships from the UK. | S52: Matched
A53: VD-052 | B53: Vilvah | C53: Vilvah Anti‑Acne Kit | D53: Gift Sets & Combos | E53: Acne & Blemishes | F53: face wash for oily skin | G53: =IFERROR(INDEX('Semrush Data'!$C$2:$C$5000,MATCH(F53,'Semrush Data'!$A$2:$A$5000,0)),"") -> 1600 | H53: =IFERROR(INDEX('Semrush Data'!$D$2:$D$5000,MATCH(F53,'Semrush Data'!$A$2:$A$5000,0)),"") -> 33 | I53: vilvah | J53: =IFERROR(INDEX('Semrush Data'!$C$2:$C$5000,MATCH(I53,'Semrush Data'!$A$2:$A$5000,0)),"") -> 480 | K53: /collections/face-wash-for-oily-skin | L53: Vilvah Anti‑Acne Kit | M53: Vilvah Anti‑Acne Kit – Face Wash for Oily Skin | Swansura | N53: =LEN(M53) -> 57 | O53: Buy Vilvah Anti‑Acne Kit, a natural face wash for oily skin from Vilvah. Official UK partner: 100% authentic, shipped from the UK, free delivery over £50. | P53: =LEN(O53) -> 154 | Q53: Vilvah Anti‑Acne Kit is a natural face wash for oily skin from Vilvah. Complete Anti-Acne Kit – 2-step combo with Honey-Fix Face Cleanser and Aloe Vera Gel for acne-prone and oily skin. Gentle Daily Skincare – Cleanses deeply without dryness; hydrates and soothes without clogging pores. Swansura is an official UK partner of Vilvah, so every order is 100% authentic and ships from the UK. | S53: Matched | T53: Review: source copy has medical-style claims (kept out of intro)
A54: VD-053 | B54: Vilvah | C54: Vilvah Anti‑Dandruff Haircare Kit | D54: Gift Sets & Combos | E54: Anti-Dandruff | F54: shampoo for dandruff | G54: =IFERROR(INDEX('Semrush Data'!$C$2:$C$5000,MATCH(F54,'Semrush Data'!$A$2:$A$5000,0)),"") -> 1600 | H54: =IFERROR(INDEX('Semrush Data'!$D$2:$D$5000,MATCH(F54,'Semrush Data'!$A$2:$A$5000,0)),"") -> 31 | I54: vilvah | J54: =IFERROR(INDEX('Semrush Data'!$C$2:$C$5000,MATCH(I54,'Semrush Data'!$A$2:$A$5000,0)),"") -> 480 | K54: /collections/shampoo-for-dandruff | L54: Vilvah Anti‑Dandruff Haircare Kit | M54: Vilvah Anti‑Dandruff Haircare Kit | Shampoo for Dandruff | N54: =LEN(M54) -> 56 | O54: Vilvah Anti‑Dandruff Haircare Kit: a natural shampoo for dandruff from Vilvah. Official UK partner: 100% authentic, shipped from the UK, free delivery over £50. | P54: =LEN(O54) -> 160 | Q54: Vilvah Anti‑Dandruff Haircare Kit is a natural shampoo for dandruff from Vilvah. Swansura is an official UK partner of Vilvah, so every order is 100% authentic and ships from the UK. | S54: Matched – no usable facts, add 1–2 from pack | T54: Review: source copy has medical-style claims (kept out of intro)
A55: VD-054 | B55: Vilvah | C55: Vilvah Sun Protection Kit | D55: Gift Sets & Combos | E55: Sun Protection | F55: natural sunscreen | G55: =IFERROR(INDEX('Semrush Data'!$C$2:$C$5000,MATCH(F55,'Semrush Data'!$A$2:$A$5000,0)),"") -> 3600 | H55: =IFERROR(INDEX('Semrush Data'!$D$2:$D$5000,MATCH(F55,'Semrush Data'!$A$2:$A$5000,0)),"") -> 24 | I55: vilvah | J55: =IFERROR(INDEX('Semrush Data'!$C$2:$C$5000,MATCH(I55,'Semrush Data'!$A$2:$A$5000,0)),"") -> 480 | K55: /collections/natural-sunscreen | L55: Vilvah Sun Protection Kit | M55: Vilvah Sun Protection Kit – Natural Sunscreen | Swansura | N55: =LEN(M55) -> 56 | O55: Buy Vilvah Sun Protection Kit, a natural sunscreen from Vilvah. SPF 50 Face Sunscreen provides broad-spectrum UVA & UVB protection. Free UK delivery over £50. | P55: =LEN(O55) -> 158 | Q55: Vilvah Sun Protection Kit is a natural sunscreen from Vilvah. SPF 50 Face Sunscreen provides broad-spectrum UVA & UVB protection. SPF 30 Lip Balm hydrates lips and offers gentle sun protection. Swansura is an official UK partner of Vilvah, so every order is 100% authentic and ships from the UK. | S55: Matched
A56: VD-055 | B56: Vilvah | C56: Vilvah Skin Brightening Kit | D56: Gift Sets & Combos | E56: Dull Skin | F56: skincare for dull skin | G56: =IFERROR(INDEX('Semrush Data'!$C$2:$C$5000,MATCH(F56,'Semrush Data'!$A$2:$A$5000,0)),"") -> 320 | H56: =IFERROR(INDEX('Semrush Data'!$D$2:$D$5000,MATCH(F56,'Semrush Data'!$A$2:$A$5000,0)),"") -> 10 | I56: vilvah | J56: =IFERROR(INDEX('Semrush Data'!$C$2:$C$5000,MATCH(I56,'Semrush Data'!$A$2:$A$5000,0)),"") -> 480 | K56: /collections/dull-skin | L56: Vilvah Skin Brightening Kit | M56: Vilvah Skin Brightening Kit | Skincare for Dull Skin | N56: =LEN(M56) -> 52 | O56: Buy Vilvah Skin Brightening Kit, natural skincare for dull skin from Vilvah. Official UK partner: 100% authentic, shipped from the UK, free delivery over £50. | P56: =LEN(O56) -> 158 | Q56: Vilvah Skin Brightening Kit is natural skincare for dull skin from Vilvah. Skin finish sunscreen SPF 50 PA+++ offers broad spectrum protection with a non-greasy, no white cast formula. Ultra-lightweight, water-based textures ideal for layering under makeup or for oily/combination skin. Swansura is an official UK partner of Vilvah, so every order is 100% authentic and ships from the UK. | S56: Matched | T56: Review: source copy has medical-style claims (kept out of intro)
A57: VD-056 | B57: Vilvah | C57: Vilvah Night Repair Kit | D57: Gift Sets & Combos | E57: Damaged Skin Barrier | F57: skincare gift set | G57: =IFERROR(INDEX('Semrush Data'!$C$2:$C$5000,MATCH(F57,'Semrush Data'!$A$2:$A$5000,0)),"") -> 3600 | H57: =IFERROR(INDEX('Semrush Data'!$D$2:$D$5000,MATCH(F57,'Semrush Data'!$A$2:$A$5000,0)),"") -> 22 | I57: vilvah | J57: =IFERROR(INDEX('Semrush Data'!$C$2:$C$5000,MATCH(I57,'Semrush Data'!$A$2:$A$5000,0)),"") -> 480 | K57: /collections/gifts-for-her | L57: Vilvah Night Repair Kit | M57: Vilvah Night Repair Kit – Skincare Gift Set | Swansura | N57: =LEN(M57) -> 54 | O57: Buy Vilvah Night Repair Kit, natural skincare gift set from Vilvah. Official UK partner: 100% authentic, shipped from the UK, free delivery over £50. | P57: =LEN(O57) -> 149 | Q57: Vilvah Night Repair Kit is natural skincare gift set from Vilvah. Better Ageing Serum enriched with Bakuchiol and Natural Peptides to combat signs of aging. Under Eye Cream formulated with Bamboo Extract and Goji Berry to reduce puffiness and dark circles. Swansura is an official UK partner of Vilvah, so every order is 100% authentic and ships from the UK. | S57: Matched | T57: Review: source copy has medical-style claims (kept out of intro)
A58: VD-057 | B58: Vilvah | C58: Vilvah AM PM Serum Kit | D58: Gift Sets & Combos | E58: Dull Skin | F58: skincare for dull skin | G58: =IFERROR(INDEX('Semrush Data'!$C$2:$C$5000,MATCH(F58,'Semrush Data'!$A$2:$A$5000,0)),"") -> 320 | H58: =IFERROR(INDEX('Semrush Data'!$D$2:$D$5000,MATCH(F58,'Semrush Data'!$A$2:$A$5000,0)),"") -> 10 | I58: vilvah | J58: =IFERROR(INDEX('Semrush Data'!$C$2:$C$5000,MATCH(I58,'Semrush Data'!$A$2:$A$5000,0)),"") -> 480 | K58: /collections/dull-skin | L58: Vilvah AM PM Serum Kit | M58: Vilvah AM PM Serum Kit – Skincare for Dull Skin | Swansura | N58: =LEN(M58) -> 58 | O58: Buy Vilvah AM PM Serum Kit, natural skincare for dull skin from Vilvah. Official UK partner: 100% authentic, shipped from the UK, free delivery over £50. | P58: =LEN(O58) -> 153 | Q58: Vilvah AM PM Serum Kit is natural skincare for dull skin from Vilvah. Lightweight and easy to layer, this duo is suitable for everyday use and works well for dull, uneven, or tired-looking skin. Swansura is an official UK partner of Vilvah, so every order is 100% authentic and ships from the UK. | S58: Matched | T58: Review: source copy has medical-style claims (kept out of intro)
A59: VD-058 | B59: Vilvah | C59: Vilvah Better Ageing Kit | D59: Gift Sets & Combos | E59: Anti-Ageing | F59: skincare gift set | G59: =IFERROR(INDEX('Semrush Data'!$C$2:$C$5000,MATCH(F59,'Semrush Data'!$A$2:$A$5000,0)),"") -> 3600 | H59: =IFERROR(INDEX('Semrush Data'!$D$2:$D$5000,MATCH(F59,'Semrush Data'!$A$2:$A$5000,0)),"") -> 22 | I59: vilvah | J59: =IFERROR(INDEX('Semrush Data'!$C$2:$C$5000,MATCH(I59,'Semrush Data'!$A$2:$A$5000,0)),"") -> 480 | K59: /collections/gifts-for-her | L59: Vilvah Better Ageing Kit | M59: Vilvah Better Ageing Kit – Skincare Gift Set | Swansura | N59: =LEN(M59) -> 55 | O59: Buy Vilvah Better Ageing Kit, natural skincare gift set from Vilvah. Official UK partner: 100% authentic, shipped from the UK, free delivery over £50. | P59: =LEN(O59) -> 150 | Q59: Vilvah Better Ageing Kit is natural skincare gift set from Vilvah. Bakuchiol and natural peptides reduce fine lines and improve skin texture. Ultra Moisturising Cream provides lasting moisture without greasiness. Swansura is an official UK partner of Vilvah, so every order is 100% authentic and ships from the UK. | S59: Matched
A60: VD-059 | B60: Vilvah | C60: Vilvah AM Brightening kit | D60: Gift Sets & Combos | E60: Dull Skin | F60: skincare for dull skin | G60: =IFERROR(INDEX('Semrush Data'!$C$2:$C$5000,MATCH(F60,'Semrush Data'!$A$2:$A$5000,0)),"") -> 320 | H60: =IFERROR(INDEX('Semrush Data'!$D$2:$D$5000,MATCH(F60,'Semrush Data'!$A$2:$A$5000,0)),"") -> 10 | I60: vilvah | J60: =IFERROR(INDEX('Semrush Data'!$C$2:$C$5000,MATCH(I60,'Semrush Data'!$A$2:$A$5000,0)),"") -> 480 | K60: /collections/dull-skin | L60: Vilvah AM Brightening Kit | M60: Vilvah AM Brightening Kit | Skincare for Dull Skin | N60: =LEN(M60) -> 50 | O60: Buy Vilvah AM Brightening Kit, natural skincare for dull skin from Vilvah. Official UK partner: 100% authentic, shipped from the UK, free delivery over £50. | P60: =LEN(O60) -> 156 | Q60: Vilvah AM Brightening Kit is natural skincare for dull skin from Vilvah. Perfect for daily morning skincare, this kit helps refresh tired-looking skin, improve overall texture, and leave the face feeling soft, balanced, and naturally luminous. Swansura is an official UK partner of Vilvah, so every order is 100% authentic and ships from the UK. | S60: Matched | T60: Review: source copy has medical-style claims (kept out of intro)
A61: VD-060 | B61: Vilvah | C61: Vilvah Tan Protection kit | D61: Gift Sets & Combos | E61: Sun Protection | F61: natural sunscreen | G61: =IFERROR(INDEX('Semrush Data'!$C$2:$C$5000,MATCH(F61,'Semrush Data'!$A$2:$A$5000,0)),"") -> 3600 | H61: =IFERROR(INDEX('Semrush Data'!$D$2:$D$5000,MATCH(F61,'Semrush Data'!$A$2:$A$5000,0)),"") -> 24 | I61: vilvah | J61: =IFERROR(INDEX('Semrush Data'!$C$2:$C$5000,MATCH(I61,'Semrush Data'!$A$2:$A$5000,0)),"") -> 480 | K61: /collections/natural-sunscreen | L61: Vilvah Tan Protection Kit | M61: Vilvah Tan Protection Kit – Natural Sunscreen | Swansura | N61: =LEN(M61) -> 56 | O61: Buy Vilvah Tan Protection Kit, a natural sunscreen from Vilvah. Official UK partner: 100% authentic, shipped from the UK, free delivery over £50. | P61: =LEN(O61) -> 145 | Q61: Vilvah Tan Protection Kit is a natural sunscreen from Vilvah. Swansura is an official UK partner of Vilvah, so every order is 100% authentic and ships from the UK. | S61: Matched – no usable facts, add 1–2 from pack | T61: Review: source copy has medical-style claims (kept out of intro)
A62: VD-061 | B62: Vilvah | C62: Vilvah skin radiance kit | D62: Gift Sets & Combos | E62: Dull Skin | F62: skincare for dull skin | G62: =IFERROR(INDEX('Semrush Data'!$C$2:$C$5000,MATCH(F62,'Semrush Data'!$A$2:$A$5000,0)),"") -> 320 | H62: =IFERROR(INDEX('Semrush Data'!$D$2:$D$5000,MATCH(F62,'Semrush Data'!$A$2:$A$5000,0)),"") -> 10 | I62: vilvah | J62: =IFERROR(INDEX('Semrush Data'!$C$2:$C$5000,MATCH(I62,'Semrush Data'!$A$2:$A$5000,0)),"") -> 480 | K62: /collections/dull-skin | L62: Vilvah Skin Radiance Kit | M62: Vilvah Skin Radiance Kit – Skincare for Dull Skin | Swansura | N62: =LEN(M62) -> 60 | O62: Buy Vilvah Skin Radiance Kit, natural skincare for dull skin from Vilvah. Official UK partner: 100% authentic, shipped from the UK, free delivery over £50. | P62: =LEN(O62) -> 155 | Q62: Vilvah Skin Radiance Kit is natural skincare for dull skin from Vilvah. Swansura is an official UK partner of Vilvah, so every order is 100% authentic and ships from the UK. | S62: Matched – no usable facts, add 1–2 from pack | T62: Review: source copy has medical-style claims (kept out of intro)
A63: VD-062 | B63: Vilvah | C63: Vilvah Pore Minimising Kit | D63: Gift Sets & Combos | E63: Blackheads & Pores | F63: skincare gift set | G63: =IFERROR(INDEX('Semrush Data'!$C$2:$C$5000,MATCH(F63,'Semrush Data'!$A$2:$A$5000,0)),"") -> 3600 | H63: =IFERROR(INDEX('Semrush Data'!$D$2:$D$5000,MATCH(F63,'Semrush Data'!$A$2:$A$5000,0)),"") -> 22 | I63: vilvah | J63: =IFERROR(INDEX('Semrush Data'!$C$2:$C$5000,MATCH(I63,'Semrush Data'!$A$2:$A$5000,0)),"") -> 480 | K63: /collections/gifts-for-her | L63: Vilvah Pore Minimising Kit | M63: Vilvah Pore Minimising Kit – Skincare Gift Set | Swansura | N63: =LEN(M63) -> 57 | O63: Buy Vilvah Pore Minimising Kit, natural skincare gift set from Vilvah. Official UK partner: 100% authentic, shipped from the UK, free delivery over £50. | P63: =LEN(O63) -> 152 | Q63: Vilvah Pore Minimising Kit is natural skincare gift set from Vilvah. Swansura is an official UK partner of Vilvah, so every order is 100% authentic and ships from the UK. | S63: Matched – no usable facts, add 1–2 from pack | T63: Review: source copy has medical-style claims (kept out of intro)
A64: VD-063 | B64: Vilvah | C64: Vilvah Face Brightening Kit Large | D64: Gift Sets & Combos | E64: Dull Skin | F64: skincare for dull skin | G64: =IFERROR(INDEX('Semrush Data'!$C$2:$C$5000,MATCH(F64,'Semrush Data'!$A$2:$A$5000,0)),"") -> 320 | H64: =IFERROR(INDEX('Semrush Data'!$D$2:$D$5000,MATCH(F64,'Semrush Data'!$A$2:$A$5000,0)),"") -> 10 | I64: vilvah | J64: =IFERROR(INDEX('Semrush Data'!$C$2:$C$5000,MATCH(I64,'Semrush Data'!$A$2:$A$5000,0)),"") -> 480 | K64: /collections/dull-skin | L64: Vilvah Face Brightening Kit Large | M64: Vilvah Face Brightening Kit Large | Skincare for Dull Skin | N64: =LEN(M64) -> 58 | O64: Vilvah Face Brightening Kit Large: natural skincare for dull skin from Vilvah. Official UK partner: 100% authentic, shipped from the UK, free delivery over £50. | P64: =LEN(O64) -> 160 | Q64: Vilvah Face Brightening Kit Large is natural skincare for dull skin from Vilvah. Deep cleanses and gently exfoliates via milk powder wash, lifting dullness while preserving moisture. Hydrates skin with hyaluronic acid and rice milk to maintain plumpness and softness. Swansura is an official UK partner of Vilvah, so every order is 100% authentic and ships from the UK. | S64: Matched | T64: Review: source copy has medical-style claims (kept out of intro)
A65: VD-064 | B65: Vilvah | C65: Vilvah Face Brightening Kit | D65: Gift Sets & Combos | E65: Dull Skin | F65: skincare for dull skin | G65: =IFERROR(INDEX('Semrush Data'!$C$2:$C$5000,MATCH(F65,'Semrush Data'!$A$2:$A$5000,0)),"") -> 320 | H65: =IFERROR(INDEX('Semrush Data'!$D$2:$D$5000,MATCH(F65,'Semrush Data'!$A$2:$A$5000,0)),"") -> 10 | I65: vilvah | J65: =IFERROR(INDEX('Semrush Data'!$C$2:$C$5000,MATCH(I65,'Semrush Data'!$A$2:$A$5000,0)),"") -> 480 | K65: /collections/dull-skin | L65: Vilvah Face Brightening Kit | M65: Vilvah Face Brightening Kit | Skincare for Dull Skin | N65: =LEN(M65) -> 52 | O65: Buy Vilvah Face Brightening Kit, natural skincare for dull skin from Vilvah. Official UK partner: 100% authentic, shipped from the UK, free delivery over £50. | P65: =LEN(O65) -> 158 | Q65: Vilvah Face Brightening Kit is natural skincare for dull skin from Vilvah. Deep cleanses and gently exfoliates via milk powder wash, lifting dullness while preserving moisture. Hydrates skin with hyaluronic acid and rice milk to maintain plumpness and softness. Swansura is an official UK partner of Vilvah, so every order is 100% authentic and ships from the UK. | S65: Matched | T65: Review: source copy has medical-style claims (kept out of intro)
A66: VD-065 | B66: Vilvah | C66: Vilvah Budget Skincare combo | D66: Gift Sets & Combos | E66: Dry Skin | F66: skincare for dry skin | G66: =IFERROR(INDEX('Semrush Data'!$C$2:$C$5000,MATCH(F66,'Semrush Data'!$A$2:$A$5000,0)),"") -> 1300 | H66: =IFERROR(INDEX('Semrush Data'!$D$2:$D$5000,MATCH(F66,'Semrush Data'!$A$2:$A$5000,0)),"") -> 16 | I66: vilvah | J66: =IFERROR(INDEX('Semrush Data'!$C$2:$C$5000,MATCH(I66,'Semrush Data'!$A$2:$A$5000,0)),"") -> 480 | K66: /collections/dry-skin | L66: Vilvah Budget Skincare Combo | M66: Vilvah Budget Skincare Combo | Skincare for Dry Skin | N66: =LEN(M66) -> 52 | O66: Buy Vilvah Budget Skincare Combo, natural skincare for dry skin from Vilvah. Official UK partner: 100% authentic, shipped from the UK, free delivery over £50. | P66: =LEN(O66) -> 158 | Q66: Vilvah Budget Skincare Combo is natural skincare for dry skin from Vilvah. Swansura is an official UK partner of Vilvah, so every order is 100% authentic and ships from the UK. | S66: Not found – write from pack
A67: VD-066 | B67: Vilvah | C67: Vilvah Face Lift Kit | D67: Gift Sets & Combos | E67: Anti-Ageing | F67: skincare gift set | G67: =IFERROR(INDEX('Semrush Data'!$C$2:$C$5000,MATCH(F67,'Semrush Data'!$A$2:$A$5000,0)),"") -> 3600 | H67: =IFERROR(INDEX('Semrush Data'!$D$2:$D$5000,MATCH(F67,'Semrush Data'!$A$2:$A$5000,0)),"") -> 22 | I67: vilvah | J67: =IFERROR(INDEX('Semrush Data'!$C$2:$C$5000,MATCH(I67,'Semrush Data'!$A$2:$A$5000,0)),"") -> 480 | K67: /collections/gifts-for-her | L67: Vilvah Face Lift Kit | M67: Vilvah Face Lift Kit – Skincare Gift Set | Swansura | N67: =LEN(M67) -> 51 | O67: Buy Vilvah Face Lift Kit, natural skincare gift set from Vilvah. Official UK partner: 100% authentic, shipped from the UK, free delivery over £50. | P67: =LEN(O67) -> 146 | Q67: Vilvah Face Lift Kit is natural skincare gift set from Vilvah. Swansura is an official UK partner of Vilvah, so every order is 100% authentic and ships from the UK. | S67: Matched – no usable facts, add 1–2 from pack | T67: Review: source copy has medical-style claims (kept out of intro)
A68: VD-067 | B68: Vilvah | C68: Vilvah x Annapoorna Gift Box | D68: Gift Sets & Combos | E68: Body Hydration | F68: body lotion for dry skin | G68: =IFERROR(INDEX('Semrush Data'!$C$2:$C$5000,MATCH(F68,'Semrush Data'!$A$2:$A$5000,0)),"") -> 1300 | H68: =IFERROR(INDEX('Semrush Data'!$D$2:$D$5000,MATCH(F68,'Semrush Data'!$A$2:$A$5000,0)),"") -> 11 | I68: vilvah | J68: =IFERROR(INDEX('Semrush Data'!$C$2:$C$5000,MATCH(I68,'Semrush Data'!$A$2:$A$5000,0)),"") -> 480 | K68: /collections/body-lotion-for-dry-skin | L68: Vilvah X Annapoorna Gift Box | M68: Vilvah X Annapoorna Gift Box | Body Lotion for Dry Skin | N68: =LEN(M68) -> 55 | O68: Vilvah X Annapoorna Gift Box: a natural body lotion for dry skin from Vilvah. Official UK partner: 100% authentic, shipped from the UK, free delivery over £50. | P68: =LEN(O68) -> 159 | Q68: Vilvah X Annapoorna Gift Box is a natural body lotion for dry skin from Vilvah. Swansura is an official UK partner of Vilvah, so every order is 100% authentic and ships from the UK. | S68: Not found – write from pack
A69: VD-068 | B69: Vilvah | C69: tinted lip balm kit | D69: Gift Sets & Combos | E69: Dry Lips | F69: lip balm for dry lips | G69: =IFERROR(INDEX('Semrush Data'!$C$2:$C$5000,MATCH(F69,'Semrush Data'!$A$2:$A$5000,0)),"") -> 1000 | H69: =IFERROR(INDEX('Semrush Data'!$D$2:$D$5000,MATCH(F69,'Semrush Data'!$A$2:$A$5000,0)),"") -> 41 | I69: vilvah | J69: =IFERROR(INDEX('Semrush Data'!$C$2:$C$5000,MATCH(I69,'Semrush Data'!$A$2:$A$5000,0)),"") -> 480 | K69: /collections/lip-balm-for-dry-lips | L69: Vilvah Tinted Lip Balm Kit | M69: Vilvah Tinted Lip Balm Kit | Lip Balm for Dry Lips | N69: =LEN(M69) -> 50 | O69: Buy Vilvah Tinted Lip Balm Kit, a natural lip balm for dry lips from Vilvah. Official UK partner: 100% authentic, shipped from the UK, free delivery over £50. | P69: =LEN(O69) -> 158 | Q69: Vilvah Tinted Lip Balm Kit is a natural lip balm for dry lips from Vilvah. Easy to wear on its own or layered for extra colour, this kit is ideal for everyday use and suits all skin tones with a natural, hydrated look. Key Benefits• Helps keep lips soft and moisturised• Adds a natural everyday tint• Lightweight, smooth, and comfortable to wear• Suitable for daily use. Swansura is an official UK partner of Vilvah, so every order is 100% authentic and ships from the UK. | S69: Matched | T69: Review: source copy has medical-style claims (kept out of intro)
A70: VD-069 | B70: Vilvah | C70: Vilvah Store Frizz Free Hair Combo | D70: Gift Sets & Combos | E70: Frizzy Hair | F70: hair serum for frizzy hair | G70: =IFERROR(INDEX('Semrush Data'!$C$2:$C$5000,MATCH(F70,'Semrush Data'!$A$2:$A$5000,0)),"") -> 1000 | H70: =IFERROR(INDEX('Semrush Data'!$D$2:$D$5000,MATCH(F70,'Semrush Data'!$A$2:$A$5000,0)),"") -> 27 | I70: vilvah | J70: =IFERROR(INDEX('Semrush Data'!$C$2:$C$5000,MATCH(I70,'Semrush Data'!$A$2:$A$5000,0)),"") -> 480 | K70: /collections/hair-serum-for-frizzy-hair | L70: Vilvah Store Frizz Free Hair Combo | M70: Vilvah Store Frizz Free Hair Combo | Vilvah UK | Swansura | N70: =LEN(M70) -> 57 | O70: Buy Vilvah Store Frizz Free Hair Combo, a natural hair serum for frizzy hair from Vilvah. Official UK partner, 100% authentic, free UK delivery over £50. | P70: =LEN(O70) -> 153 | Q70: Vilvah Store Frizz Free Hair Combo is a natural hair serum for frizzy hair from Vilvah. Swansura is an official UK partner of Vilvah, so every order is 100% authentic and ships from the UK. | S70: Not found – write from pack
A71: VD-070 | B71: Vilvah | C71: Vilvah Bestseller Hair Kit | D71: Gift Sets & Combos | E71: Dry Hair | F71: hair mask for dry hair | G71: =IFERROR(INDEX('Semrush Data'!$C$2:$C$5000,MATCH(F71,'Semrush Data'!$A$2:$A$5000,0)),"") -> 2400 | H71: =IFERROR(INDEX('Semrush Data'!$D$2:$D$5000,MATCH(F71,'Semrush Data'!$A$2:$A$5000,0)),"") -> 13 | I71: vilvah | J71: =IFERROR(INDEX('Semrush Data'!$C$2:$C$5000,MATCH(I71,'Semrush Data'!$A$2:$A$5000,0)),"") -> 480 | K71: /collections/hair-mask-for-dry-hair | L71: Vilvah Bestseller Hair Kit | M71: Vilvah Bestseller Hair Kit | Hair Mask for Dry Hair | N71: =LEN(M71) -> 51 | O71: Buy Vilvah Bestseller Hair Kit, a natural hair mask for dry hair from Vilvah. Official UK partner: 100% authentic, shipped from the UK, free delivery over £50. | P71: =LEN(O71) -> 159 | Q71: Vilvah Bestseller Hair Kit is a natural hair mask for dry hair from Vilvah. Goat milk replenishes moisture, leaving hair soft and manageable. Tucuma Butter and Broccoli Oil smoothen hair and reduce flyaways. Swansura is an official UK partner of Vilvah, so every order is 100% authentic and ships from the UK. | S71: Matched | T71: Review: source copy has medical-style claims (kept out of intro)
A72: VD-071 | B72: Vilvah | C72: Vilvah Shampoo and Hair Serum Kit | D72: Gift Sets & Combos | E72: Dry Hair | F72: hair mask for dry hair | G72: =IFERROR(INDEX('Semrush Data'!$C$2:$C$5000,MATCH(F72,'Semrush Data'!$A$2:$A$5000,0)),"") -> 2400 | H72: =IFERROR(INDEX('Semrush Data'!$D$2:$D$5000,MATCH(F72,'Semrush Data'!$A$2:$A$5000,0)),"") -> 13 | I72: vilvah | J72: =IFERROR(INDEX('Semrush Data'!$C$2:$C$5000,MATCH(I72,'Semrush Data'!$A$2:$A$5000,0)),"") -> 480 | K72: /collections/hair-mask-for-dry-hair | L72: Vilvah Shampoo and Hair Serum Kit | M72: Vilvah Shampoo and Hair Serum Kit | Hair Mask for Dry Hair | N72: =LEN(M72) -> 58 | O72: Buy Vilvah Shampoo and Hair Serum Kit, a natural hair mask for dry hair from Vilvah. Official UK partner, 100% authentic, free UK delivery over £50. | P72: =LEN(O72) -> 148 | Q72: Vilvah Shampoo and Hair Serum Kit is a natural hair mask for dry hair from Vilvah. Swansura is an official UK partner of Vilvah, so every order is 100% authentic and ships from the UK. | S72: Matched – no usable facts, add 1–2 from pack | T72: Review: source copy has medical-style claims (kept out of intro)
A73: VD-072 | B73: Vilvah | C73: Vilvah Hair Strengthening Kit | D73: Gift Sets & Combos | E73: Damaged Hair | F73: skincare gift set | G73: =IFERROR(INDEX('Semrush Data'!$C$2:$C$5000,MATCH(F73,'Semrush Data'!$A$2:$A$5000,0)),"") -> 3600 | H73: =IFERROR(INDEX('Semrush Data'!$D$2:$D$5000,MATCH(F73,'Semrush Data'!$A$2:$A$5000,0)),"") -> 22 | I73: vilvah | J73: =IFERROR(INDEX('Semrush Data'!$C$2:$C$5000,MATCH(I73,'Semrush Data'!$A$2:$A$5000,0)),"") -> 480 | K73: /collections/gifts-for-her | L73: Vilvah Hair Strengthening Kit | M73: Vilvah Hair Strengthening Kit – Skincare Gift Set | Swansura | N73: =LEN(M73) -> 60 | O73: Buy Vilvah Hair Strengthening Kit, natural skincare gift set from Vilvah. Official UK partner: 100% authentic, shipped from the UK, free delivery over £50. | P73: =LEN(O73) -> 155 | Q73: Vilvah Hair Strengthening Kit is natural skincare gift set from Vilvah. Dual Action Care – Hair Growth Oil stimulates scalp & hair growth; Goat Milk Shampoo nourishes & hydrates. Reduces Hair Fall – Strengthens roots, minimizes breakage, and protects against thinning. Swansura is an official UK partner of Vilvah, so every order is 100% authentic and ships from the UK. | S73: Matched
A74: VD-073 | B74: Vilvah | C74: Vilvah Lip Lightening Kit | D74: Gift Sets & Combos | E74: Pigmentation | F74: skincare gift set | G74: =IFERROR(INDEX('Semrush Data'!$C$2:$C$5000,MATCH(F74,'Semrush Data'!$A$2:$A$5000,0)),"") -> 3600 | H74: =IFERROR(INDEX('Semrush Data'!$D$2:$D$5000,MATCH(F74,'Semrush Data'!$A$2:$A$5000,0)),"") -> 22 | I74: vilvah | J74: =IFERROR(INDEX('Semrush Data'!$C$2:$C$5000,MATCH(I74,'Semrush Data'!$A$2:$A$5000,0)),"") -> 480 | K74: /collections/gifts-for-her | L74: Vilvah Lip Lightening Kit | M74: Vilvah Lip Lightening Kit – Skincare Gift Set | Swansura | N74: =LEN(M74) -> 56 | O74: Buy Vilvah Lip Lightening Kit, natural skincare gift set from Vilvah. Official UK partner: 100% authentic, shipped from the UK, free delivery over £50. | P74: =LEN(O74) -> 151 | Q74: Vilvah Lip Lightening Kit is natural skincare gift set from Vilvah. Lip Scrub exfoliates gently, removing dead skin and lightening lips. Hydrating formula keeps lips soft, smooth & supple. Swansura is an official UK partner of Vilvah, so every order is 100% authentic and ships from the UK. | S74: Matched | T74: Review: source copy has medical-style claims (kept out of intro)
A75: VD-074 | B75: Vilvah | C75: Vilvah Skin Hydration Kit | D75: Gift Sets & Combos | E75: Dry Skin | F75: skincare for dry skin | G75: =IFERROR(INDEX('Semrush Data'!$C$2:$C$5000,MATCH(F75,'Semrush Data'!$A$2:$A$5000,0)),"") -> 1300 | H75: =IFERROR(INDEX('Semrush Data'!$D$2:$D$5000,MATCH(F75,'Semrush Data'!$A$2:$A$5000,0)),"") -> 16 | I75: vilvah | J75: =IFERROR(INDEX('Semrush Data'!$C$2:$C$5000,MATCH(I75,'Semrush Data'!$A$2:$A$5000,0)),"") -> 480 | K75: /collections/dry-skin | L75: Vilvah Skin Hydration Kit | M75: Vilvah Skin Hydration Kit – Skincare for Dry Skin | Swansura | N75: =LEN(M75) -> 60 | O75: Buy Vilvah Skin Hydration Kit, natural skincare for dry skin from Vilvah. Official UK partner: 100% authentic, shipped from the UK, free delivery over £50. | P75: =LEN(O75) -> 155 | Q75: Vilvah Skin Hydration Kit is natural skincare for dry skin from Vilvah. Hydrates & plumps skin with rice milk and plant-based hyaluronic acid. Minimises visible pores using Earth Marine Water and gentle exfoliation with glycolic acid. Swansura is an official UK partner of Vilvah, so every order is 100% authentic and ships from the UK. | S75: Matched | T75: Review: source copy has medical-style claims (kept out of intro)
A76: VD-075 | B76: Vilvah | C76: Vilvah Anti Frizz Hair Kit | D76: Gift Sets & Combos | E76: Frizzy Hair | F76: hair serum for frizzy hair | G76: =IFERROR(INDEX('Semrush Data'!$C$2:$C$5000,MATCH(F76,'Semrush Data'!$A$2:$A$5000,0)),"") -> 1000 | H76: =IFERROR(INDEX('Semrush Data'!$D$2:$D$5000,MATCH(F76,'Semrush Data'!$A$2:$A$5000,0)),"") -> 27 | I76: vilvah | J76: =IFERROR(INDEX('Semrush Data'!$C$2:$C$5000,MATCH(I76,'Semrush Data'!$A$2:$A$5000,0)),"") -> 480 | K76: /collections/hair-serum-for-frizzy-hair | L76: Vilvah Anti Frizz Hair Kit | M76: Vilvah Anti Frizz Hair Kit | Hair Serum for Frizzy Hair | N76: =LEN(M76) -> 55 | O76: Vilvah Anti Frizz Hair Kit: a natural hair serum for frizzy hair from Vilvah. Official UK partner: 100% authentic, shipped from the UK, free delivery over £50. | P76: =LEN(O76) -> 159 | Q76: Vilvah Anti Frizz Hair Kit is a natural hair serum for frizzy hair from Vilvah. Swansura is an official UK partner of Vilvah, so every order is 100% authentic and ships from the UK. | S76: Matched – no usable facts, add 1–2 from pack | T76: Review: source copy has medical-style claims (kept out of intro)
A77: VD-076 | B77: Vilvah | C77: Vilvah Body Polishing Kit | D77: Gift Sets & Combos | E77: Dull Skin | F77: skincare for dull skin | G77: =IFERROR(INDEX('Semrush Data'!$C$2:$C$5000,MATCH(F77,'Semrush Data'!$A$2:$A$5000,0)),"") -> 320 | H77: =IFERROR(INDEX('Semrush Data'!$D$2:$D$5000,MATCH(F77,'Semrush Data'!$A$2:$A$5000,0)),"") -> 10 | I77: vilvah | J77: =IFERROR(INDEX('Semrush Data'!$C$2:$C$5000,MATCH(I77,'Semrush Data'!$A$2:$A$5000,0)),"") -> 480 | K77: /collections/dull-skin | L77: Vilvah Body Polishing Kit | M77: Vilvah Body Polishing Kit | Skincare for Dull Skin | N77: =LEN(M77) -> 50 | O77: Vilvah Body Polishing Kit: natural skincare for dull skin from Vilvah. Coffee Scrub gently exfoliates, removes tan and unclogs pores. Free UK delivery over £50. | P77: =LEN(O77) -> 160 | Q77: Vilvah Body Polishing Kit is natural skincare for dull skin from Vilvah. Coffee Scrub gently exfoliates, removes tan and unclogs pores. Almond Milk keeps skin firm, supple & radiant. Swansura is an official UK partner of Vilvah, so every order is 100% authentic and ships from the UK. | S77: Matched
A78: VD-077 | B78: Vilvah | C78: Vilvah Hairfall Control Kit | D78: Gift Sets & Combos | E78: Hair Thinning & Loss | F78: hair oil for hair loss | G78: =IFERROR(INDEX('Semrush Data'!$C$2:$C$5000,MATCH(F78,'Semrush Data'!$A$2:$A$5000,0)),"") -> 260 | H78: =IFERROR(INDEX('Semrush Data'!$D$2:$D$5000,MATCH(F78,'Semrush Data'!$A$2:$A$5000,0)),"") -> 22 | I78: vilvah | J78: =IFERROR(INDEX('Semrush Data'!$C$2:$C$5000,MATCH(I78,'Semrush Data'!$A$2:$A$5000,0)),"") -> 480 | K78: /collections/hair-oil-for-hair-loss | L78: Vilvah Hairfall Control Kit | M78: Vilvah Hairfall Control Kit | Hair Oil for Hair Loss | N78: =LEN(M78) -> 52 | O78: Buy Vilvah Hairfall Control Kit, a natural hair oil for hair loss from Vilvah. Official UK partner: 100% authentic, shipped from the UK, free delivery over £50. | P78: =LEN(O78) -> 160 | Q78: Vilvah Hairfall Control Kit is a natural hair oil for hair loss from Vilvah. Dual Action Formula – Nourishing Hair Growth Oil + scalp-purifying Herbal Shampoo. Strengthens & Protects – Reduces breakage and supports new follicle growth. Swansura is an official UK partner of Vilvah, so every order is 100% authentic and ships from the UK. | S78: Matched | T78: Review: source copy has medical-style claims (kept out of intro)
A79: VD-078 | B79: Vilvah | C79: Vilvah Anti‑Dandruff Haircare Kit | D79: Gift Sets & Combos | E79: Anti-Dandruff | F79: shampoo for dandruff | G79: =IFERROR(INDEX('Semrush Data'!$C$2:$C$5000,MATCH(F79,'Semrush Data'!$A$2:$A$5000,0)),"") -> 1600 | H79: =IFERROR(INDEX('Semrush Data'!$D$2:$D$5000,MATCH(F79,'Semrush Data'!$A$2:$A$5000,0)),"") -> 31 | I79: vilvah | J79: =IFERROR(INDEX('Semrush Data'!$C$2:$C$5000,MATCH(I79,'Semrush Data'!$A$2:$A$5000,0)),"") -> 480 | K79: /collections/shampoo-for-dandruff | L79: Vilvah Anti‑Dandruff Haircare Kit | M79: Vilvah Anti‑Dandruff Haircare Kit | Shampoo for Dandruff | N79: =LEN(M79) -> 56 | O79: Vilvah Anti‑Dandruff Haircare Kit: a natural shampoo for dandruff from Vilvah. Official UK partner: 100% authentic, shipped from the UK, free delivery over £50. | P79: =LEN(O79) -> 160 | Q79: Vilvah Anti‑Dandruff Haircare Kit is a natural shampoo for dandruff from Vilvah. Swansura is an official UK partner of Vilvah, so every order is 100% authentic and ships from the UK. | S79: Matched – no usable facts, add 1–2 from pack | T79: Review: source copy has medical-style claims (kept out of intro)
A80: VD-079 | B80: Vilvah | C80: Vilvah Goat Milk Hair Kit | D80: Gift Sets & Combos | E80: Dry Hair | F80: hair mask for dry hair | G80: =IFERROR(INDEX('Semrush Data'!$C$2:$C$5000,MATCH(F80,'Semrush Data'!$A$2:$A$5000,0)),"") -> 2400 | H80: =IFERROR(INDEX('Semrush Data'!$D$2:$D$5000,MATCH(F80,'Semrush Data'!$A$2:$A$5000,0)),"") -> 13 | I80: vilvah | J80: =IFERROR(INDEX('Semrush Data'!$C$2:$C$5000,MATCH(I80,'Semrush Data'!$A$2:$A$5000,0)),"") -> 480 | K80: /collections/hair-mask-for-dry-hair | L80: Vilvah Goat Milk Hair Kit | M80: Vilvah Goat Milk Hair Kit | Hair Mask for Dry Hair | N80: =LEN(M80) -> 50 | O80: Buy Vilvah Goat Milk Hair Kit, a natural hair mask for dry hair from Vilvah. Official UK partner: 100% authentic, shipped from the UK, free delivery over £50. | P80: =LEN(O80) -> 158 | Q80: Vilvah Goat Milk Hair Kit is a natural hair mask for dry hair from Vilvah. Swansura is an official UK partner of Vilvah, so every order is 100% authentic and ships from the UK. | S80: Matched – no usable facts, add 1–2 from pack
A81: VD-080 | B81: Vilvah | C81: Vilvah Everyday Care Milk Kit | D81: Gift Sets & Combos | E81: Body Hydration | F81: body lotion for dry skin | G81: =IFERROR(INDEX('Semrush Data'!$C$2:$C$5000,MATCH(F81,'Semrush Data'!$A$2:$A$5000,0)),"") -> 1300 | H81: =IFERROR(INDEX('Semrush Data'!$D$2:$D$5000,MATCH(F81,'Semrush Data'!$A$2:$A$5000,0)),"") -> 11 | I81: vilvah | J81: =IFERROR(INDEX('Semrush Data'!$C$2:$C$5000,MATCH(I81,'Semrush Data'!$A$2:$A$5000,0)),"") -> 480 | K81: /collections/body-lotion-for-dry-skin | L81: Vilvah Everyday Care Milk Kit | M81: Vilvah Everyday Care Milk Kit | Body Lotion for Dry Skin | N81: =LEN(M81) -> 56 | O81: Vilvah Everyday Care Milk Kit: a natural body lotion for dry skin from Vilvah. Official UK partner: 100% authentic, shipped from the UK, free delivery over £50. | P81: =LEN(O81) -> 160 | Q81: Vilvah Everyday Care Milk Kit is a natural body lotion for dry skin from Vilvah. Swansura is an official UK partner of Vilvah, so every order is 100% authentic and ships from the UK. | S81: Matched – no usable facts, add 1–2 from pack | T81: Review: source copy has medical-style claims (kept out of intro)
A82: VD-081 | B82: Vilvah | C82: Vilvah Lip Nourishing Kit | D82: Gift Sets & Combos | E82: Dry Lips | F82: lip balm for dry lips | G82: =IFERROR(INDEX('Semrush Data'!$C$2:$C$5000,MATCH(F82,'Semrush Data'!$A$2:$A$5000,0)),"") -> 1000 | H82: =IFERROR(INDEX('Semrush Data'!$D$2:$D$5000,MATCH(F82,'Semrush Data'!$A$2:$A$5000,0)),"") -> 41 | I82: vilvah | J82: =IFERROR(INDEX('Semrush Data'!$C$2:$C$5000,MATCH(I82,'Semrush Data'!$A$2:$A$5000,0)),"") -> 480 | K82: /collections/lip-balm-for-dry-lips | L82: Vilvah Lip Nourishing Kit | M82: Vilvah Lip Nourishing Kit – Lip Balm for Dry Lips | Swansura | N82: =LEN(M82) -> 60 | O82: Buy Vilvah Lip Nourishing Kit, a natural lip balm for dry lips from Vilvah. Official UK partner: 100% authentic, shipped from the UK, free delivery over £50. | P82: =LEN(O82) -> 157 | Q82: Vilvah Lip Nourishing Kit is a natural lip balm for dry lips from Vilvah. Grapefruit Lip Balm hydrates and gives a natural tint to your lips. Lip Scrub gently exfoliates and removes dead skin. Swansura is an official UK partner of Vilvah, so every order is 100% authentic and ships from the UK. | S82: Matched
A83: VD-082 | B83: Deyga | C83: Chocolate Body Butter 100G | D83: Body Butters | E83: Dry Skin | F83: body butter | G83: =IFERROR(INDEX('Semrush Data'!$C$2:$C$5000,MATCH(F83,'Semrush Data'!$A$2:$A$5000,0)),"") -> 6600 | H83: =IFERROR(INDEX('Semrush Data'!$D$2:$D$5000,MATCH(F83,'Semrush Data'!$A$2:$A$5000,0)),"") -> 12 | I83: deyga | J83: =IFERROR(INDEX('Semrush Data'!$C$2:$C$5000,MATCH(I83,'Semrush Data'!$A$2:$A$5000,0)),"") -> 140 | K83: /collections/body-butter | L83: Deyga Chocolate Body Butter | M83: Deyga Chocolate Body Butter – Body Butter | Swansura | N83: =LEN(M83) -> 52 | O83: Buy Deyga Chocolate Body Butter, a natural body butter from Deyga. Official UK partner: 100% authentic, shipped from the UK, free delivery over £50. | P83: =LEN(O83) -> 148 | Q83: Deyga Chocolate Body Butter is a natural body butter from Deyga. Intense Moisture for Dry Skin – Formulated with cocoa and nourishing oils to provide deep hydration and combat dryness throughout the day. Helps Reduce Stretch Marks – Regular use supports skin elasticity and helps minimize the appearance of stretch marks. Swansura is an official UK partner of Deyga, so every order is 100% authentic and ships from the UK. | S83: Matched
A84: VD-083 | B84: Deyga | C84: Charcoal Detox Face Mask 100G | D84: Face Masks | E84: Oily Skin | F84: face mask | G84: =IFERROR(INDEX('Semrush Data'!$C$2:$C$5000,MATCH(F84,'Semrush Data'!$A$2:$A$5000,0)),"") -> 22200 | H84: =IFERROR(INDEX('Semrush Data'!$D$2:$D$5000,MATCH(F84,'Semrush Data'!$A$2:$A$5000,0)),"") -> 30 | I84: deyga | J84: =IFERROR(INDEX('Semrush Data'!$C$2:$C$5000,MATCH(I84,'Semrush Data'!$A$2:$A$5000,0)),"") -> 140 | K84: /collections/face-mask-for-oily-skin | L84: Deyga Charcoal Detox Face Mask | M84: Deyga Charcoal Detox Face Mask – Face Mask | Swansura | N84: =LEN(M84) -> 53 | O84: Buy Deyga Charcoal Detox Face Mask, a natural face mask from Deyga. Official UK partner: 100% authentic, shipped from the UK, free delivery over £50. | P84: =LEN(O84) -> 149 | Q84: Deyga Charcoal Detox Face Mask is a natural face mask from Deyga. Activated charcoal draws out dirt, toxins, and impurities from deep within pores for a clear and refreshed look. Helps regulate sebum production, making it ideal for oily, combination, and acne-prone skin. Swansura is an official UK partner of Deyga, so every order is 100% authentic and ships from the UK. | S84: Matched | T84: Review: source copy has medical-style claims (kept out of intro)
A85: VD-084 | B85: Deyga | C85: Activated Charcoal Body Wash 220ML | D85: Bath & Body Wash | E85: Body Cleansing | F85: natural body wash | G85: =IFERROR(INDEX('Semrush Data'!$C$2:$C$5000,MATCH(F85,'Semrush Data'!$A$2:$A$5000,0)),"") -> 1300 | H85: =IFERROR(INDEX('Semrush Data'!$D$2:$D$5000,MATCH(F85,'Semrush Data'!$A$2:$A$5000,0)),"") -> 19 | I85: deyga | J85: =IFERROR(INDEX('Semrush Data'!$C$2:$C$5000,MATCH(I85,'Semrush Data'!$A$2:$A$5000,0)),"") -> 140 | K85: /collections/shower-gel-body-wash | L85: Deyga Activated Charcoal Body Wash | M85: Deyga Activated Charcoal Body Wash | Natural Body Wash | N85: =LEN(M85) -> 54 | O85: Buy Deyga Activated Charcoal Body Wash, a natural body wash from Deyga. Official UK partner: 100% authentic, shipped from the UK, free delivery over £50. | P85: =LEN(O85) -> 153 | Q85: Deyga Activated Charcoal Body Wash is a natural body wash from Deyga. Enriched with cucumber to soothe irritation and provide long-lasting hydration. Free from sulphates, parabens, BPA, and harsh chemicals, making it safe for all skin types. Swansura is an official UK partner of Deyga, so every order is 100% authentic and ships from the UK. | S85: Matched | T85: Review: source copy has medical-style claims (kept out of intro)
A86: VD-085 | B86: Deyga | C86: Body Scrub 100g | D86: Body Scrub & Exfoliators | E86: Dry Skin | F86: body scrub | G86: =IFERROR(INDEX('Semrush Data'!$C$2:$C$5000,MATCH(F86,'Semrush Data'!$A$2:$A$5000,0)),"") -> 12100 | H86: =IFERROR(INDEX('Semrush Data'!$D$2:$D$5000,MATCH(F86,'Semrush Data'!$A$2:$A$5000,0)),"") -> 18 | I86: deyga | J86: =IFERROR(INDEX('Semrush Data'!$C$2:$C$5000,MATCH(I86,'Semrush Data'!$A$2:$A$5000,0)),"") -> 140 | K86: /collections/body-scrub | L86: Deyga Body Scrub | M86: Deyga Body Scrub | Body Scrub | N86: =LEN(M86) -> 29 | O86: Buy Deyga Body Scrub, a natural body scrub from Deyga. Official UK partner: 100% authentic, shipped from the UK, free delivery over £50. | P86: =LEN(O86) -> 136 | Q86: Deyga Body Scrub is a natural body scrub from Deyga. Gently removes dead skin and impurities with fruit-derived exfoliants for visibly smoother skin. Infused with papaya, pomegranate and other skin-loving ingredients for deep nourishment. Swansura is an official UK partner of Deyga, so every order is 100% authentic and ships from the UK. | R86: deyga body wash · deyga body wash review · deyga body wash ingredients · how to use deyga body scrub | S86: Matched
A87: VD-086 | B87: Deyga | C87: Deep Moisturising Face Cream 30G | D87: Moisturisers | E87: Dry Skin | F87: moisturiser for dry skin | G87: =IFERROR(INDEX('Semrush Data'!$C$2:$C$5000,MATCH(F87,'Semrush Data'!$A$2:$A$5000,0)),"") -> 2900 | H87: =IFERROR(INDEX('Semrush Data'!$D$2:$D$5000,MATCH(F87,'Semrush Data'!$A$2:$A$5000,0)),"") -> 29 | I87: deyga | J87: =IFERROR(INDEX('Semrush Data'!$C$2:$C$5000,MATCH(I87,'Semrush Data'!$A$2:$A$5000,0)),"") -> 140 | K87: /collections/moisturiser-for-dry-skin | L87: Deyga Deep Moisturising Face Cream | M87: Deyga Deep Moisturising Face Cream | Deyga UK | Swansura | N87: =LEN(M87) -> 56 | O87: Buy Deyga Deep Moisturising Face Cream, a natural moisturiser for dry skin from Deyga. Official UK partner, 100% authentic, free UK delivery over £50. | P87: =LEN(O87) -> 150 | Q87: Deyga Deep Moisturising Face Cream is a natural moisturiser for dry skin from Deyga. Provides long-lasting moisture for up to 7–8 hours, helping to combat dryness and flakiness effectively. Made with plant-based oils and free from parabens, phthalates, artificial fragrances, and harmful chemicals. Swansura is an official UK partner of Deyga, so every order is 100% authentic and ships from the UK. | S87: Matched | T87: Review: source copy has medical-style claims (kept out of intro)
A88: VD-087 | B88: Deyga | C88: 2% Hyaluronic Acid Serum 20ML | D88: Serums | E88: Dull Skin | F88: skincare for dull skin | G88: =IFERROR(INDEX('Semrush Data'!$C$2:$C$5000,MATCH(F88,'Semrush Data'!$A$2:$A$5000,0)),"") -> 320 | H88: =IFERROR(INDEX('Semrush Data'!$D$2:$D$5000,MATCH(F88,'Semrush Data'!$A$2:$A$5000,0)),"") -> 10 | I88: deyga | J88: =IFERROR(INDEX('Semrush Data'!$C$2:$C$5000,MATCH(I88,'Semrush Data'!$A$2:$A$5000,0)),"") -> 140 | K88: /collections/dull-skin | L88: Deyga 2% Hyaluronic Acid Serum | M88: Deyga 2% Hyaluronic Acid Serum | Skincare for Dull Skin | N88: =LEN(M88) -> 55 | O88: Buy Deyga 2% Hyaluronic Acid Serum, natural skincare for dull skin from Deyga. Official UK partner: 100% authentic, shipped from the UK, free delivery over £50. | P88: =LEN(O88) -> 160 | Q88: Deyga 2% Hyaluronic Acid Serum is natural skincare for dull skin from Deyga. Deep Hydration & Moisture Lock – Formulated with 2% hyaluronic acid to attract and retain moisture, keeping skin hydrated, soft, and supple throughout the day. Plumps Skin & Reduces Fine Lines – Helps visibly smooth fine lines and improve elasticity for a youthful, plump appearance with consistent use. Swansura is an official UK partner of Deyga, so every order is 100% authentic and ships from the UK. | S88: Matched
A89: VD-088 | B89: Deyga | C89: Orange & Almond Face Pack Powder 100G | D89: Skincare Treatments | E89: Skin Nourishment | F89: face serum | G89: =IFERROR(INDEX('Semrush Data'!$C$2:$C$5000,MATCH(F89,'Semrush Data'!$A$2:$A$5000,0)),"") -> 9900 | H89: =IFERROR(INDEX('Semrush Data'!$D$2:$D$5000,MATCH(F89,'Semrush Data'!$A$2:$A$5000,0)),"") -> 30 | I89: deyga | J89: =IFERROR(INDEX('Semrush Data'!$C$2:$C$5000,MATCH(I89,'Semrush Data'!$A$2:$A$5000,0)),"") -> 140 | K89: /collections/face-serum | L89: Deyga Orange & Almond Face Pack Powder | M89: Deyga Orange & Almond Face Pack Powder | Face Serum | N89: =LEN(M89) -> 51 | O89: Buy Deyga Orange & Almond Face Pack Powder, a natural face serum from Deyga. Official UK partner: 100% authentic, shipped from the UK, free delivery over £50. | P89: =LEN(O89) -> 158 | Q89: Deyga Orange & Almond Face Pack Powder is a natural face serum from Deyga. Natural Skin Brightening Formula – Enriched with orange peel and Vitamin C to help brighten dull skin and improve overall complexion for a radiant glow. Gentle Exfoliation with Almond Meal – Naturally removes dead skin cells and impurities while nourishing the skin for a smooth, soft finish. Swansura is an official UK partner of Deyga, so every order is 100% authentic and ships from the UK. | S89: Matched | T89: Review: source copy has medical-style claims (kept out of intro)
A90: VD-089 | B90: Deyga | C90: Premature Greying Hair Oil 100ML | D90: Hair Oil | E90: Dry Hair | F90: hair growth oil | G90: =IFERROR(INDEX('Semrush Data'!$C$2:$C$5000,MATCH(F90,'Semrush Data'!$A$2:$A$5000,0)),"") -> 5400 | H90: =IFERROR(INDEX('Semrush Data'!$D$2:$D$5000,MATCH(F90,'Semrush Data'!$A$2:$A$5000,0)),"") -> 21 | I90: deyga | J90: =IFERROR(INDEX('Semrush Data'!$C$2:$C$5000,MATCH(I90,'Semrush Data'!$A$2:$A$5000,0)),"") -> 140 | K90: /collections/hair-growth-oil | L90: Deyga Premature Greying Hair Oil | M90: Deyga Premature Greying Hair Oil | Hair Growth Oil | N90: =LEN(M90) -> 50 | O90: Buy Deyga Premature Greying Hair Oil, a natural hair growth oil from Deyga. Official UK partner: 100% authentic, shipped from the UK, free delivery over £50. | P90: =LEN(O90) -> 157 | Q90: Deyga Premature Greying Hair Oil is a natural hair growth oil from Deyga. Deeply Nourishes Hair & Scalp – Infused with Coconut, Castor, and Moringa oils to hydrate the scalp, improve softness, and strengthen hair from the roots. Chemical-Free Herbal Formula – Free from mineral oils, artificial colours, and synthetic fragrances, making it suitable for all hair types including sensitive scalps. Swansura is an official UK partner of Deyga, so every order is 100% authentic and ships from the UK. | S90: Matched | T90: Review: source copy has medical-style claims (kept out of intro)
A91: VD-090 | B91: Deyga | C91: Anti-dandruff Oil | D91: Hair Oil | E91: Anti-Dandruff | F91: hair growth oil | G91: =IFERROR(INDEX('Semrush Data'!$C$2:$C$5000,MATCH(F91,'Semrush Data'!$A$2:$A$5000,0)),"") -> 5400 | H91: =IFERROR(INDEX('Semrush Data'!$D$2:$D$5000,MATCH(F91,'Semrush Data'!$A$2:$A$5000,0)),"") -> 21 | I91: deyga | J91: =IFERROR(INDEX('Semrush Data'!$C$2:$C$5000,MATCH(I91,'Semrush Data'!$A$2:$A$5000,0)),"") -> 140 | K91: /collections/hair-growth-oil | L91: Deyga Anti-dandruff Oil | M91: Deyga Anti-dandruff Oil – Hair Growth Oil | Swansura | N91: =LEN(M91) -> 52 | O91: Buy Deyga Anti-dandruff Oil, a natural hair growth oil from Deyga. Official UK partner: 100% authentic, shipped from the UK, free delivery over £50. | P91: =LEN(O91) -> 148 | Q91: Deyga Anti-dandruff Oil is a natural hair growth oil from Deyga. Swansura is an official UK partner of Deyga, so every order is 100% authentic and ships from the UK. | R91: deyga anti dandruff oil · deyga anti dandruff oil review | S91: Not found – write from pack
A92: VD-091 | B92: Deyga | C92: Rose & Geranium Body Butter 40G | D92: Body Butters | E92: Dry Skin | F92: body butter | G92: =IFERROR(INDEX('Semrush Data'!$C$2:$C$5000,MATCH(F92,'Semrush Data'!$A$2:$A$5000,0)),"") -> 6600 | H92: =IFERROR(INDEX('Semrush Data'!$D$2:$D$5000,MATCH(F92,'Semrush Data'!$A$2:$A$5000,0)),"") -> 12 | I92: deyga | J92: =IFERROR(INDEX('Semrush Data'!$C$2:$C$5000,MATCH(I92,'Semrush Data'!$A$2:$A$5000,0)),"") -> 140 | K92: /collections/body-butter | L92: Deyga Rose & Geranium Body Butter | M92: Deyga Rose & Geranium Body Butter – Body Butter | Swansura | N92: =LEN(M92) -> 58 | O92: Buy Deyga Rose & Geranium Body Butter, a natural body butter from Deyga. Official UK partner: 100% authentic, shipped from the UK, free delivery over £50. | P92: =LEN(O92) -> 154 | Q92: Deyga Rose & Geranium Body Butter is a natural body butter from Deyga. Intensely moisturizes dry and rough skin with a rich blend of natural butters and oils for long-lasting softness and comfort. Nourishing ingredients help improve skin elasticity and visibly reduce the appearance of stretch marks over time. Swansura is an official UK partner of Deyga, so every order is 100% authentic and ships from the UK. | S92: Matched | T92: Review: source copy has medical-style claims (kept out of intro)
A93: VD-092 | B93: Deyga | C93: Rose Glow Serum 30ml | D93: Serums | E93: Dull Skin | F93: skincare for dull skin | G93: =IFERROR(INDEX('Semrush Data'!$C$2:$C$5000,MATCH(F93,'Semrush Data'!$A$2:$A$5000,0)),"") -> 320 | H93: =IFERROR(INDEX('Semrush Data'!$D$2:$D$5000,MATCH(F93,'Semrush Data'!$A$2:$A$5000,0)),"") -> 10 | I93: deyga | J93: =IFERROR(INDEX('Semrush Data'!$C$2:$C$5000,MATCH(I93,'Semrush Data'!$A$2:$A$5000,0)),"") -> 140 | K93: /collections/dull-skin | L93: Deyga Rose Glow Serum | M93: Deyga Rose Glow Serum – Skincare for Dull Skin | Swansura | N93: =LEN(M93) -> 57 | O93: Buy Deyga Rose Glow Serum, natural skincare for dull skin from Deyga. Official UK partner: 100% authentic, shipped from the UK, free delivery over £50. | P93: =LEN(O93) -> 151 | Q93: Deyga Rose Glow Serum is natural skincare for dull skin from Deyga. Deeply hydrates and nourishes skin to enhance natural glow and softness. Minimizes fine lines and signs of aging with antioxidant-rich formula. Swansura is an official UK partner of Deyga, so every order is 100% authentic and ships from the UK. | R93: deyga rose glow serum review | S93: Matched | T93: Review: source copy has medical-style claims (kept out of intro)
A94: VD-093 | B94: Deyga | C94: Light Moisturising Face Cream 30G | D94: Moisturisers | E94: Dry Skin | F94: moisturiser for oily skin | G94: =IFERROR(INDEX('Semrush Data'!$C$2:$C$5000,MATCH(F94,'Semrush Data'!$A$2:$A$5000,0)),"") -> 1900 | H94: =IFERROR(INDEX('Semrush Data'!$D$2:$D$5000,MATCH(F94,'Semrush Data'!$A$2:$A$5000,0)),"") -> 22 | I94: deyga | J94: =IFERROR(INDEX('Semrush Data'!$C$2:$C$5000,MATCH(I94,'Semrush Data'!$A$2:$A$5000,0)),"") -> 140 | K94: /collections/moisturiser | L94: Deyga Light Moisturising Face Cream | M94: Deyga Light Moisturising Face Cream | Deyga UK | Swansura | N94: =LEN(M94) -> 57 | O94: Buy Deyga Light Moisturising Face Cream, a natural moisturiser for oily skin from Deyga. Official UK partner, 100% authentic, free UK delivery over £50. | P94: =LEN(O94) -> 152 | Q94: Deyga Light Moisturising Face Cream is a natural moisturiser for oily skin from Deyga. Fast-absorbing light moisturising face cream designed for oily and normal skin without leaving a greasy residue. Helps regulate excess sebum while maintaining balanced skin hydration for a fresh, matte finish. Swansura is an official UK partner of Deyga, so every order is 100% authentic and ships from the UK. | S94: Matched
A95: VD-094 | B95: Deyga | C95: Foot Soak Powder 160G | D95: Body Care | E95: Dry Skin | F95: body lotion for dry skin | G95: =IFERROR(INDEX('Semrush Data'!$C$2:$C$5000,MATCH(F95,'Semrush Data'!$A$2:$A$5000,0)),"") -> 1300 | H95: =IFERROR(INDEX('Semrush Data'!$D$2:$D$5000,MATCH(F95,'Semrush Data'!$A$2:$A$5000,0)),"") -> 11 | I95: deyga | J95: =IFERROR(INDEX('Semrush Data'!$C$2:$C$5000,MATCH(I95,'Semrush Data'!$A$2:$A$5000,0)),"") -> 140 | K95: /collections/body-lotion-for-dry-skin | L95: Deyga Foot Soak Powder | M95: Deyga Foot Soak Powder – Body Lotion for Dry Skin | Swansura | N95: =LEN(M95) -> 60 | O95: Buy Deyga Foot Soak Powder, a natural body lotion for dry skin from Deyga. Official UK partner: 100% authentic, shipped from the UK, free delivery over £50. | P95: =LEN(O95) -> 156 | Q95: Deyga Foot Soak Powder is a natural body lotion for dry skin from Deyga. Deep Relaxation for Tired Feet – Helps soothe stressed and overworked feet by easing muscle tension and promoting relaxation after long hours of standing or walking. Natural Dead Skin Removal Support – Softens hard skin, calluses, and rough patches, making it easier to exfoliate and maintain smooth feet. Swansura is an official UK partner of Deyga, so every order is 100% authentic and ships from the UK. | S95: Matched
A96: VD-095 | B96: Deyga | C96: Vitamin C Foaming Face Wash 100ML | D96: Cleansers | E96: Skin Nourishment | F96: face wash for oily skin | G96: =IFERROR(INDEX('Semrush Data'!$C$2:$C$5000,MATCH(F96,'Semrush Data'!$A$2:$A$5000,0)),"") -> 1600 | H96: =IFERROR(INDEX('Semrush Data'!$D$2:$D$5000,MATCH(F96,'Semrush Data'!$A$2:$A$5000,0)),"") -> 33 | I96: deyga | J96: =IFERROR(INDEX('Semrush Data'!$C$2:$C$5000,MATCH(I96,'Semrush Data'!$A$2:$A$5000,0)),"") -> 140 | K96: /collections/face-wash-for-oily-skin | L96: Deyga Vitamin C Foaming Face Wash | M96: Deyga Vitamin C Foaming Face Wash | Face Wash for Oily Skin | N96: =LEN(M96) -> 59 | O96: Buy Deyga Vitamin C Foaming Face Wash, a natural face wash for oily skin from Deyga. Official UK partner, 100% authentic, free UK delivery over £50. | P96: =LEN(O96) -> 148 | Q96: Deyga Vitamin C Foaming Face Wash is a natural face wash for oily skin from Deyga. Deep Cleansing Foaming Action – Micro-foam formula effectively removes dirt, oil, and impurities while keeping skin fresh and clean without over-drying. Controls Oil & Improves Texture – Helps regulate excess sebum production, leaving skin smooth, soft, and shine-free for up to 8 hours. Swansura is an official UK partner of Deyga, so every order is 100% authentic and ships from the UK. | R96: deyga vitamin c foaming face wash review | S96: Matched | T96: Review: source copy has medical-style claims (kept out of intro)
A97: VD-096 | B97: Deyga | C97: Wild Berry Body Wash 220ml | D97: Bath & Body Wash | E97: Body Cleansing | F97: natural body wash | G97: =IFERROR(INDEX('Semrush Data'!$C$2:$C$5000,MATCH(F97,'Semrush Data'!$A$2:$A$5000,0)),"") -> 1300 | H97: =IFERROR(INDEX('Semrush Data'!$D$2:$D$5000,MATCH(F97,'Semrush Data'!$A$2:$A$5000,0)),"") -> 19 | I97: deyga | J97: =IFERROR(INDEX('Semrush Data'!$C$2:$C$5000,MATCH(I97,'Semrush Data'!$A$2:$A$5000,0)),"") -> 140 | K97: /collections/shower-gel-body-wash | L97: Deyga Wild Berry Body Wash | M97: Deyga Wild Berry Body Wash – Natural Body Wash | Swansura | N97: =LEN(M97) -> 57 | O97: Buy Deyga Wild Berry Body Wash, a natural body wash from Deyga. Official UK partner: 100% authentic, shipped from the UK, free delivery over £50. | P97: =LEN(O97) -> 145 | Q97: Deyga Wild Berry Body Wash is a natural body wash from Deyga. Deeply hydrates and nourishes skin without stripping natural oils, leaving it soft and smooth after every wash. Free from harmful chemicals like sulphates, parabens, BPA, and benzophenone for safe daily use. Swansura is an official UK partner of Deyga, so every order is 100% authentic and ships from the UK. | R97: deyga wild berry body wash review | S97: Matched | T97: Review: source copy has medical-style claims (kept out of intro)
A98: VD-097 | B98: Deyga | C98: Neem Seed Oil 30ML | D98: Body Oil | E98: Body Hydration | F98: body lotion for dry skin | G98: =IFERROR(INDEX('Semrush Data'!$C$2:$C$5000,MATCH(F98,'Semrush Data'!$A$2:$A$5000,0)),"") -> 1300 | H98: =IFERROR(INDEX('Semrush Data'!$D$2:$D$5000,MATCH(F98,'Semrush Data'!$A$2:$A$5000,0)),"") -> 11 | I98: deyga | J98: =IFERROR(INDEX('Semrush Data'!$C$2:$C$5000,MATCH(I98,'Semrush Data'!$A$2:$A$5000,0)),"") -> 140 | K98: /collections/body-lotion-for-dry-skin | L98: Deyga Neem Seed Oil | M98: Deyga Neem Seed Oil – Body Lotion for Dry Skin | Swansura | N98: =LEN(M98) -> 57 | O98: Buy Deyga Neem Seed Oil, a natural body lotion for dry skin from Deyga. Multi-Purpose Skin & Hair Care Oil – Can be used for face. Free UK delivery over £50. | P98: =LEN(O98) -> 157 | Q98: Deyga Neem Seed Oil is a natural body lotion for dry skin from Deyga. Multi-Purpose Skin & Hair Care Oil – Can be used for face care, scalp massage, spot treatment, or mixed with carrier oils for daily skincare routine. Suitable for All Skin Types – Gentle yet powerful formulation suitable for oily, dry, sensitive, and acne-prone skin without harsh chemicals. Swansura is an official UK partner of Deyga, so every order is 100% authentic and ships from the UK. | R98: deyga neem seed oil review | S98: Matched | T98: Review: source copy has medical-style claims (kept out of intro)
A99: VD-098 | B99: Deyga | C99: Under Eye Mask 15G | D99: Skincare Treatments | E99: Skin Nourishment | F99: face serum | G99: =IFERROR(INDEX('Semrush Data'!$C$2:$C$5000,MATCH(F99,'Semrush Data'!$A$2:$A$5000,0)),"") -> 9900 | H99: =IFERROR(INDEX('Semrush Data'!$D$2:$D$5000,MATCH(F99,'Semrush Data'!$A$2:$A$5000,0)),"") -> 30 | I99: deyga | J99: =IFERROR(INDEX('Semrush Data'!$C$2:$C$5000,MATCH(I99,'Semrush Data'!$A$2:$A$5000,0)),"") -> 140 | K99: /collections/face-serum | L99: Deyga Under Eye Mask | M99: Deyga Under Eye Mask | Face Serum | N99: =LEN(M99) -> 33 | O99: Buy Deyga Under Eye Mask, a natural face serum from Deyga. Official UK partner: 100% authentic, shipped from the UK, free delivery over £50. | P99: =LEN(O99) -> 140 | Q99: Deyga Under Eye Mask is a natural face serum from Deyga. Helps visibly reduce dark circles, puffiness, and under-eye fatigue by improving blood circulation and skin nourishment for a refreshed appearance. Formulated with natural Ayurvedic ingredients like almond oil, chamomile extract, olive oil, and wheat germ oil for deep hydration and skin repair. Swansura is an official UK partner of Deyga, so every order is 100% authentic and ships from the UK. | R99: deyga under eye mask review · how to use deyga under eye mask | S99: Matched | T99: Review: source copy has medical-style claims (kept out of intro)
A100: VD-099 | B100: Deyga | C100: Spirulina Matcha Face Pack 150G | D100: Skincare Treatments | E100: Skin Nourishment | F100: face serum | G100: =IFERROR(INDEX('Semrush Data'!$C$2:$C$5000,MATCH(F100,'Semrush Data'!$A$2:$A$5000,0)),"") -> 9900 | H100: =IFERROR(INDEX('Semrush Data'!$D$2:$D$5000,MATCH(F100,'Semrush Data'!$A$2:$A$5000,0)),"") -> 30 | I100: deyga | J100: =IFERROR(INDEX('Semrush Data'!$C$2:$C$5000,MATCH(I100,'Semrush Data'!$A$2:$A$5000,0)),"") -> 140 | K100: /collections/face-serum | L100: Deyga Spirulina Matcha Face Pack | M100: Deyga Spirulina Matcha Face Pack – Face Serum | Swansura | N100: =LEN(M100) -> 56 | O100: Buy Deyga Spirulina Matcha Face Pack, a natural face serum from Deyga. Official UK partner: 100% authentic, shipped from the UK, free delivery over £50. | P100: =LEN(O100) -> 152 | Q100: Deyga Spirulina Matcha Face Pack is a natural face serum from Deyga. Powerful Anti-Acne Formula – Helps reduce pimples and breakouts by detoxifying clogged pores and controlling excess sebum for clearer skin. Oil Control & Deep Cleansing – Effectively removes dirt, impurities, and excess oil without stripping natural moisture. Swansura is an official UK partner of Deyga, so every order is 100% authentic and ships from the UK. | S100: Matched | T100: Review: source copy has medical-style claims (kept out of intro)
...

Sheet Products
A1: ID | B1: Source sheet | C1: S.No | D1: Brand | E1: Brand note | F1: Category | G1: Type | H1: Concern / scent | I1: Product name | J1: Size | K1: MRP (£) | L1: Core keyword | M1: + UK | N1: Buy online | O1: Price | P1: + Concentration | Q1: Vol: Core keyword | R1: Vol: + UK | S1: Vol: Buy online | T1: Vol: Price | U1: Vol: + Concentration | V1: Primary keyword | W1: Primary volume | X1: Primary KD | Y1: Primary CPC ($) | Z1: Category / brand keywords | AA1: Google autocomplete phrases | AB1: Draft H1 | AC1: Draft meta title | AD1: Title length | AE1: Draft meta description | AF1: Description length
A2: VD-001 | B2: Vilvah & Deyga | C2: 1 | D2: Vilvah | F2: Skincare | G2: Toners | H2: Skin Nourishment | I2: Rosewater Facial Toner | J2: 100 ml | K2: 16.99 | L2: vilvah rosewater facial toner | M2: vilvah rosewater facial toner uk | N2: buy vilvah rosewater facial toner online | O2: vilvah rosewater facial toner price | Q2: =IF(L2="","",IFERROR(INDEX('Semrush Data'!$A$1:$Z$20000,MATCH(L2,'Semrush Data'!$A$1:$A$20000,0),MATCH("Volume",'Semrush Data'!$A$1:$Z$1,0)),"")) -> 0 | R2: =IF(M2="","",IFERROR(INDEX('Semrush Data'!$A$1:$Z$20000,MATCH(M2,'Semrush Data'!$A$1:$A$20000,0),MATCH("Volume",'Semrush Data'!$A$1:$Z$1,0)),"")) | S2: =IF(N2="","",IFERROR(INDEX('Semrush Data'!$A$1:$Z$20000,MATCH(N2,'Semrush Data'!$A$1:$A$20000,0),MATCH("Volume",'Semrush Data'!$A$1:$Z$1,0)),"")) | T2: =IF(O2="","",IFERROR(INDEX('Semrush Data'!$A$1:$Z$20000,MATCH(O2,'Semrush Data'!$A$1:$A$20000,0),MATCH("Volume",'Semrush Data'!$A$1:$Z$1,0)),"")) | U2: =IF(P2="","",IFERROR(INDEX('Semrush Data'!$A$1:$Z$20000,MATCH(P2,'Semrush Data'!$A$1:$A$20000,0),MATCH("Volume",'Semrush Data'!$A$1:$Z$1,0)),"")) | V2: =IF(COUNT(Q2:U2)=0,L2,IF(MAX(Q2:U2)=0,L2,INDEX(L2:P2,MATCH(MAX(Q2:U2),Q2:U2,0)))) -> vilvah rosewater facial toner | W2: =IFERROR(INDEX('Semrush Data'!$A$1:$Z$20000,MATCH(V2,'Semrush Data'!$A$1:$A$20000,0),MATCH("Volume",'Semrush Data'!$A$1:$Z$1,0)),"") -> 0 | X2: =IFERROR(INDEX('Semrush Data'!$A$1:$Z$20000,MATCH(V2,'Semrush Data'!$A$1:$A$20000,0),MATCH("Keyword Difficulty*",'Semrush Data'!$A$1:$Z$1,0)),"") -> 16 | Y2: =IFERROR(INDEX('Semrush Data'!$A$1:$Z$20000,MATCH(V2,'Semrush Data'!$A$1:$A$20000,0),MATCH("CPC*",'Semrush Data'!$A$1:$Z$1,0)),"") -> 0 | Z2: vilvah toner · toner for skin nourishment · natural toner uk | AB2: Vilvah Rosewater Facial Toner | AC2: Vilvah Rosewater Facial Toner | Buy Online UK | Swansura | AD2: =LEN(AC2) -> 56 | AE2: Buy Vilvah Rosewater Facial Toner online at Swansura, official UK partner of Vilvah. Natural toner. 100% authentic, shipped from the UK, free delivery over £50. | AF2: =LEN(AE2) -> 160
A3: VD-002 | B3: Vilvah & Deyga | C3: 2 | D3: Vilvah | F3: Haircare | G3: Hair Oil | H3: Hair Thinning & Loss | I3: Hair growth oil | J3: 50 ml | K3: 9.99 | L3: vilvah hair growth oil | M3: vilvah hair growth oil uk | N3: buy vilvah hair growth oil online | O3: vilvah hair growth oil price | Q3: =IF(L3="","",IFERROR(INDEX('Semrush Data'!$A$1:$Z$20000,MATCH(L3,'Semrush Data'!$A$1:$A$20000,0),MATCH("Volume",'Semrush Data'!$A$1:$Z$1,0)),"")) -> 20 | R3: =IF(M3="","",IFERROR(INDEX('Semrush Data'!$A$1:$Z$20000,MATCH(M3,'Semrush Data'!$A$1:$A$20000,0),MATCH("Volume",'Semrush Data'!$A$1:$Z$1,0)),"")) | S3: =IF(N3="","",IFERROR(INDEX('Semrush Data'!$A$1:$Z$20000,MATCH(N3,'Semrush Data'!$A$1:$A$20000,0),MATCH("Volume",'Semrush Data'!$A$1:$Z$1,0)),"")) | T3: =IF(O3="","",IFERROR(INDEX('Semrush Data'!$A$1:$Z$20000,MATCH(O3,'Semrush Data'!$A$1:$A$20000,0),MATCH("Volume",'Semrush Data'!$A$1:$Z$1,0)),"")) | U3: =IF(P3="","",IFERROR(INDEX('Semrush Data'!$A$1:$Z$20000,MATCH(P3,'Semrush Data'!$A$1:$A$20000,0),MATCH("Volume",'Semrush Data'!$A$1:$Z$1,0)),"")) | V3: =IF(COUNT(Q3:U3)=0,L3,IF(MAX(Q3:U3)=0,L3,INDEX(L3:P3,MATCH(MAX(Q3:U3),Q3:U3,0)))) -> vilvah hair growth oil | W3: =IFERROR(INDEX('Semrush Data'!$A$1:$Z$20000,MATCH(V3,'Semrush Data'!$A$1:$A$20000,0),MATCH("Volume",'Semrush Data'!$A$1:$Z$1,0)),"") -> 20 | X3: =IFERROR(INDEX('Semrush Data'!$A$1:$Z$20000,MATCH(V3,'Semrush Data'!$A$1:$A$20000,0),MATCH("Keyword Difficulty*",'Semrush Data'!$A$1:$Z$1,0)),"") -> 26 | Y3: =IFERROR(INDEX('Semrush Data'!$A$1:$Z$20000,MATCH(V3,'Semrush Data'!$A$1:$A$20000,0),MATCH("CPC*",'Semrush Data'!$A$1:$Z$1,0)),"") -> 0.55 | Z3: vilvah hair oil · hair oil for hair loss · natural hair oil uk | AA3: vilvah hair growth oil review · vilvah hair growth oil how to use · vilvah hair growth oil benefits · vilvah hair growth oil india · vilvah hair growth oil review before and after · vilvah hair growth oil amazon | AB3: Vilvah Hair Growth Oil | AC3: Vilvah Hair Growth Oil 50ml | Buy Online UK | Swansura | AD3: =LEN(AC3) -> 54 | AE3: Buy Vilvah Hair Growth Oil online at Swansura, official UK partner of Vilvah. A natural hair oil for thinning hair. 100% authentic, free UK delivery over £50. | AF3: =LEN(AE3) -> 158
A4: VD-003 | B4: Vilvah & Deyga | C4: 3 | D4: Vilvah | F4: Bodycare | G4: Bath & Body Wash | H4: Body Cleansing | I4: Classic Goatmilk Soap | J4: 115 g | K4: 9.99 | L4: vilvah classic goatmilk soap | M4: vilvah classic goatmilk soap uk | N4: buy vilvah classic goatmilk soap online | O4: vilvah classic goatmilk soap price | Q4: =IF(L4="","",IFERROR(INDEX('Semrush Data'!$A$1:$Z$20000,MATCH(L4,'Semrush Data'!$A$1:$A$20000,0),MATCH("Volume",'Semrush Data'!$A$1:$Z$1,0)),"")) -> 0 | R4: =IF(M4="","",IFERROR(INDEX('Semrush Data'!$A$1:$Z$20000,MATCH(M4,'Semrush Data'!$A$1:$A$20000,0),MATCH("Volume",'Semrush Data'!$A$1:$Z$1,0)),"")) | S4: =IF(N4="","",IFERROR(INDEX('Semrush Data'!$A$1:$Z$20000,MATCH(N4,'Semrush Data'!$A$1:$A$20000,0),MATCH("Volume",'Semrush Data'!$A$1:$Z$1,0)),"")) | T4: =IF(O4="","",IFERROR(INDEX('Semrush Data'!$A$1:$Z$20000,MATCH(O4,'Semrush Data'!$A$1:$A$20000,0),MATCH("Volume",'Semrush Data'!$A$1:$Z$1,0)),"")) | U4: =IF(P4="","",IFERROR(INDEX('Semrush Data'!$A$1:$Z$20000,MATCH(P4,'Semrush Data'!$A$1:$A$20000,0),MATCH("Volume",'Semrush Data'!$A$1:$Z$1,0)),"")) | V4: =IF(COUNT(Q4:U4)=0,L4,IF(MAX(Q4:U4)=0,L4,INDEX(L4:P4,MATCH(MAX(Q4:U4),Q4:U4,0)))) -> vilvah classic goatmilk soap | W4: =IFERROR(INDEX('Semrush Data'!$A$1:$Z$20000,MATCH(V4,'Semrush Data'!$A$1:$A$20000,0),MATCH("Volume",'Semrush Data'!$A$1:$Z$1,0)),"") -> 0 | X4: =IFERROR(INDEX('Semrush Data'!$A$1:$Z$20000,MATCH(V4,'Semrush Data'!$A$1:$A$20000,0),MATCH("Keyword Difficulty*",'Semrush Data'!$A$1:$Z$1,0)),"") -> 20 | Y4: =IFERROR(INDEX('Semrush Data'!$A$1:$Z$20000,MATCH(V4,'Semrush Data'!$A$1:$A$20000,0),MATCH("CPC*",'Semrush Data'!$A$1:$Z$1,0)),"") -> 0 | Z4: vilvah body wash · body wash for body cleansing · natural body wash uk | AB4: Vilvah Classic Goatmilk Soap | AC4: Vilvah Classic Goatmilk Soap | Buy Online UK | Swansura | AD4: =LEN(AC4) -> 55 | AE4: Buy Vilvah Classic Goatmilk Soap online in the UK at Swansura, official UK partner of Vilvah. Natural body wash. 100% authentic, free UK delivery over £50. | AF4: =LEN(AE4) -> 155
A5: VD-004 | B5: Vilvah & Deyga | C5: 4 | D5: Vilvah | F5: Bodycare | G5: Deodorant | H5: Body Hydration | I5: Deo Shot - Rose and Vanilla | J5: 20 g | K5: 9.99 | L5: vilvah deo shot - rose and vanilla | M5: vilvah deo shot - rose and vanilla uk | N5: buy vilvah deo shot - rose and vanilla online | O5: vilvah deo shot - rose and vanilla price | Q5: =IF(L5="","",IFERROR(INDEX('Semrush Data'!$A$1:$Z$20000,MATCH(L5,'Semrush Data'!$A$1:$A$20000,0),MATCH("Volume",'Semrush Data'!$A$1:$Z$1,0)),"")) -> 0 | R5: =IF(M5="","",IFERROR(INDEX('Semrush Data'!$A$1:$Z$20000,MATCH(M5,'Semrush Data'!$A$1:$A$20000,0),MATCH("Volume",'Semrush Data'!$A$1:$Z$1,0)),"")) | S5: =IF(N5="","",IFERROR(INDEX('Semrush Data'!$A$1:$Z$20000,MATCH(N5,'Semrush Data'!$A$1:$A$20000,0),MATCH("Volume",'Semrush Data'!$A$1:$Z$1,0)),"")) | T5: =IF(O5="","",IFERROR(INDEX('Semrush Data'!$A$1:$Z$20000,MATCH(O5,'Semrush Data'!$A$1:$A$20000,0),MATCH("Volume",'Semrush Data'!$A$1:$Z$1,0)),"")) | U5: =IF(P5="","",IFERROR(INDEX('Semrush Data'!$A$1:$Z$20000,MATCH(P5,'Semrush Data'!$A$1:$A$20000,0),MATCH("Volume",'Semrush Data'!$A$1:$Z$1,0)),"")) | V5: =IF(COUNT(Q5:U5)=0,L5,IF(MAX(Q5:U5)=0,L5,INDEX(L5:P5,MATCH(MAX(Q5:U5),Q5:U5,0)))) -> vilvah deo shot - rose and vanilla | W5: =IFERROR(INDEX('Semrush Data'!$A$1:$Z$20000,MATCH(V5,'Semrush Data'!$A$1:$A$20000,0),MATCH("Volume",'Semrush Data'!$A$1:$Z$1,0)),"") -> 0 | X5: =IFERROR(INDEX('Semrush Data'!$A$1:$Z$20000,MATCH(V5,'Semrush Data'!$A$1:$A$20000,0),MATCH("Keyword Difficulty*",'Semrush Data'!$A$1:$Z$1,0)),"") -> 18 | Y5: =IFERROR(INDEX('Semrush Data'!$A$1:$Z$20000,MATCH(V5,'Semrush Data'!$A$1:$A$20000,0),MATCH("CPC*",'Semrush Data'!$A$1:$Z$1,0)),"") -> 0 | Z5: vilvah natural deodorant · natural deodorant for body hydration · natural natural deodorant uk | AB5: Vilvah Deo Shot - Rose and Vanilla | AC5: Vilvah Deo Shot - Rose and Vanilla | Swansura UK | AD5: =LEN(AC5) -> 48 | AE5: Buy Vilvah Deo Shot - Rose and Vanilla online in the UK at Swansura, official UK partner of Vilvah. 100% authentic, shipped from the UK, free delivery over £50. | AF5: =LEN(AE5) -> 160
A6: VD-005 | B6: Vilvah & Deyga | C6: 5 | D6: Vilvah | F6: Skincare | G6: SPF for Face | H6: Sun Protection | I6: Skin finish Sunscreen SPF 50 | J6: 50ml | K6: 17.99 | L6: vilvah skin finish sunscreen spf 50 | M6: vilvah skin finish sunscreen spf 50 uk | N6: buy vilvah skin finish sunscreen spf 50 online | O6: vilvah skin finish sunscreen spf 50 price | Q6: =IF(L6="","",IFERROR(INDEX('Semrush Data'!$A$1:$Z$20000,MATCH(L6,'Semrush Data'!$A$1:$A$20000,0),MATCH("Volume",'Semrush Data'!$A$1:$Z$1,0)),"")) -> 0 | R6: =IF(M6="","",IFERROR(INDEX('Semrush Data'!$A$1:$Z$20000,MATCH(M6,'Semrush Data'!$A$1:$A$20000,0),MATCH("Volume",'Semrush Data'!$A$1:$Z$1,0)),"")) | S6: =IF(N6="","",IFERROR(INDEX('Semrush Data'!$A$1:$Z$20000,MATCH(N6,'Semrush Data'!$A$1:$A$20000,0),MATCH("Volume",'Semrush Data'!$A$1:$Z$1,0)),"")) | T6: =IF(O6="","",IFERROR(INDEX('Semrush Data'!$A$1:$Z$20000,MATCH(O6,'Semrush Data'!$A$1:$A$20000,0),MATCH("Volume",'Semrush Data'!$A$1:$Z$1,0)),"")) | U6: =IF(P6="","",IFERROR(INDEX('Semrush Data'!$A$1:$Z$20000,MATCH(P6,'Semrush Data'!$A$1:$A$20000,0),MATCH("Volume",'Semrush Data'!$A$1:$Z$1,0)),"")) | V6: =IF(COUNT(Q6:U6)=0,L6,IF(MAX(Q6:U6)=0,L6,INDEX(L6:P6,MATCH(MAX(Q6:U6),Q6:U6,0)))) -> vilvah skin finish sunscreen spf 50 | W6: =IFERROR(INDEX('Semrush Data'!$A$1:$Z$20000,MATCH(V6,'Semrush Data'!$A$1:$A$20000,0),MATCH("Volume",'Semrush Data'!$A$1:$Z$1,0)),"") -> 0 | X6: =IFERROR(INDEX('Semrush Data'!$A$1:$Z$20000,MATCH(V6,'Semrush Data'!$A$1:$A$20000,0),MATCH("Keyword Difficulty*",'Semrush Data'!$A$1:$Z$1,0)),"") -> 25 | Y6: =IFERROR(INDEX('Semrush Data'!$A$1:$Z$20000,MATCH(V6,'Semrush Data'!$A$1:$A$20000,0),MATCH("CPC*",'Semrush Data'!$A$1:$Z$1,0)),"") -> 0 | Z6: vilvah sunscreen · natural sunscreen uk | AB6: Vilvah Skin Finish Sunscreen SPF 50 | AC6: Vilvah Skin Finish Sunscreen SPF 50 | Swansura UK | AD6: =LEN(AC6) -> 49 | AE6: Buy Vilvah Skin Finish Sunscreen SPF 50 online at Swansura, official UK partner of Vilvah. Natural sunscreen. 100% authentic, free UK delivery over £50. | AF6: =LEN(AE6) -> 152
A7: VD-006 | B7: Vilvah & Deyga | C7: 6 | D7: Vilvah | F7: Skincare | G7: Cleansers | H7: Skin Nourishment | I7: Milk Powder Face Wash | J7: 50 gm | K7: 13.99 | L7: vilvah milk powder face wash | M7: vilvah milk powder face wash uk | N7: buy vilvah milk powder face wash online | O7: vilvah milk powder face wash price | Q7: =IF(L7="","",IFERROR(INDEX('Semrush Data'!$A$1:$Z$20000,MATCH(L7,'Semrush Data'!$A$1:$A$20000,0),MATCH("Volume",'Semrush Data'!$A$1:$Z$1,0)),"")) -> 20 | R7: =IF(M7="","",IFERROR(INDEX('Semrush Data'!$A$1:$Z$20000,MATCH(M7,'Semrush Data'!$A$1:$A$20000,0),MATCH("Volume",'Semrush Data'!$A$1:$Z$1,0)),"")) | S7: =IF(N7="","",IFERROR(INDEX('Semrush Data'!$A$1:$Z$20000,MATCH(N7,'Semrush Data'!$A$1:$A$20000,0),MATCH("Volume",'Semrush Data'!$A$1:$Z$1,0)),"")) | T7: =IF(O7="","",IFERROR(INDEX('Semrush Data'!$A$1:$Z$20000,MATCH(O7,'Semrush Data'!$A$1:$A$20000,0),MATCH("Volume",'Semrush Data'!$A$1:$Z$1,0)),"")) | U7: =IF(P7="","",IFERROR(INDEX('Semrush Data'!$A$1:$Z$20000,MATCH(P7,'Semrush Data'!$A$1:$A$20000,0),MATCH("Volume",'Semrush Data'!$A$1:$Z$1,0)),"")) | V7: =IF(COUNT(Q7:U7)=0,L7,IF(MAX(Q7:U7)=0,L7,INDEX(L7:P7,MATCH(MAX(Q7:U7),Q7:U7,0)))) -> vilvah milk powder face wash | W7: =IFERROR(INDEX('Semrush Data'!$A$1:$Z$20000,MATCH(V7,'Semrush Data'!$A$1:$A$20000,0),MATCH("Volume",'Semrush Data'!$A$1:$Z$1,0)),"") -> 20 | X7: =IFERROR(INDEX('Semrush Data'!$A$1:$Z$20000,MATCH(V7,'Semrush Data'!$A$1:$A$20000,0),MATCH("Keyword Difficulty*",'Semrush Data'!$A$1:$Z$1,0)),"") -> 17 | Y7: =IFERROR(INDEX('Semrush Data'!$A$1:$Z$20000,MATCH(V7,'Semrush Data'!$A$1:$A$20000,0),MATCH("CPC*",'Semrush Data'!$A$1:$Z$1,0)),"") -> 0.34 | Z7: vilvah face wash · face wash for skin nourishment · natural face wash uk | AA7: vilvah milk powder face wash review · vilvah milk powder face wash benefits · vilvah milk powder face wash price · vilvah milk powder face wash how to use · vilvah milk powder face wash and serum · vilvah milk powder face wash amazon | AB7: Vilvah Milk Powder Face Wash | AC7: Vilvah Milk Powder Face Wash | Buy Online UK | Swansura | AD7: =LEN(AC7) -> 55 | AE7: Buy Vilvah Milk Powder Face Wash online in the UK at Swansura, official UK partner of Vilvah. A natural face wash for nourished skin. Free UK delivery over £50. | AF7: =LEN(AE7) -> 160
A8: VD-007 | B8: Vilvah & Deyga | C8: 7 | D8: Vilvah | F8: Skincare | G8: Moisturisers | H8: Dry Skin | I8: Ultra Moisturising Cream | J8: 50 ml | K8: 25.99 | L8: vilvah ultra moisturising cream | M8: vilvah ultra moisturising cream uk | N8: buy vilvah ultra moisturising cream online | O8: vilvah ultra moisturising cream price | Q8: =IF(L8="","",IFERROR(INDEX('Semrush Data'!$A$1:$Z$20000,MATCH(L8,'Semrush Data'!$A$1:$A$20000,0),MATCH("Volume",'Semrush Data'!$A$1:$Z$1,0)),"")) -> 0 | R8: =IF(M8="","",IFERROR(INDEX('Semrush Data'!$A$1:$Z$20000,MATCH(M8,'Semrush Data'!$A$1:$A$20000,0),MATCH("Volume",'Semrush Data'!$A$1:$Z$1,0)),"")) | S8: =IF(N8="","",IFERROR(INDEX('Semrush Data'!$A$1:$Z$20000,MATCH(N8,'Semrush Data'!$A$1:$A$20000,0),MATCH("Volume",'Semrush Data'!$A$1:$Z$1,0)),"")) | T8: =IF(O8="","",IFERROR(INDEX('Semrush Data'!$A$1:$Z$20000,MATCH(O8,'Semrush Data'!$A$1:$A$20000,0),MATCH("Volume",'Semrush Data'!$A$1:$Z$1,0)),"")) | U8: =IF(P8="","",IFERROR(INDEX('Semrush Data'!$A$1:$Z$20000,MATCH(P8,'Semrush Data'!$A$1:$A$20000,0),MATCH("Volume",'Semrush Data'!$A$1:$Z$1,0)),"")) | V8: =IF(COUNT(Q8:U8)=0,L8,IF(MAX(Q8:U8)=0,L8,INDEX(L8:P8,MATCH(MAX(Q8:U8),Q8:U8,0)))) -> vilvah ultra moisturising cream | W8: =IFERROR(INDEX('Semrush Data'!$A$1:$Z$20000,MATCH(V8,'Semrush Data'!$A$1:$A$20000,0),MATCH("Volume",'Semrush Data'!$A$1:$Z$1,0)),"") -> 0 | X8: =IFERROR(INDEX('Semrush Data'!$A$1:$Z$20000,MATCH(V8,'Semrush Data'!$A$1:$A$20000,0),MATCH("Keyword Difficulty*",'Semrush Data'!$A$1:$Z$1,0)),"") -> 20 | Y8: =IFERROR(INDEX('Semrush Data'!$A$1:$Z$20000,MATCH(V8,'Semrush Data'!$A$1:$A$20000,0),MATCH("CPC*",'Semrush Data'!$A$1:$Z$1,0)),"") -> 0 | Z8: vilvah moisturiser · moisturiser for dry skin · natural moisturiser uk | AB8: Vilvah Ultra Moisturising Cream | AC8: Vilvah Ultra Moisturising Cream | Buy Online UK | Swansura | AD8: =LEN(AC8) -> 58 | AE8: Buy Vilvah Ultra Moisturising Cream online in the UK at Swansura, official UK partner of Vilvah. Natural moisturiser. 100% authentic, free UK delivery over £50. | AF8: =LEN(AE8) -> 160
A9: VD-008 | B9: Vilvah & Deyga | C9: 8 | D9: Vilvah | F9: Bodycare | G9: Bath & Body Wash | H9: Body Cleansing | I9: Classic Rose Goatmilk Soap | J9: 115 g | K9: 9.99 | L9: vilvah classic rose goatmilk soap | M9: vilvah classic rose goatmilk soap uk | N9: buy vilvah classic rose goatmilk soap online | O9: vilvah classic rose goatmilk soap price | Q9: =IF(L9="","",IFERROR(INDEX('Semrush Data'!$A$1:$Z$20000,MATCH(L9,'Semrush Data'!$A$1:$A$20000,0),MATCH("Volume",'Semrush Data'!$A$1:$Z$1,0)),"")) -> 0 | R9: =IF(M9="","",IFERROR(INDEX('Semrush Data'!$A$1:$Z$20000,MATCH(M9,'Semrush Data'!$A$1:$A$20000,0),MATCH("Volume",'Semrush Data'!$A$1:$Z$1,0)),"")) | S9: =IF(N9="","",IFERROR(INDEX('Semrush Data'!$A$1:$Z$20000,MATCH(N9,'Semrush Data'!$A$1:$A$20000,0),MATCH("Volume",'Semrush Data'!$A$1:$Z$1,0)),"")) | T9: =IF(O9="","",IFERROR(INDEX('Semrush Data'!$A$1:$Z$20000,MATCH(O9,'Semrush Data'!$A$1:$A$20000,0),MATCH("Volume",'Semrush Data'!$A$1:$Z$1,0)),"")) | U9: =IF(P9="","",IFERROR(INDEX('Semrush Data'!$A$1:$Z$20000,MATCH(P9,'Semrush Data'!$A$1:$A$20000,0),MATCH("Volume",'Semrush Data'!$A$1:$Z$1,0)),"")) | V9: =IF(COUNT(Q9:U9)=0,L9,IF(MAX(Q9:U9)=0,L9,INDEX(L9:P9,MATCH(MAX(Q9:U9),Q9:U9,0)))) -> vilvah classic rose goatmilk soap | W9: =IFERROR(INDEX('Semrush Data'!$A$1:$Z$20000,MATCH(V9,'Semrush Data'!$A$1:$A$20000,0),MATCH("Volume",'Semrush Data'!$A$1:$Z$1,0)),"") -> 0 | X9: =IFERROR(INDEX('Semrush Data'!$A$1:$Z$20000,MATCH(V9,'Semrush Data'!$A$1:$A$20000,0),MATCH("Keyword Difficulty*",'Semrush Data'!$A$1:$Z$1,0)),"") -> 12 | Y9: =IFERROR(INDEX('Semrush Data'!$A$1:$Z$20000,MATCH(V9,'Semrush Data'!$A$1:$A$20000,0),MATCH("CPC*",'Semrush Data'!$A$1:$Z$1,0)),"") -> 0 | Z9: vilvah body wash · body wash for body cleansing · natural body wash uk | AB9: Vilvah Classic Rose Goatmilk Soap | AC9: Vilvah Classic Rose Goatmilk Soap | Buy Online UK | Swansura | AD9: =LEN(AC9) -> 60 | AE9: Buy Vilvah Classic Rose Goatmilk Soap online in the UK at Swansura, official UK partner of Vilvah. Natural body wash. 100% authentic, free UK delivery over £50. | AF9: =LEN(AE9) -> 160
A10: VD-009 | B10: Vilvah & Deyga | C10: 9 | D10: Vilvah | F10: Bodycare | G10: Bath & Body Wash | H10: Body Cleansing | I10: Goat Milk Body Wash | J10: 200 ml | K10: 15.99 | L10: vilvah goat milk body wash | M10: vilvah goat milk body wash uk | N10: buy vilvah goat milk body wash online | O10: vilvah goat milk body wash price | Q10: =IF(L10="","",IFERROR(INDEX('Semrush Data'!$A$1:$Z$20000,MATCH(L10,'Semrush Data'!$A$1:$A$20000,0),MATCH("Volume",'Semrush Data'!$A$1:$Z$1,0)),"")) -> 0 | R10: =IF(M10="","",IFERROR(INDEX('Semrush Data'!$A$1:$Z$20000,MATCH(M10,'Semrush Data'!$A$1:$A$20000,0),MATCH("Volume",'Semrush Data'!$A$1:$Z$1,0)),"")) | S10: =IF(N10="","",IFERROR(INDEX('Semrush Data'!$A$1:$Z$20000,MATCH(N10,'Semrush Data'!$A$1:$A$20000,0),MATCH("Volume",'Semrush Data'!$A$1:$Z$1,0)),"")) | T10: =IF(O10="","",IFERROR(INDEX('Semrush Data'!$A$1:$Z$20000,MATCH(O10,'Semrush Data'!$A$1:$A$20000,0),MATCH("Volume",'Semrush Data'!$A$1:$Z$1,0)),"")) | U10: =IF(P10="","",IFERROR(INDEX('Semrush Data'!$A$1:$Z$20000,MATCH(P10,'Semrush Data'!$A$1:$A$20000,0),MATCH("Volume",'Semrush Data'!$A$1:$Z$1,0)),"")) | V10: =IF(COUNT(Q10:U10)=0,L10,IF(MAX(Q10:U10)=0,L10,INDEX(L10:P10,MATCH(MAX(Q10:U10),Q10:U10,0)))) -> vilvah goat milk body wash | W10: =IFERROR(INDEX('Semrush Data'!$A$1:$Z$20000,MATCH(V10,'Semrush Data'!$A$1:$A$20000,0),MATCH("Volume",'Semrush Data'!$A$1:$Z$1,0)),"") -> 0 | X10: =IFERROR(INDEX('Semrush Data'!$A$1:$Z$20000,MATCH(V10,'Semrush Data'!$A$1:$A$20000,0),MATCH("Keyword Difficulty*",'Semrush Data'!$A$1:$Z$1,0)),"") -> 11 | Y10: =IFERROR(INDEX('Semrush Data'!$A$1:$Z$20000,MATCH(V10,'Semrush Data'!$A$1:$A$20000,0),MATCH("CPC*",'Semrush Data'!$A$1:$Z$1,0)),"") -> 0 | Z10: vilvah body wash · body wash for body cleansing · natural body wash uk | AA10: vilvah goat milk body wash review · vilvah goat milk body wash ingredients · vilvah goat milk body wash benefits · vilvah goat milk body soap · vilvah goat milk soap review | AB10: Vilvah Goat Milk Body Wash | AC10: Vilvah Goat Milk Body Wash | Buy Online UK | Swansura | AD10: =LEN(AC10) -> 53 | AE10: Buy Vilvah Goat Milk Body Wash online in the UK at Swansura, official UK partner of Vilvah. Natural body wash. 100% authentic, free UK delivery over £50. | AF10: =LEN(AE10) -> 153
A11: VD-010 | B11: Vilvah & Deyga | C11: 10 | D11: Vilvah | F11: Skincare | G11: Lip Care | H11: Dry Lips | I11: Rose Milk Lip Balm | J11: 10 g | K11: 9.99 | L11: vilvah rose milk lip balm | M11: vilvah rose milk lip balm uk | N11: buy vilvah rose milk lip balm online | O11: vilvah rose milk lip balm price | Q11: =IF(L11="","",IFERROR(INDEX('Semrush Data'!$A$1:$Z$20000,MATCH(L11,'Semrush Data'!$A$1:$A$20000,0),MATCH("Volume",'Semrush Data'!$A$1:$Z$1,0)),"")) -> 0 | R11: =IF(M11="","",IFERROR(INDEX('Semrush Data'!$A$1:$Z$20000,MATCH(M11,'Semrush Data'!$A$1:$A$20000,0),MATCH("Volume",'Semrush Data'!$A$1:$Z$1,0)),"")) | S11: =IF(N11="","",IFERROR(INDEX('Semrush Data'!$A$1:$Z$20000,MATCH(N11,'Semrush Data'!$A$1:$A$20000,0),MATCH("Volume",'Semrush Data'!$A$1:$Z$1,0)),"")) | T11: =IF(O11="","",IFERROR(INDEX('Semrush Data'!$A$1:$Z$20000,MATCH(O11,'Semrush Data'!$A$1:$A$20000,0),MATCH("Volume",'Semrush Data'!$A$1:$Z$1,0)),"")) | U11: =IF(P11="","",IFERROR(INDEX('Semrush Data'!$A$1:$Z$20000,MATCH(P11,'Semrush Data'!$A$1:$A$20000,0),MATCH("Volume",'Semrush Data'!$A$1:$Z$1,0)),"")) | V11: =IF(COUNT(Q11:U11)=0,L11,IF(MAX(Q11:U11)=0,L11,INDEX(L11:P11,MATCH(MAX(Q11:U11),Q11:U11,0)))) -> vilvah rose milk lip balm | W11: =IFERROR(INDEX('Semrush Data'!$A$1:$Z$20000,MATCH(V11,'Semrush Data'!$A$1:$A$20000,0),MATCH("Volume",'Semrush Data'!$A$1:$Z$1,0)),"") -> 0 | X11: =IFERROR(INDEX('Semrush Data'!$A$1:$Z$20000,MATCH(V11,'Semrush Data'!$A$1:$A$20000,0),MATCH("Keyword Difficulty*",'Semrush Data'!$A$1:$Z$1,0)),"") -> 22 | Y11: =IFERROR(INDEX('Semrush Data'!$A$1:$Z$20000,MATCH(V11,'Semrush Data'!$A$1:$A$20000,0),MATCH("CPC*",'Semrush Data'!$A$1:$Z$1,0)),"") -> 0 | Z11: vilvah lip balm · lip balm for dry lips · natural lip balm uk | AA11: vilvah rose milk lip balm review · vilvah rose milk lip balm ingredients · vilvah rose milk lip balm price · vilvah lip balm review · vilvah lip balm price | AB11: Vilvah Rose Milk Lip Balm | AC11: Vilvah Rose Milk Lip Balm | Buy Online UK | Swansura | AD11: =LEN(AC11) -> 52 | AE11: Buy Vilvah Rose Milk Lip Balm online at Swansura, official UK partner of Vilvah. Natural lip care. 100% authentic, shipped from the UK, free delivery over £50. | AF11: =LEN(AE11) -> 159
A12: VD-011 | B12: Vilvah & Deyga | C12: 11 | D12: Vilvah | F12: Bodycare | G12: Bath & Body Wash | H12: Body Cleansing | I12: Charcoal Goatmilk Soap | J12: 115 g | K12: 9.99 | L12: vilvah charcoal goatmilk soap | M12: vilvah charcoal goatmilk soap uk | N12: buy vilvah charcoal goatmilk soap online | O12: vilvah charcoal goatmilk soap price | Q12: =IF(L12="","",IFERROR(INDEX('Semrush Data'!$A$1:$Z$20000,MATCH(L12,'Semrush Data'!$A$1:$A$20000,0),MATCH("Volume",'Semrush Data'!$A$1:$Z$1,0)),"")) -> 0 | R12: =IF(M12="","",IFERROR(INDEX('Semrush Data'!$A$1:$Z$20000,MATCH(M12,'Semrush Data'!$A$1:$A$20000,0),MATCH("Volume",'Semrush Data'!$A$1:$Z$1,0)),"")) | S12: =IF(N12="","",IFERROR(INDEX('Semrush Data'!$A$1:$Z$20000,MATCH(N12,'Semrush Data'!$A$1:$A$20000,0),MATCH("Volume",'Semrush Data'!$A$1:$Z$1,0)),"")) | T12: =IF(O12="","",IFERROR(INDEX('Semrush Data'!$A$1:$Z$20000,MATCH(O12,'Semrush Data'!$A$1:$A$20000,0),MATCH("Volume",'Semrush Data'!$A$1:$Z$1,0)),"")) | U12: =IF(P12="","",IFERROR(INDEX('Semrush Data'!$A$1:$Z$20000,MATCH(P12,'Semrush Data'!$A$1:$A$20000,0),MATCH("Volume",'Semrush Data'!$A$1:$Z$1,0)),"")) | V12: =IF(COUNT(Q12:U12)=0,L12,IF(MAX(Q12:U12)=0,L12,INDEX(L12:P12,MATCH(MAX(Q12:U12),Q12:U12,0)))) -> vilvah charcoal goatmilk soap | W12: =IFERROR(INDEX('Semrush Data'!$A$1:$Z$20000,MATCH(V12,'Semrush Data'!$A$1:$A$20000,0),MATCH("Volume",'Semrush Data'!$A$1:$Z$1,0)),"") -> 0 | X12: =IFERROR(INDEX('Semrush Data'!$A$1:$Z$20000,MATCH(V12,'Semrush Data'!$A$1:$A$20000,0),MATCH("Keyword Difficulty*",'Semrush Data'!$A$1:$Z$1,0)),"") -> 20 | Y12: =IFERROR(INDEX('Semrush Data'!$A$1:$Z$20000,MATCH(V12,'Semrush Data'!$A$1:$A$20000,0),MATCH("CPC*",'Semrush Data'!$A$1:$Z$1,0)),"") -> 0 | Z12: vilvah body wash · body wash for body cleansing · natural body wash uk | AB12: Vilvah Charcoal Goatmilk Soap | AC12: Vilvah Charcoal Goatmilk Soap | Buy Online UK | Swansura | AD12: =LEN(AC12) -> 56 | AE12: Buy Vilvah Charcoal Goatmilk Soap online in the UK at Swansura, official UK partner of Vilvah. Natural body wash. 100% authentic, free UK delivery over £50. | AF12: =LEN(AE12) -> 156
A13: VD-012 | B13: Vilvah & Deyga | C13: 12 | D13: Vilvah | F13: Haircare | G13: Conditioner | H13: Hair Nourishment | I13: Cream Conditioner | J13: 250 ml | K13: 15.99 | L13: vilvah cream conditioner | M13: vilvah cream conditioner uk | N13: buy vilvah cream conditioner online | O13: vilvah cream conditioner price | Q13: =IF(L13="","",IFERROR(INDEX('Semrush Data'!$A$1:$Z$20000,MATCH(L13,'Semrush Data'!$A$1:$A$20000,0),MATCH("Volume",'Semrush Data'!$A$1:$Z$1,0)),"")) -> 10 | R13: =IF(M13="","",IFERROR(INDEX('Semrush Data'!$A$1:$Z$20000,MATCH(M13,'Semrush Data'!$A$1:$A$20000,0),MATCH("Volume",'Semrush Data'!$A$1:$Z$1,0)),"")) | S13: =IF(N13="","",IFERROR(INDEX('Semrush Data'!$A$1:$Z$20000,MATCH(N13,'Semrush Data'!$A$1:$A$20000,0),MATCH("Volume",'Semrush Data'!$A$1:$Z$1,0)),"")) | T13: =IF(O13="","",IFERROR(INDEX('Semrush Data'!$A$1:$Z$20000,MATCH(O13,'Semrush Data'!$A$1:$A$20000,0),MATCH("Volume",'Semrush Data'!$A$1:$Z$1,0)),"")) | U13: =IF(P13="","",IFERROR(INDEX('Semrush Data'!$A$1:$Z$20000,MATCH(P13,'Semrush Data'!$A$1:$A$20000,0),MATCH("Volume",'Semrush Data'!$A$1:$Z$1,0)),"")) | V13: =IF(COUNT(Q13:U13)=0,L13,IF(MAX(Q13:U13)=0,L13,INDEX(L13:P13,MATCH(MAX(Q13:U13),Q13:U13,0)))) -> vilvah cream conditioner | W13: =IFERROR(INDEX('Semrush Data'!$A$1:$Z$20000,MATCH(V13,'Semrush Data'!$A$1:$A$20000,0),MATCH("Volume",'Semrush Data'!$A$1:$Z$1,0)),"") -> 10 | X13: =IFERROR(INDEX('Semrush Data'!$A$1:$Z$20000,MATCH(V13,'Semrush Data'!$A$1:$A$20000,0),MATCH("Keyword Difficulty*",'Semrush Data'!$A$1:$Z$1,0)),"") -> 16 | Y13: =IFERROR(INDEX('Semrush Data'!$A$1:$Z$20000,MATCH(V13,'Semrush Data'!$A$1:$A$20000,0),MATCH("CPC*",'Semrush Data'!$A$1:$Z$1,0)),"") -> 0 | Z13: vilvah conditioner · conditioner for hair nourishment · natural conditioner uk | AA13: vilvah cream conditioner review · vilvah cream conditioner ingredients · how to use vilvah cream conditioner · vilvah conditioner review | AB13: Vilvah Cream Conditioner | AC13: Vilvah Cream Conditioner | Buy Online UK | Swansura | AD13: =LEN(AC13) -> 51 | AE13: Buy Vilvah Cream Conditioner online in the UK at Swansura, official UK partner of Vilvah. A natural conditioner for nourished hair. Free UK delivery over £50. | AF13: =LEN(AE13) -> 158
A14: VD-013 | B14: Vilvah & Deyga | C14: 13 | D14: Vilvah | F14: Haircare | G14: Shampoo | H14: Dry Skin | I14: Goat Milk Shampoo | J14: 250 ml | K14: 15.99 | L14: vilvah goat milk shampoo | M14: vilvah goat milk shampoo uk | N14: buy vilvah goat milk shampoo online | O14: vilvah goat milk shampoo price | Q14: =IF(L14="","",IFERROR(INDEX('Semrush Data'!$A$1:$Z$20000,MATCH(L14,'Semrush Data'!$A$1:$A$20000,0),MATCH("Volume",'Semrush Data'!$A$1:$Z$1,0)),"")) -> 20 | R14: =IF(M14="","",IFERROR(INDEX('Semrush Data'!$A$1:$Z$20000,MATCH(M14,'Semrush Data'!$A$1:$A$20000,0),MATCH("Volume",'Semrush Data'!$A$1:$Z$1,0)),"")) | S14: =IF(N14="","",IFERROR(INDEX('Semrush Data'!$A$1:$Z$20000,MATCH(N14,'Semrush Data'!$A$1:$A$20000,0),MATCH("Volume",'Semrush Data'!$A$1:$Z$1,0)),"")) | T14: =IF(O14="","",IFERROR(INDEX('Semrush Data'!$A$1:$Z$20000,MATCH(O14,'Semrush Data'!$A$1:$A$20000,0),MATCH("Volume",'Semrush Data'!$A$1:$Z$1,0)),"")) | U14: =IF(P14="","",IFERROR(INDEX('Semrush Data'!$A$1:$Z$20000,MATCH(P14,'Semrush Data'!$A$1:$A$20000,0),MATCH("Volume",'Semrush Data'!$A$1:$Z$1,0)),"")) | V14: =IF(COUNT(Q14:U14)=0,L14,IF(MAX(Q14:U14)=0,L14,INDEX(L14:P14,MATCH(MAX(Q14:U14),Q14:U14,0)))) -> vilvah goat milk shampoo | W14: =IFERROR(INDEX('Semrush Data'!$A$1:$Z$20000,MATCH(V14,'Semrush Data'!$A$1:$A$20000,0),MATCH("Volume",'Semrush Data'!$A$1:$Z$1,0)),"") -> 20 | X14: =IFERROR(INDEX('Semrush Data'!$A$1:$Z$20000,MATCH(V14,'Semrush Data'!$A$1:$A$20000,0),MATCH("Keyword Difficulty*",'Semrush Data'!$A$1:$Z$1,0)),"") -> 9 | Y14: =IFERROR(INDEX('Semrush Data'!$A$1:$Z$20000,MATCH(V14,'Semrush Data'!$A$1:$A$20000,0),MATCH("CPC*",'Semrush Data'!$A$1:$Z$1,0)),"") -> 0.3 | Z14: vilvah shampoo · shampoo for dry skin · natural shampoo uk | AA14: vilvah goat milk shampoo review · vilvah goat milk shampoo price · vilvah goat milk shampoo benefits · vilvah goat milk shampoo ingredients | AB14: Vilvah Goat Milk Shampoo | AC14: Vilvah Goat Milk Shampoo | Buy Online UK | Swansura | AD14: =LEN(AC14) -> 51 | AE14: Buy Vilvah Goat Milk Shampoo online at Swansura, official UK partner of Vilvah. Natural shampoo. 100% authentic, shipped from the UK, free delivery over £50. | AF14: =LEN(AE14) -> 157
A15: VD-014 | B15: Vilvah & Deyga | C15: 14 | D15: Vilvah | F15: Skincare | G15: Cleansers | H15: Skin Nourishment | I15: Honey Fix Face Wash | J15: 100 ml | K15: 12.99 | L15: vilvah honey fix face wash | M15: vilvah honey fix face wash uk | N15: buy vilvah honey fix face wash online | O15: vilvah honey fix face wash price | Q15: =IF(L15="","",IFERROR(INDEX('Semrush Data'!$A$1:$Z$20000,MATCH(L15,'Semrush Data'!$A$1:$A$20000,0),MATCH("Volume",'Semrush Data'!$A$1:$Z$1,0)),"")) -> 0 | R15: =IF(M15="","",IFERROR(INDEX('Semrush Data'!$A$1:$Z$20000,MATCH(M15,'Semrush Data'!$A$1:$A$20000,0),MATCH("Volume",'Semrush Data'!$A$1:$Z$1,0)),"")) | S15: =IF(N15="","",IFERROR(INDEX('Semrush Data'!$A$1:$Z$20000,MATCH(N15,'Semrush Data'!$A$1:$A$20000,0),MATCH("Volume",'Semrush Data'!$A$1:$Z$1,0)),"")) | T15: =IF(O15="","",IFERROR(INDEX('Semrush Data'!$A$1:$Z$20000,MATCH(O15,'Semrush Data'!$A$1:$A$20000,0),MATCH("Volume",'Semrush Data'!$A$1:$Z$1,0)),"")) | U15: =IF(P15="","",IFERROR(INDEX('Semrush Data'!$A$1:$Z$20000,MATCH(P15,'Semrush Data'!$A$1:$A$20000,0),MATCH("Volume",'Semrush Data'!$A$1:$Z$1,0)),"")) | V15: =IF(COUNT(Q15:U15)=0,L15,IF(MAX(Q15:U15)=0,L15,INDEX(L15:P15,MATCH(MAX(Q15:U15),Q15:U15,0)))) -> vilvah honey fix face wash | W15: =IFERROR(INDEX('Semrush Data'!$A$1:$Z$20000,MATCH(V15,'Semrush Data'!$A$1:$A$20000,0),MATCH("Volume",'Semrush Data'!$A$1:$Z$1,0)),"") -> 0 | X15: =IFERROR(INDEX('Semrush Data'!$A$1:$Z$20000,MATCH(V15,'Semrush Data'!$A$1:$A$20000,0),MATCH("Keyword Difficulty*",'Semrush Data'!$A$1:$Z$1,0)),"") -> 23 | Y15: =IFERROR(INDEX('Semrush Data'!$A$1:$Z$20000,MATCH(V15,'Semrush Data'!$A$1:$A$20000,0),MATCH("CPC*",'Semrush Data'!$A$1:$Z$1,0)),"") -> 0 | Z15: vilvah face wash · face wash for skin nourishment · natural face wash uk | AA15: vilvah honey fix face wash review | AB15: Vilvah Honey Fix Face Wash | AC15: Vilvah Honey Fix Face Wash | Buy Online UK | Swansura | AD15: =LEN(AC15) -> 53 | AE15: Buy Vilvah Honey Fix Face Wash online in the UK at Swansura, official UK partner of Vilvah. A natural face wash for nourished skin. Free UK delivery over £50. | AF15: =LEN(AE15) -> 158
A16: VD-015 | B16: Vilvah & Deyga | C16: 15 | D16: Vilvah | F16: Skincare | G16: Lip Care | H16: Dry Lips | I16: Lip Balm - Lemon | J16: 10 g | K16: 6.99 | L16: vilvah lip balm - lemon | M16: vilvah lip balm - lemon uk | N16: buy vilvah lip balm - lemon online | O16: vilvah lip balm - lemon price | Q16: =IF(L16="","",IFERROR(INDEX('Semrush Data'!$A$1:$Z$20000,MATCH(L16,'Semrush Data'!$A$1:$A$20000,0),MATCH("Volume",'Semrush Data'!$A$1:$Z$1,0)),"")) -> 0 | R16: =IF(M16="","",IFERROR(INDEX('Semrush Data'!$A$1:$Z$20000,MATCH(M16,'Semrush Data'!$A$1:$A$20000,0),MATCH("Volume",'Semrush Data'!$A$1:$Z$1,0)),"")) | S16: =IF(N16="","",IFERROR(INDEX('Semrush Data'!$A$1:$Z$20000,MATCH(N16,'Semrush Data'!$A$1:$A$20000,0),MATCH("Volume",'Semrush Data'!$A$1:$Z$1,0)),"")) | T16: =IF(O16="","",IFERROR(INDEX('Semrush Data'!$A$1:$Z$20000,MATCH(O16,'Semrush Data'!$A$1:$A$20000,0),MATCH("Volume",'Semrush Data'!$A$1:$Z$1,0)),"")) | U16: =IF(P16="","",IFERROR(INDEX('Semrush Data'!$A$1:$Z$20000,MATCH(P16,'Semrush Data'!$A$1:$A$20000,0),MATCH("Volume",'Semrush Data'!$A$1:$Z$1,0)),"")) | V16: =IF(COUNT(Q16:U16)=0,L16,IF(MAX(Q16:U16)=0,L16,INDEX(L16:P16,MATCH(MAX(Q16:U16),Q16:U16,0)))) -> vilvah lip balm - lemon | W16: =IFERROR(INDEX('Semrush Data'!$A$1:$Z$20000,MATCH(V16,'Semrush Data'!$A$1:$A$20000,0),MATCH("Volume",'Semrush Data'!$A$1:$Z$1,0)),"") -> 0 | X16: =IFERROR(INDEX('Semrush Data'!$A$1:$Z$20000,MATCH(V16,'Semrush Data'!$A$1:$A$20000,0),MATCH("Keyword Difficulty*",'Semrush Data'!$A$1:$Z$1,0)),"") -> 28 | Y16: =IFERROR(INDEX('Semrush Data'!$A$1:$Z$20000,MATCH(V16,'Semrush Data'!$A$1:$A$20000,0),MATCH("CPC*",'Semrush Data'!$A$1:$Z$1,0)),"") -> 0 | Z16: vilvah lip balm · lip balm for dry lips · natural lip balm uk | AA16: vilvah lip balm lemon · vilvah lemon lip balm review · vilvah lip balm review · vilvah lip balm price | AB16: Vilvah Lip Balm - Lemon | AC16: Vilvah Lip Balm - Lemon | Buy Online UK | Swansura | AD16: =LEN(AC16) -> 50 | AE16: Buy Vilvah Lip Balm - Lemon online at Swansura, official UK partner of Vilvah. Natural lip care. 100% authentic, shipped from the UK, free delivery over £50. | AF16: =LEN(AE16) -> 157
A17: VD-016 | B17: Vilvah & Deyga | C17: 16 | D17: Vilvah | F17: Bodycare | G17: Body Cream & Lotions | H17: Dry Skin | I17: Milk Body Lotion | J17: 250 ml | K17: 25.99 | L17: vilvah milk body lotion | M17: vilvah milk body lotion uk | N17: buy vilvah milk body lotion online | O17: vilvah milk body lotion price | Q17: =IF(L17="","",IFERROR(INDEX('Semrush Data'!$A$1:$Z$20000,MATCH(L17,'Semrush Data'!$A$1:$A$20000,0),MATCH("Volume",'Semrush Data'!$A$1:$Z$1,0)),"")) -> 10 | R17: =IF(M17="","",IFERROR(INDEX('Semrush Data'!$A$1:$Z$20000,MATCH(M17,'Semrush Data'!$A$1:$A$20000,0),MATCH("Volume",'Semrush Data'!$A$1:$Z$1,0)),"")) | S17: =IF(N17="","",IFERROR(INDEX('Semrush Data'!$A$1:$Z$20000,MATCH(N17,'Semrush Data'!$A$1:$A$20000,0),MATCH("Volume",'Semrush Data'!$A$1:$Z$1,0)),"")) | T17: =IF(O17="","",IFERROR(INDEX('Semrush Data'!$A$1:$Z$20000,MATCH(O17,'Semrush Data'!$A$1:$A$20000,0),MATCH("Volume",'Semrush Data'!$A$1:$Z$1,0)),"")) | U17: =IF(P17="","",IFERROR(INDEX('Semrush Data'!$A$1:$Z$20000,MATCH(P17,'Semrush Data'!$A$1:$A$20000,0),MATCH("Volume",'Semrush Data'!$A$1:$Z$1,0)),"")) | V17: =IF(COUNT(Q17:U17)=0,L17,IF(MAX(Q17:U17)=0,L17,INDEX(L17:P17,MATCH(MAX(Q17:U17),Q17:U17,0)))) -> vilvah milk body lotion | W17: =IFERROR(INDEX('Semrush Data'!$A$1:$Z$20000,MATCH(V17,'Semrush Data'!$A$1:$A$20000,0),MATCH("Volume",'Semrush Data'!$A$1:$Z$1,0)),"") -> 10 | X17: =IFERROR(INDEX('Semrush Data'!$A$1:$Z$20000,MATCH(V17,'Semrush Data'!$A$1:$A$20000,0),MATCH("Keyword Difficulty*",'Semrush Data'!$A$1:$Z$1,0)),"") -> 7 | Y17: =IFERROR(INDEX('Semrush Data'!$A$1:$Z$20000,MATCH(V17,'Semrush Data'!$A$1:$A$20000,0),MATCH("CPC*",'Semrush Data'!$A$1:$Z$1,0)),"") -> 0 | Z17: vilvah body lotion · body lotion for dry skin · natural body lotion uk | AA17: vilvah milk body lotion review · vilvah milk body lotion price | AB17: Vilvah Milk Body Lotion | AC17: Vilvah Milk Body Lotion | Buy Online UK | Swansura | AD17: =LEN(AC17) -> 50 | AE17: Buy Vilvah Milk Body Lotion online at Swansura, official UK partner of Vilvah. Natural body lotion. 100% authentic, shipped from the UK, free delivery over £50. | AF17: =LEN(AE17) -> 160
A18: VD-017 | B18: Vilvah & Deyga | C18: 17 | D18: Vilvah | F18: Skincare | G18: Toners | H18: Dry Skin | I18: Milk Face Toner | J18: 100 ml | K18: 19.99 | L18: vilvah milk face toner | M18: vilvah milk face toner uk | N18: buy vilvah milk face toner online | O18: vilvah milk face toner price | Q18: =IF(L18="","",IFERROR(INDEX('Semrush Data'!$A$1:$Z$20000,MATCH(L18,'Semrush Data'!$A$1:$A$20000,0),MATCH("Volume",'Semrush Data'!$A$1:$Z$1,0)),"")) -> 0 | R18: =IF(M18="","",IFERROR(INDEX('Semrush Data'!$A$1:$Z$20000,MATCH(M18,'Semrush Data'!$A$1:$A$20000,0),MATCH("Volume",'Semrush Data'!$A$1:$Z$1,0)),"")) | S18: =IF(N18="","",IFERROR(INDEX('Semrush Data'!$A$1:$Z$20000,MATCH(N18,'Semrush Data'!$A$1:$A$20000,0),MATCH("Volume",'Semrush Data'!$A$1:$Z$1,0)),"")) | T18: =IF(O18="","",IFERROR(INDEX('Semrush Data'!$A$1:$Z$20000,MATCH(O18,'Semrush Data'!$A$1:$A$20000,0),MATCH("Volume",'Semrush Data'!$A$1:$Z$1,0)),"")) | U18: =IF(P18="","",IFERROR(INDEX('Semrush Data'!$A$1:$Z$20000,MATCH(P18,'Semrush Data'!$A$1:$A$20000,0),MATCH("Volume",'Semrush Data'!$A$1:$Z$1,0)),"")) | V18: =IF(COUNT(Q18:U18)=0,L18,IF(MAX(Q18:U18)=0,L18,INDEX(L18:P18,MATCH(MAX(Q18:U18),Q18:U18,0)))) -> vilvah milk face toner | W18: =IFERROR(INDEX('Semrush Data'!$A$1:$Z$20000,MATCH(V18,'Semrush Data'!$A$1:$A$20000,0),MATCH("Volume",'Semrush Data'!$A$1:$Z$1,0)),"") -> 0 | X18: =IFERROR(INDEX('Semrush Data'!$A$1:$Z$20000,MATCH(V18,'Semrush Data'!$A$1:$A$20000,0),MATCH("Keyword Difficulty*",'Semrush Data'!$A$1:$Z$1,0)),"") -> 20 | Y18: =IFERROR(INDEX('Semrush Data'!$A$1:$Z$20000,MATCH(V18,'Semrush Data'!$A$1:$A$20000,0),MATCH("CPC*",'Semrush Data'!$A$1:$Z$1,0)),"") -> 0 | Z18: vilvah toner · toner for dry skin · natural toner uk | AA18: vilvah milk face toner review · vilvah toner review | AB18: Vilvah Milk Face Toner | AC18: Vilvah Milk Face Toner 100ml | Buy Online UK | Swansura | AD18: =LEN(AC18) -> 55 | AE18: Buy Vilvah Milk Face Toner online in the UK at Swansura, official UK partner of Vilvah. A natural toner for dry skin. 100% authentic, free UK delivery over £50. | AF18: =LEN(AE18) -> 160
A19: VD-018 | B19: Vilvah & Deyga | C19: 18 | D19: Vilvah | F19: Skincare | G19: Face Masks | H19: Skin Nourishment | I19: Milk Mud Mask | J19: 50 ml | K19: 19.99 | L19: vilvah milk mud mask | M19: vilvah milk mud mask uk | N19: buy vilvah milk mud mask online | O19: vilvah milk mud mask price | Q19: =IF(L19="","",IFERROR(INDEX('Semrush Data'!$A$1:$Z$20000,MATCH(L19,'Semrush Data'!$A$1:$A$20000,0),MATCH("Volume",'Semrush Data'!$A$1:$Z$1,0)),"")) -> 20 | R19: =IF(M19="","",IFERROR(INDEX('Semrush Data'!$A$1:$Z$20000,MATCH(M19,'Semrush Data'!$A$1:$A$20000,0),MATCH("Volume",'Semrush Data'!$A$1:$Z$1,0)),"")) | S19: =IF(N19="","",IFERROR(INDEX('Semrush Data'!$A$1:$Z$20000,MATCH(N19,'Semrush Data'!$A$1:$A$20000,0),MATCH("Volume",'Semrush Data'!$A$1:$Z$1,0)),"")) | T19: =IF(O19="","",IFERROR(INDEX('Semrush Data'!$A$1:$Z$20000,MATCH(O19,'Semrush Data'!$A$1:$A$20000,0),MATCH("Volume",'Semrush Data'!$A$1:$Z$1,0)),"")) | U19: =IF(P19="","",IFERROR(INDEX('Semrush Data'!$A$1:$Z$20000,MATCH(P19,'Semrush Data'!$A$1:$A$20000,0),MATCH("Volume",'Semrush Data'!$A$1:$Z$1,0)),"")) | V19: =IF(COUNT(Q19:U19)=0,L19,IF(MAX(Q19:U19)=0,L19,INDEX(L19:P19,MATCH(MAX(Q19:U19),Q19:U19,0)))) -> vilvah milk mud mask | W19: =IFERROR(INDEX('Semrush Data'!$A$1:$Z$20000,MATCH(V19,'Semrush Data'!$A$1:$A$20000,0),MATCH("Volume",'Semrush Data'!$A$1:$Z$1,0)),"") -> 20 | X19: =IFERROR(INDEX('Semrush Data'!$A$1:$Z$20000,MATCH(V19,'Semrush Data'!$A$1:$A$20000,0),MATCH("Keyword Difficulty*",'Semrush Data'!$A$1:$Z$1,0)),"") -> 10 | Y19: =IFERROR(INDEX('Semrush Data'!$A$1:$Z$20000,MATCH(V19,'Semrush Data'!$A$1:$A$20000,0),MATCH("CPC*",'Semrush Data'!$A$1:$Z$1,0)),"") -> 0 | Z19: vilvah face mask · face mask for skin nourishment · natural face mask uk | AA19: vilvah milk mud mask review · vilvah milk mud mask benefits · vilvah milk mud mask ingredients · vilvah milk mud mask how to use · vilvah milk mud mask amazon · vilvah milk mud mask price | AB19: Vilvah Milk Mud Mask | AC19: Vilvah Milk Mud Mask 50ml | Buy Online UK | Swansura | AD19: =LEN(AC19) -> 52 | AE19: Buy Vilvah Milk Mud Mask online at Swansura, official UK partner of Vilvah. A natural face mask for nourished skin. 100% authentic, free UK delivery over £50. | AF19: =LEN(AE19) -> 158
